Workbook

Sheet Claude Log
A1: Turn # | B1: Date | C1: User Request | D1: Action Taken | E1: Details | F1: Outcome
A2: 1 | B2: 46091 | C2: Construire un simulateur Pilier 2 GloBE complet (8 onglets) : Structure Groupe, P&L GloBE, Impôts Couverts, ETR Juridictionnel, Substance Carve-out, Top-up Tax, Safe Harbours, Déclaration GIR. Proposer des améliorations. | D2: Créé 8 onglets entièrement liés par formules cross-sheet. Groupe fictif (holding FR + 6 entités). Données fictives illustratives (en k€). Arbre de décision Safe Harbours automatisé. Maquette GIR OCDE pré-remplie. | E2: Formules : ETR = Covered Taxes / GloBE Income, Top-up = MAX(0, 15%−ETR) × Excess Profit, SBIE transitoire 2026 (8.6% salaires, 7.0% immo). MFC rouge si ETR < 15%. IIR via UPE (FR-HQ). 3 tests Safe Harbour (de minimis, ETR simplifié, profit routine). Toutes données en bleu = inputs modifiables. | F2: Résultat : IE (ETR 10.46%) et MU (ETR 11.88%) sous le seuil → Top-up Tax brut ~1 220 k€. Après Safe Harbours : MU qualifiée (de minimis), IE non qualifiée → Top-up final ~1 017 k€ uniquement sur IE via IIR.

Sheet 1 — Structure Groupe
A1: 0.01
A2: Directive (UE) 2022/2523 — Pilier 2 GloBE | IIR : exercices ouverts ≥ 31/12/2024 | UTPR : 2025 | GIR : 2026
A4: Code Entité | B4: Nom de l'entité | C4: Juridiction | D4: Pays ISO | E4: Taux IS local | F4: % Détention directe | G4: % Détention indirecte | H4: Entité parente | I4: Statut GloBE | J4: Consolidée ? | K4: Exclue GloBE ? | L4: Motif d'exclusion
A5: FR-HQ | B5: Groupe Alpha Holding SA | C5: France | D5: FR | E5: 0.2573 | F5: - | G5: - | H5: - | I5: UPE | J5: Oui | K5: Non | L5: -
A6: DE-01 | B6: Alpha GmbH | C6: Allemagne | D6: DE | E6: 0.2983 | F6: 1 | G6: 0 | H6: FR-HQ | I6: CE | J6: Oui | K6: Non | L6: -
A7: IE-01 | B7: Alpha Ireland Ltd | C7: Irlande | D7: IE | E7: 0.125 | F7: 1 | G7: 0 | H7: FR-HQ | I7: CE | J7: Oui | K7: Non | L7: -
A8: SG-01 | B8: Alpha Asia Pte Ltd | C8: Singapour | D8: SG | E8: 0.17 | F8: 0.8 | G8: 0 | H8: FR-HQ | I8: POPE | J8: Oui | K8: Non | L8: -
A9: US-01 | B9: Alpha Inc. | C9: États-Unis | D9: US | E9: 0.21 | F9: 1 | G9: 0 | H9: FR-HQ | I9: CE | J9: Oui | K9: Non | L9: -
A10: MU-01 | B10: Alpha Mauritius Ltd | C10: Maurice | D10: MU | E10: 0.15 | F10: 0.6 | G10: 0.2 | H10: SG-01 | I10: IPE | J10: Oui | K10: Non | L10: -
A11: FR-FP | B11: Caisse de Retraite Alpha | C11: France | D11: FR | E11: 0 | F11: 1 | G11: 0 | H11: FR-HQ | I11: - | J11: Non | K11: Oui | L11: Fonds de pension (Art. 10.1.1(d))
A13: LÉGENDE DES STATUTS GloBE
A14: UPE | B14: Ultimate Parent Entity — Entité mère ultime (obligation déclarative primaire)
A15: IPE | B15: Intermediate Parent Entity — Entité mère intermédiaire (IIR secondaire si UPE défaillante)
A16: POPE | B16: Partially-Owned Parent Entity — Entité mère partiellement détenue (détention < 100%)
A17: CE | B17: Constituent Entity — Entité constitutive (filiale simple)
A18: JV | B18: Joint Venture — Coentreprise (traitée séparément si détention ≥ 50%)
A19: Exclue | B19: Entité exclue du périmètre GloBE (Art. 10.1) : entités gouvernementales, OI, OBNL, fonds de pension, fonds d'investissement
A21: ORGANIGRAMME JURIDIQUE SIMPLIFIÉ
D23: 🏢 Groupe Alpha Holding SA (FR)
D24: UPE — 100% | Taux IS : 25,73%
F25: │
B26: ┌─────── | D26: ─────── | F26: ─────┬──── | H26: ─────── | J26: ───────┐
A28: 🇩🇪 Alpha GmbH | C28: 🇮🇪 Alpha Ireland | E28: 🇸🇬 Alpha Asia Pte | G28: 🇺🇸 Alpha Inc. | I28: 💼 Caisse Retraite
A29: CE | 100% | IS 29,83% | C29: CE | 100% | IS 12,50% | E29: POPE | 80% | IS 17% | G29: CE | 100% | IS 21% | I29: EXCLUE | Fonds pension
E30: │
E31: 🇲🇺 Alpha Mauritius
E32: IPE | 60% (via SG) | IS 15%

Sheet 2 — P&L GloBE
A1: ONGLET 2 — RÉSULTAT QUALIFIÉ GloBE (GloBE Income) PAR JURIDICTION
A2: Base : Résultat comptable IFRS → Retraitements Art. 15–22 du modèle de règles GloBE
A4: Poste (en k€) | B4: Référence | C4: FR | D4: DE | E4: IE | F4: SG | G4: US | H4: MU | I4: TOTAL GROUPE
A5: Résultat net comptable (IFRS) | B5: IAS 1 | C5: 12000 | D5: 8500 | E5: 25000 | F5: 15000 | G5: 18000 | H5: 6000 | I5: =SUM(C5:H5) -> 84500
A6: RETRAITEMENTS GloBE :
A7: (+) Charge d'impôt comptabilisée | B7: Art. 15.1 | C7: 3500 | D7: 2800 | E7: 3200 | F7: 2600 | G7: 4200 | H7: 900 | I7: =SUM(C7:H7) -> 17200
A8: (−) Dividendes intra-groupe | B8: Art. 15.2(a) | C8: -2000 | D8: 0 | E8: 0 | F8: -500 | G8: 0 | H8: 0 | I8: =SUM(C8:H8) -> -2500
A9: (−) Plus-values de cessions de participations | B9: Art. 15.2(b) | C9: 0 | D9: 0 | E9: -1500 | F9: 0 | G9: 0 | H9: 0 | I9: =SUM(C9:H9) -> -1500
A10: (−) Gains/pertes de change non réalisés | B10: Art. 15.3 | C10: -300 | D10: -200 | E10: 150 | F10: -400 | G10: 600 | H10: -100 | I10: =SUM(C10:H10) -> -250
A11: (−) Charges de stock-options (SBP) | B11: Art. 15.4 | C11: -800 | D11: -300 | E11: -1200 | F11: -600 | G11: -1500 | H11: 0 | I11: =SUM(C11:H11) -> -4400
A12: (+/−) Ajustement Fair Value (IFRS 9/13) | B12: Art. 15.5 | C12: -500 | D12: 200 | E12: -800 | F12: 300 | G12: -400 | H12: 100 | I12: =SUM(C12:H12) -> -1100
A13: (+/−) Ajust. régimes de retraite (IAS 19) | B13: Art. 15.6 | C13: -150 | D13: -100 | E13: 0 | F13: -50 | G13: -200 | H13: 0 | I13: =SUM(C13:H13) -> -500
A14: (−) Profits de navigation intérnationale | B14: Art. 16 | C14: 0 | D14: 0 | E14: 0 | F14: -1000 | G14: 0 | H14: 0 | I14: =SUM(C14:H14) -> -1000
A15: (+/−) Erreurs matérielles corrigées (IAS 8) | B15: Art. 17 | C15: 0 | D15: 0 | E15: 0 | F15: 0 | G15: 0 | H15: 0 | I15: =SUM(C15:H15) -> 0
A16: (+/−) Ajust. changement de méthodes comptables | B16: Art. 18 | C16: 0 | D16: 0 | E16: 0 | F16: 0 | G16: 0 | H16: 0 | I16: =SUM(C16:H16) -> 0
A17: (+/−) Autres ajustements (asymmetries, assurance capt.) | B17: Art. 19-22 | C17: 0 | D17: 0 | E17: 0 | F17: 0 | G17: 0 | H17: 0 | I17: =SUM(C17:H17) -> 0
A18: {=RÉSULTAT QUALIFIÉ GloBE (GloBE Income)} -> #NAME? | C18: =SUM(C5:C17) -> 11750 | D18: =SUM(D5:D17) -> 10900 | E18: =SUM(E5:E17) -> 24850 | F18: =SUM(F5:F17) -> 15350 | G18: =SUM(G5:G17) -> 20700 | H18: =SUM(H5:H17) -> 6900 | I18: =SUM(C18:H18) -> 90450

Sheet 3 — Impôts Couverts
A1: ONGLET 3 — IMPÔTS COUVERTS (COVERED TAXES) PAR JURIDICTION
A2: Calcul conforme aux Art. 20–23 du modèle de règles GloBE — IS courant + IS différé ajusté | Montants en k€
A4: Poste (en k€) | B4: Référence | C4: FR | D4: DE | E4: IE | F4: SG | G4: US | H4: MU | I4: TOTAL
A5: IS courant de l'exercice | B5: Art. 20.1 | C5: 3000 | D5: 2500 | E5: 2800 | F5: 2300 | G5: 3800 | H5: 700 | I5: =SUM(C5:H5) -> 15100
A6: (+) Retenues à la source (WHT) | B6: Art. 20.2 | C6: 200 | D6: 100 | E6: 0 | F6: 150 | G6: 300 | H6: 50 | I6: =SUM(C6:H6) -> 800
A7: (−) Crédits d'impôt non qualifiés (QRTC) | B7: Art. 20.3 | C7: -400 | D7: 0 | E7: -600 | F7: -200 | G7: -500 | H7: 0 | I7: =SUM(C7:H7) -> -1700
A8: {=Sous-total IS courant ajusté} -> #NAME? | C8: =SUM(C5:C7) -> 2800 | D8: =SUM(D5:D7) -> 2600 | E8: =SUM(E5:E7) -> 2200 | F8: =SUM(F5:F7) -> 2250 | G8: =SUM(G5:G7) -> 3600 | H8: =SUM(H5:H7) -> 750 | I8: =SUM(C8:H8) -> 14200
A10: IS différé de l'exercice (total) | B10: Art. 21.1 | C10: 500 | D10: 400 | E10: 600 | F10: 300 | G10: 700 | H10: 100 | I10: =SUM(C10:H10) -> 2600
A11: (−) Ajust. DTL non récurrentes (recast) | B11: Art. 21.2 | C11: -100 | D11: -50 | E11: -200 | F11: -80 | G11: -150 | H11: -30 | I11: =SUM(C11:H11) -> -610
A12: (−) Plafonnement du taux (cap à 15%) | B12: Art. 21.3 | C12: 0 | D12: 0 | E12: 0 | F12: 0 | G12: 0 | H12: 0 | I12: =SUM(C12:H12) -> 0
A13: {=Sous-total IS différé ajusté} -> #NAME? | C13: =SUM(C10:C12) -> 400 | D13: =SUM(D10:D12) -> 350 | E13: =SUM(E10:E12) -> 400 | F13: =SUM(F10:F12) -> 220 | G13: =SUM(G10:G12) -> 550 | H13: =SUM(H10:H12) -> 70 | I13: =SUM(C13:H13) -> 1990
A15: (−) Impôts liés à revenus exclus (QDMTT d'une autre jur.) | B15: Art. 22 | C15: 0 | D15: 0 | E15: 0 | F15: 0 | G15: 0 | H15: 0 | I15: =SUM(C15:H15) -> 0
A16: {=total IMPÔTS COUVERTS (Covered Taxes)} -> #NAME? | C16: =C8+C13+C15 -> 3200 | D16: =D8+D13+D15 -> 2950 | E16: =E8+E13+E15 -> 2600 | F16: =F8+F13+F15 -> 2470 | G16: =G8+G13+G15 -> 4150 | H16: =H8+H13+H15 -> 820 | I16: =SUM(C16:H16) -> 16190

Sheet 4 — ETR Juridictionnel
A1: ONGLET 4 — TAUX EFFECTIF D'IMPOSITION (ETR) JURIDICTIONNEL
A2: ETR = Covered Taxes / GloBE Income (Art. 26) | Seuil minimum : 15,00%
A4: Juridiction | B4: GloBE Income (k€) | C4: Covered Taxes (k€) | D4: ETR Juridictionnel | E4: Taux minimum (15%) | F4: Déficit d'ETR | G4: Statut | H4: Commentaire
A5: FR | B5: ='2 — P&L GloBE'!C18 -> 11750 | C5: ='3 — Impôts Couverts'!C16 -> 3200 | D5: =IF(B5=0,"-",C5/B5) -> 0.27234043 | E5: 0.15 | F5: =IF(B5=0,"-",MAX(0,E5-D5)) -> 0 | G5: =IF(D5="-","N/A",IF(D5>=E5,"✅ Conforme","❌ Sous le seuil")) -> ✅ Conforme | H5: =IF(D5="-","GloBE Income nul",IF(D5>=0.15,"Pas de Top-up Tax","Top-up Tax requis")) -> Pas de Top-up Tax
A6: DE | B6: ='2 — P&L GloBE'!D18 -> 10900 | C6: ='3 — Impôts Couverts'!D16 -> 2950 | D6: =IF(B6=0,"-",C6/B6) -> 0.2706422 | E6: 0.15 | F6: =IF(B6=0,"-",MAX(0,E6-D6)) -> 0 | G6: =IF(D6="-","N/A",IF(D6>=E6,"✅ Conforme","❌ Sous le seuil")) -> ✅ Conforme | H6: =IF(D6="-","GloBE Income nul",IF(D6>=0.15,"Pas de Top-up Tax","Top-up Tax requis")) -> Pas de Top-up Tax
A7: IE | B7: ='2 — P&L GloBE'!E18 -> 24850 | C7: ='3 — Impôts Couverts'!E16 -> 2600 | D7: =IF(B7=0,"-",C7/B7) -> 0.10462777 | E7: 0.15 | F7: =IF(B7=0,"-",MAX(0,E7-D7)) -> 0.045372233 | G7: =IF(D7="-","N/A",IF(D7>=E7,"✅ Conforme","❌ Sous le seuil")) -> ❌ Sous le seuil | H7: =IF(D7="-","GloBE Income nul",IF(D7>=0.15,"Pas de Top-up Tax","Top-up Tax requis")) -> Top-up Tax requis
A8: SG | B8: ='2 — P&L GloBE'!F18 -> 15350 | C8: ='3 — Impôts Couverts'!F16 -> 2470 | D8: =IF(B8=0,"-",C8/B8) -> 0.16091205 | E8: 0.15 | F8: =IF(B8=0,"-",MAX(0,E8-D8)) -> 0 | G8: =IF(D8="-","N/A",IF(D8>=E8,"✅ Conforme","❌ Sous le seuil")) -> ✅ Conforme | H8: =IF(D8="-","GloBE Income nul",IF(D8>=0.15,"Pas de Top-up Tax","Top-up Tax requis")) -> Pas de Top-up Tax
A9: US | B9: ='2 — P&L GloBE'!G18 -> 20700 | C9: ='3 — Impôts Couverts'!G16 -> 4150 | D9: =IF(B9=0,"-",C9/B9) -> 0.20048309 | E9: 0.15 | F9: =IF(B9=0,"-",MAX(0,E9-D9)) -> 0 | G9: =IF(D9="-","N/A",IF(D9>=E9,"✅ Conforme","❌ Sous le seuil")) -> ✅ Conforme | H9: =IF(D9="-","GloBE Income nul",IF(D9>=0.15,"Pas de Top-up Tax","Top-up Tax requis")) -> Pas de Top-up Tax
A10: MU | B10: ='2 — P&L GloBE'!H18 -> 6900 | C10: ='3 — Impôts Couverts'!H16 -> 820 | D10: =IF(B10=0,"-",C10/B10) -> 0.11884058 | E10: 0.15 | F10: =IF(B10=0,"-",MAX(0,E10-D10)) -> 0.03115942 | G10: =IF(D10="-","N/A",IF(D10>=E10,"✅ Conforme","❌ Sous le seuil")) -> ❌ Sous le seuil | H10: =IF(D10="-","GloBE Income nul",IF(D10>=0.15,"Pas de Top-up Tax","Top-up Tax requis")) -> Top-up Tax requis

Sheet 5 — Substance Carve-out
A1: ONGLET 5 — SUBSTANCE-BASED INCOME EXCLUSION (SBIE / CARVE-OUT)
A2: Art. 28 — Exclusion = Taux salarial × Masse salariale + Taux immo. × VNC immo. corporelles | Taux transitoires dégressifs 2024–2033
A4: TABLEAU DES TAUX TRANSITOIRES (Art. 9.2)
A5: Année | B5: Taux Masse salariale | C5: Taux VNC Immo.
A6: 2024 | B6: 0.098 | C6: 0.078
A7: 2025 | B7: 0.092 | C7: 0.074
A8: 2026 | B8: 0.086 | C8: 0.07
A9: 2027 | B9: 0.08 | C9: 0.066
A10: 2028 | B10: 0.074 | C10: 0.062
A11: 2029 | B11: 0.068 | C11: 0.058
A12: 2030 | B12: 0.062 | C12: 0.054
A13: 2031 | B13: 0.056 | C13: 0.052
A14: 2032 | B14: 0.053 | C14: 0.051
A15: 2033+ | B15: 0.05 | C15: 0.05
A17: CALCUL DU CARVE-OUT PAR JURIDICTION (Exercice 2026)
A18: Poste (en k€) | B18: Taux 2026 | C18: FR | D18: DE | E18: IE | F18: SG | G18: US | H18: MU | I18: TOTAL
A19: Masse salariale éligible | C19: 8000 | D19: 5500 | E19: 12000 | F19: 7000 | G19: 10000 | H19: 2000 | I19: =SUM(C19:H19) -> 44500
A20: Taux salarial transitoire (2026) | B20: =B8 -> 0.086 | C20: =$B20 -> 0.086 | D20: =$B20 -> 0.086 | E20: =$B20 -> 0.086 | F20: =$B20 -> 0.086 | G20: =$B20 -> 0.086 | H20: =$B20 -> 0.086
A21: {=Exclusion salariale} -> #NAME? | C21: =C19*C20 -> 688 | D21: =D19*D20 -> 473 | E21: =E19*E20 -> 1032 | F21: =F19*F20 -> 602 | G21: =G19*G20 -> 860 | H21: =H19*H20 -> 172 | I21: =SUM(C21:H21) -> 3827
A23: VNC immo. corporelles (éligibles) | C23: 15000 | D23: 12000 | E23: 20000 | F23: 8000 | G23: 25000 | H23: 3000 | I23: =SUM(C23:H23) -> 83000
A24: Taux immo. transitoire (2026) | B24: =C8 -> 0.07 | C24: =$B24 -> 0.07 | D24: =$B24 -> 0.07 | E24: =$B24 -> 0.07 | F24: =$B24 -> 0.07 | G24: =$B24 -> 0.07 | H24: =$B24 -> 0.07
A25: {=Exclusion immobilisations} -> #NAME? | C25: =C23*C24 -> 1050 | D25: =D23*D24 -> 840 | E25: =E23*E24 -> 1400 | F25: =F23*F24 -> 560 | G25: =G23*G24 -> 1750 | H25: =H23*H24 -> 210 | I25: =SUM(C25:H25) -> 5810
A26: {=total CARVE-OUT (SBIE)} -> #NAME? | C26: =C21+C25 -> 1738 | D26: =D21+D25 -> 1313 | E26: =E21+E25 -> 2432 | F26: =F21+F25 -> 1162 | G26: =G21+G25 -> 2610 | H26: =H21+H25 -> 382 | I26: =SUM(C26:H26) -> 9637

Sheet 6 — Top-up Tax
A1: ONGLET 6 — CALCUL DU COMPLÉMENT D'IMPÔT (TOP-UP TAX) & ALLOCATION IIR / UTPR
A2: Top-up Tax = (15% − ETR) × Excess Profit | Excess Profit = GloBE Income − Carve-out | Allocation : IIR (Art. 5.2) puis UTPR (Art. 5.4)
A4: Poste (en k€) | B4: Formule | C4: FR | D4: DE | E4: IE | F4: SG | G4: US | H4: MU | I4: TOTAL
A5: GloBE Income | B5: Onglet 2 | C5: ='2 — P&L GloBE'!C18 -> 11750 | D5: ='2 — P&L GloBE'!D18 -> 10900 | E5: ='2 — P&L GloBE'!E18 -> 24850 | F5: ='2 — P&L GloBE'!F18 -> 15350 | G5: ='2 — P&L GloBE'!G18 -> 20700 | H5: ='2 — P&L GloBE'!H18 -> 6900 | I5: =SUM(C5:H5) -> 90450
A6: (−) Carve-out (SBIE) | B6: Onglet 5 | C6: ='5 — Substance Carve-out'!C26 -> 1738 | D6: ='5 — Substance Carve-out'!D26 -> 1313 | E6: ='5 — Substance Carve-out'!E26 -> 2432 | F6: ='5 — Substance Carve-out'!F26 -> 1162 | G6: ='5 — Substance Carve-out'!G26 -> 2610 | H6: ='5 — Substance Carve-out'!H26 -> 382 | I6: =SUM(C6:H6) -> 9637
A7: {=Excess Profit} -> #NAME? | B7: GI − SBIE | C7: =MAX(0,C5-C6) -> 10012 | D7: =MAX(0,D5-D6) -> 9587 | E7: =MAX(0,E5-E6) -> 22418 | F7: =MAX(0,F5-F6) -> 14188 | G7: =MAX(0,G5-G6) -> 18090 | H7: =MAX(0,H5-H6) -> 6518 | I7: =SUM(C7:H7) -> 80813
A9: ETR Juridictionnel | B9: Onglet 4 | C9: ='4 — ETR Juridictionnel'!D5 -> 0.27234043 | D9: ='4 — ETR Juridictionnel'!D6 -> 0.2706422 | E9: ='4 — ETR Juridictionnel'!D7 -> 0.10462777 | F9: ='4 — ETR Juridictionnel'!D8 -> 0.16091205 | G9: ='4 — ETR Juridictionnel'!D9 -> 0.20048309 | H9: ='4 — ETR Juridictionnel'!D10 -> 0.11884058
A10: Top-up Tax Percentage | B10: MAX(0, 15%−ETR) | C10: =MAX(0,0.15-C9) -> 0 | D10: =MAX(0,0.15-D9) -> 0 | E10: =MAX(0,0.15-E9) -> 0.045372233 | F10: =MAX(0,0.15-F9) -> 0 | G10: =MAX(0,0.15-G9) -> 0 | H10: =MAX(0,0.15-H9) -> 0.03115942
A11: {=TOP-UP TAX (par juridiction)} -> #NAME? | B11: % × Excess | C11: =C10*C7 -> 0 | D11: =D10*D7 -> 0 | E11: =E10*E7 -> 1017.1547 | F11: =F10*F7 -> 0 | G11: =G10*G7 -> 0 | H11: =H10*H7 -> 203.0971 | I11: =SUM(C11:H11) -> 1220.2518
A13: ALLOCATION DU TOP-UP TAX :
A14: Via IIR (UPE = FR-HQ) | B14: Art. 5.2 | C14: =C11 -> 0 | D14: =D11 -> 0 | E14: =E11 -> 1017.1547 | F14: =F11 -> 0 | G14: =G11 -> 0 | H14: =H11 -> 203.0971 | I14: =SUM(C14:H14) -> 1220.2518
A15: Via UTPR (allocation résiduelle) | B15: Art. 5.4 | C15: 0 | D15: 0 | E15: 0 | F15: 0 | G15: 0 | H15: 0 | I15: =SUM(C15:H15) -> 0
A17: {=total DÛ par LE GROUPE} -> #NAME? | C17: =C14+C15 -> 0 | D17: =D14+D15 -> 0 | E17: =E14+E15 -> 1017.1547 | F17: =F14+F15 -> 0 | G17: =G14+G15 -> 0 | H17: =H14+H15 -> 203.0971 | I17: =SUM(C17:H17) -> 1220.2518

Sheet 7 — Safe Harbours
A1: ONGLET 7 — SAFE HARBOURS TRANSITOIRES (CbCR-BASED)
A2: Tests transitoires (OECD AG, Déc. 2022) : De minimis | ETR simplifié | Profit de routine — Si 1 test passé → Top-up Tax = 0 pour la juridiction
A4: Juridiction | B4: CA CbCR (k€) | C4: Résultat CbCR (k€) | D4: IS payé CbCR (k€) | E4: Test 1: De minimis | F4: Test 2: ETR simplifié | G4: Seuil ETR (2026) | H4: Test 3: Profit routine | I4: QUALIFIÉ ? | J4: Top-up Tax final
A5: FR | B5: 50000 | C5: 14000 | D5: 3600 | E5: =IF(AND(B5<10000,C5<1000000),"✅ PASS","❌ FAIL") -> ❌ FAIL | F5: =IF(C5=0,"N/A",IF(D5/C5>=G5,"✅ PASS","❌ FAIL")) -> ✅ PASS | G5: 0.15 | H5: =IF(C5<=0,"✅ PASS","❌ FAIL") -> ❌ FAIL | I5: =IF(OR(E5="✅ PASS",F5="✅ PASS",H5="✅ PASS"),"✅ OUI","❌ NON") -> ✅ OUI | J5: =IF(I5="✅ OUI",0,'6 — Top-up Tax'!C11) -> 0
A6: DE | B6: 35000 | C6: 10000 | D6: 3000 | E6: =IF(AND(B6<10000,C6<1000000),"✅ PASS","❌ FAIL") -> ❌ FAIL | F6: =IF(C6=0,"N/A",IF(D6/C6>=G6,"✅ PASS","❌ FAIL")) -> ✅ PASS | G6: 0.15 | H6: =IF(C6<=0,"✅ PASS","❌ FAIL") -> ❌ FAIL | I6: =IF(OR(E6="✅ PASS",F6="✅ PASS",H6="✅ PASS"),"✅ OUI","❌ NON") -> ✅ OUI | J6: =IF(I6="✅ OUI",0,'6 — Top-up Tax'!D11) -> 0
A7: IE | B7: 80000 | C7: 28000 | D7: 3500 | E7: =IF(AND(B7<10000,C7<1000000),"✅ PASS","❌ FAIL") -> ❌ FAIL | F7: =IF(C7=0,"N/A",IF(D7/C7>=G7,"✅ PASS","❌ FAIL")) -> ❌ FAIL | G7: 0.15 | H7: =IF(C7<=0,"✅ PASS","❌ FAIL") -> ❌ FAIL | I7: =IF(OR(E7="✅ PASS",F7="✅ PASS",H7="✅ PASS"),"✅ OUI","❌ NON") -> ❌ NON | J7: =IF(I7="✅ OUI",0,'6 — Top-up Tax'!E11) -> 1017.1547
A8: SG | B8: 45000 | C8: 16000 | D8: 2700 | E8: =IF(AND(B8<10000,C8<1000000),"✅ PASS","❌ FAIL") -> ❌ FAIL | F8: =IF(C8=0,"N/A",IF(D8/C8>=G8,"✅ PASS","❌ FAIL")) -> ✅ PASS | G8: 0.15 | H8: =IF(C8<=0,"✅ PASS","❌ FAIL") -> ❌ FAIL | I8: =IF(OR(E8="✅ PASS",F8="✅ PASS",H8="✅ PASS"),"✅ OUI","❌ NON") -> ✅ OUI | J8: =IF(I8="✅ OUI",0,'6 — Top-up Tax'!F11) -> 0
A9: US | B9: 60000 | C9: 20000 | D9: 4500 | E9: =IF(AND(B9<10000,C9<1000000),"✅ PASS","❌ FAIL") -> ❌ FAIL | F9: =IF(C9=0,"N/A",IF(D9/C9>=G9,"✅ PASS","❌ FAIL")) -> ✅ PASS | G9: 0.15 | H9: =IF(C9<=0,"✅ PASS","❌ FAIL") -> ❌ FAIL | I9: =IF(OR(E9="✅ PASS",F9="✅ PASS",H9="✅ PASS"),"✅ OUI","❌ NON") -> ✅ OUI | J9: =IF(I9="✅ OUI",0,'6 — Top-up Tax'!G11) -> 0
A10: MU | B10: 8000 | C10: 5500 | D10: 700 | E10: =IF(AND(B10<10000,C10<1000000),"✅ PASS","❌ FAIL") -> ✅ PASS | F10: =IF(C10=0,"N/A",IF(D10/C10>=G10,"✅ PASS","❌ FAIL")) -> ❌ FAIL | G10: 0.15 | H10: =IF(C10<=0,"✅ PASS","❌ FAIL") -> ❌ FAIL | I10: =IF(OR(E10="✅ PASS",F10="✅ PASS",H10="✅ PASS"),"✅ OUI","❌ NON") -> ✅ OUI | J10: =IF(I10="✅ OUI",0,'6 — Top-up Tax'!H11) -> 0

Sheet 8 — Déclaration GIR
A1: ONGLET 8 — MAQUETTE DE LA GLOBE INFORMATION RETURN (GIR) — FORMAT OCDE
A2: Conformément au modèle OCDE (Déc. 2023) — Pré-remplie à partir des calculs des onglets 1–7
A4: SECTION 1 — IDENTIFICATION DU GROUPE
A5: Champ | B5: Valeur | C5: Source
A6: Nom du groupe MNE | B6: Groupe Alpha Holding SA | C6: Onglet 1
A7: TIN de l'UPE | B7: FR-XXX-XXXX-XXXX | C7: À compléter
A8: Juridiction de l'UPE | B8: France (FR) | C8: Onglet 1
A9: Exercice fiscal déclaré | B9: 01/01/2026 – 31/12/2026 | C9: Input
A10: Date de dépôt | B10: 30/06/2028 (18 mois) | C10: Art. 44
A11: Seuil de CA consolidé | B11: ≥ 750 M€ | C11: Art. 1.1
A12: Nombre de juridictions | B12: 6 | C12: Onglet 1
A13: Règle appliquée | B13: IIR (Income Inclusion Rule) | C13: Art. 5.2
A15: SECTION 2 — RÉSUMÉ PAR JURIDICTION (pré-rempli)
A16: Juridiction | B16: GloBE Income (k€) | C16: Covered Taxes (k€) | D16: ETR (%) | E16: SBIE (k€) | F16: Top-up Tax (k€) | G16: Safe Harbour ? | H16: Top-up final (k€)
A17: FR | B17: ='4 — ETR Juridictionnel'!B5 -> 11750 | C17: ='4 — ETR Juridictionnel'!C5 -> 3200 | D17: ='4 — ETR Juridictionnel'!D5 -> 0.27234043 | E17: ='5 — Substance Carve-out'!C26 -> 1738 | F17: ='6 — Top-up Tax'!C11 -> 0 | G17: ='7 — Safe Harbours'!I5 -> ✅ OUI | H17: ='7 — Safe Harbours'!J5 -> 0
A18: DE | B18: ='4 — ETR Juridictionnel'!B6 -> 10900 | C18: ='4 — ETR Juridictionnel'!C6 -> 2950 | D18: ='4 — ETR Juridictionnel'!D6 -> 0.2706422 | E18: ='5 — Substance Carve-out'!D26 -> 1313 | F18: ='6 — Top-up Tax'!D11 -> 0 | G18: ='7 — Safe Harbours'!I6 -> ✅ OUI | H18: ='7 — Safe Harbours'!J6 -> 0
A19: IE | B19: ='4 — ETR Juridictionnel'!B7 -> 24850 | C19: ='4 — ETR Juridictionnel'!C7 -> 2600 | D19: ='4 — ETR Juridictionnel'!D7 -> 0.10462777 | E19: ='5 — Substance Carve-out'!E26 -> 2432 | F19: ='6 — Top-up Tax'!E11 -> 1017.1547 | G19: ='7 — Safe Harbours'!I7 -> ❌ NON | H19: ='7 — Safe Harbours'!J7 -> 1017.1547
A20: SG | B20: ='4 — ETR Juridictionnel'!B8 -> 15350 | C20: ='4 — ETR Juridictionnel'!C8 -> 2470 | D20: ='4 — ETR Juridictionnel'!D8 -> 0.16091205 | E20: ='5 — Substance Carve-out'!F26 -> 1162 | F20: ='6 — Top-up Tax'!F11 -> 0 | G20: ='7 — Safe Harbours'!I8 -> ✅ OUI | H20: ='7 — Safe Harbours'!J8 -> 0
A21: US | B21: ='4 — ETR Juridictionnel'!B9 -> 20700 | C21: ='4 — ETR Juridictionnel'!C9 -> 4150 | D21: ='4 — ETR Juridictionnel'!D9 -> 0.20048309 | E21: ='5 — Substance Carve-out'!G26 -> 2610 | F21: ='6 — Top-up Tax'!G11 -> 0 | G21: ='7 — Safe Harbours'!I9 -> ✅ OUI | H21: ='7 — Safe Harbours'!J9 -> 0
A22: MU | B22: ='4 — ETR Juridictionnel'!B10 -> 6900 | C22: ='4 — ETR Juridictionnel'!C10 -> 820 | D22: ='4 — ETR Juridictionnel'!D10 -> 0.11884058 | E22: ='5 — Substance Carve-out'!H26 -> 382 | F22: ='6 — Top-up Tax'!H11 -> 203.0971 | G22: ='7 — Safe Harbours'!I10 -> ✅ OUI | H22: ='7 — Safe Harbours'!J10 -> 0
A23: TOTAL | B23: =SUM(B17:B22) -> 90450 | C23: =SUM(C17:C22) -> 16190 | D23: =IF(B23=0,"-",C23/B23) -> 0.17899392 | E23: =SUM(E17:E22) -> 9637 | F23: =SUM(F17:F22) -> 1220.2518 | H23: =SUM(H17:H22) -> 1017.1547
A25: SECTION 3 — DÉTAIL DES ENTITÉS CONSTITUTIVES
A26: Code Entité | B26: Nom | C26: Juridiction | D26: Statut GloBE | E26: Exclue ? | F26: GloBE Income (k€)
A27: ='1 — Structure Groupe'!A5 -> FR-HQ | B27: ='1 — Structure Groupe'!B5 -> Groupe Alpha Holding SA | C27: ='1 — Structure Groupe'!C5 -> France | D27: ='1 — Structure Groupe'!I5 -> UPE | E27: ='1 — Structure Groupe'!K5 -> Non | F27: ='2 — P&L GloBE'!C18 -> 11750
A28: ='1 — Structure Groupe'!A6 -> DE-01 | B28: ='1 — Structure Groupe'!B6 -> Alpha GmbH | C28: ='1 — Structure Groupe'!C6 -> Allemagne | D28: ='1 — Structure Groupe'!I6 -> CE | E28: ='1 — Structure Groupe'!K6 -> Non | F28: ='2 — P&L GloBE'!D18 -> 10900
A29: ='1 — Structure Groupe'!A7 -> IE-01 | B29: ='1 — Structure Groupe'!B7 -> Alpha Ireland Ltd | C29: ='1 — Structure Groupe'!C7 -> Irlande | D29: ='1 — Structure Groupe'!I7 -> CE | E29: ='1 — Structure Groupe'!K7 -> Non | F29: ='2 — P&L GloBE'!E18 -> 24850
A30: ='1 — Structure Groupe'!A8 -> SG-01 | B30: ='1 — Structure Groupe'!B8 -> Alpha Asia Pte Ltd | C30: ='1 — Structure Groupe'!C8 -> Singapour | D30: ='1 — Structure Groupe'!I8 -> POPE | E30: ='1 — Structure Groupe'!K8 -> Non | F30: ='2 — P&L GloBE'!F18 -> 15350
A31: ='1 — Structure Groupe'!A9 -> US-01 | B31: ='1 — Structure Groupe'!B9 -> Alpha Inc. | C31: ='1 — Structure Groupe'!C9 -> États-Unis | D31: ='1 — Structure Groupe'!I9 -> CE | E31: ='1 — Structure Groupe'!K9 -> Non | F31: ='2 — P&L GloBE'!G18 -> 20700
A32: ='1 — Structure Groupe'!A10 -> MU-01 | B32: ='1 — Structure Groupe'!B10 -> Alpha Mauritius Ltd | C32: ='1 — Structure Groupe'!C10 -> Maurice | D32: ='1 — Structure Groupe'!I10 -> IPE | E32: ='1 — Structure Groupe'!K10 -> Non | F32: ='2 — P&L GloBE'!H18 -> 6900
A33: ='1 — Structure Groupe'!A11 -> FR-FP | B33: ='1 — Structure Groupe'!B11 -> Caisse de Retraite Alpha | C33: ='1 — Structure Groupe'!C11 -> France | D33: ='1 — Structure Groupe'!I11 -> - | E33: ='1 — Structure Groupe'!K11 -> Oui | F33: N/A — Exclue
