Workbook
Name CA_Groupe: CONSOL_CR!$C$35
Name EBIT_Groupe: CONSOL_CR!$C$36
Name EBITDA_Groupe: CONSOL_CR!$C$38
Name Marge_EBIT_Groupe: CONSOL_CR!$C$37
Name Marge_EBITDA_Groupe: CONSOL_CR!$C$39
Name RN_Groupe: CONSOL_CR!$C$40
Name Taux_GBP_Cloture: PQ_TAUX_CHANGE!$F$6
Name Taux_SGD_Cloture: PQ_TAUX_CHANGE!$F$16
Name Taux_USD_Cloture: PQ_TAUX_CHANGE!$F$11

Sheet HOME
A1: 📑 SOMMAIRE COMPLET – TOUS LES ONGLETS (37 + 1 onglet)
B2: GROUPE MULTINATIONAL – CONSOLIDATION IFRS 18 | ESG / CSRD · Exercice 2025–2026
B5: Outil automatisé de consolidation · 5 entités · Société Mère FR + 4 Filiales Internationales
B7: LÉGENDE DES ONGLETS
B8: 🟢 VERT CLAIR | E8: 🔵 BLEU | H8: 🟠 ORANGE | K8: ⬛ ANTHRACITE
B9: Données sources (saisie / import) | E9: Calculs, consolidation & IFRS 18 | H9: Dashboards & reporting | K9: Navigation & documentation
B11: PLAN DU CLASSEUR – INDEX DES ONGLETS
B12: # | C12: Onglet | D12: Bloc | E12: Couleur | F12: Description | G12: Rôle
B13: 1 | C13: HOME | D13: Navigation | E13: Anthracite | F13: Page d'accueil et index de navigation | G13: Dashboard de lancement
B14: 2 | C14: GUIDE | D14: Navigation | E14: Anthracite | F14: Manuel utilisateur, légende, conventions IFRS 18 | G14: Documentation pédagogique
B15: 3 | C15: FR_ParentCo | D15: Sources 🟢 | E15: Vert | F15: Liasses comptables – Société Mère France (EUR) | G15: Saisie / import balances
B16: 4 | C16: DE_Filiale | D16: Sources 🟢 | E16: Vert | F16: Liasses comptables – Filiale Allemagne (EUR) | G16: Saisie / import balances
A17: N° | B17: Onglet | C17: Catégorie | D17: Description | E17: Statut | F17: Liasses comptables – Filiale Royaume-Uni (GBP) | G17: Saisie / import balances
A18: 1 | B18: HOME | C18: Navigation | D18: Accueil, légende, sommaire – point d'entrée du simulateur | E18: ✅ Complet | F18: Liasses comptables – Filiale États-Unis (USD) | G18: Saisie / import balances
A19: 2 | B19: GUIDE | C19: Documentation | D19: Guide utilisateur: couleurs, IFRS 18, ESG/CSRD, workflow | E19: ✅ Complet | F19: Liasses comptables – Filiale Singapour (SGD) | G19: Saisie / import balances
A20: 3 | B20: Méthodologie & Pédagogie | C20: Documentation | D20: §1-§10: IFRS 18, IAS 21, IFRS 3, Éliminations, PQ, Glossaire 60 termes, Audit Trail | E20: ✅ NOUVEAU | F20: Écritures d'élimination intercompagnies & capital | G20: Neutralisation flux internes
A21: 4 | B21: FR_ParentCo | C21: Données sources | D21: Bilan + CR Société Mère France (devise EUR) | E21: ✅ Complet | F21: Bilan consolidé agrégé + éliminations (IFRS) | G21: État financier consolidé
A22: 5 | B22: DE_Filiale | C22: Données sources | D22: Bilan + CR Filiale Allemagne (devise EUR) | E22: ✅ Complet | F22: Compte de résultat consolidé IFRS 18 (nouvelles catégories) | G22: P&L consolidé IFRS 18
A23: 6 | B23: UK_Filiale | C23: Données sources | D23: Bilan + CR Filiale Royaume-Uni (devise GBP) | E23: ✅ Complet | F23: Tableau des flux de trésorerie consolidé (méthode indirecte) | G23: Cash flow statement
A24: 7 | B24: US_Filiale | C24: Données sources | D24: Bilan + CR Filiale États-Unis (devise USD) | E24: ✅ Complet | F24: Mapping des postes IFRS 18 : Opérationnel / Investissement / Financement | G24: Reclassement IFRS 18
A25: 8 | B25: SG_Filiale | C25: Données sources | D25: Bilan + CR Filiale Singapour (devise SGD) | E25: ✅ Complet | F25: Notes annexes : Regroupements, GW, conversion, impôts différés | G25: Annexes IFRS
A26: 9 | B26: ELIM | C26: Consolidation | D26: Éliminations IC (7 écritures) + IFRS 3 Goodwill/NCI | E26: ✅ Complet | F26: Données ESG brutes : E (CO₂, énergie), S (emploi, parité), G (gouvernance) | G26: Collecte KPIs ESG
A27: 10 | B27: CONSOL_BILAN | C27: Consolidation | D27: Bilan consolidé groupe – toutes entités converties en EUR | E27: ✅ Complet | F27: Rapport CSRD structuré : E1-E5, S1-S4, G1-G2 (ESRS) | G27: Conformité CSRD/ESRS
A28: 11 | B28: CONSOL_CR | C28: Consolidation | D28: Compte de résultat consolidé – 5 catégories IFRS 18 | E28: ✅ Complet | F28: Dashboard financier interactif : KPIs, graphiques, comparaisons | G28: Analyse & décision
A29: 12 | B29: CONSOL_TRESORERIE | C29: Consolidation | D29: Tableau de flux de trésorerie consolidé (IAS 7) | E29: ✅ Complet | F29: Dashboard ESG interactif : scores, tendances, benchmarks | G29: Pilotage ESG
A30: 13 | B30: IFRS18_MAPPING | C30: IFRS 18 | D30: Mapping 5 catégories IFRS 18 pour tous les postes P&L | E30: ✅ Complet
A31: 14 | B31: NOTES_IFRS
A32: 15 | B32: ESG_DATA | C32: ESG/CSRD | D32: Données ESG brutes – KPIs E/S/G par entité et période | E32: ✅ Complet | F32: Méthode | G32: Taux de clôture | H32: Taux moyen | I32: Secteur
A33: 16 | B33: CSRD_RAPPORT | C33: ESG/CSRD | D33: Rapport de durabilité CSRD – ESRS E1/S1/G1 | E33: ✅ Complet | F33: Mère / Intégration Globale | G33: 1 | H33: 1 | I33: Holding / Services
A34: 17 | B34: DASHBOARD_FIN | C34: Dashboards | D34: Dashboard financier – KPIs, EBITDA, marges, levier | E34: ✅ Complet | F34: Intégration Globale | G34: 1 | H34: 1 | I34: Industrie manufacturière
A35: 18 | B35: DASHBOARD_ESG | C35: Dashboards | D35: Dashboard ESG – CO2, parité, accidents, gouvernance | E35: ✅ Complet | F35: Intégration Globale | G35: 1.165 | H35: 1.152 | I35: Technologies & Digital
A36: 19 | B36: DASHBOARD | C36: Dashboards | D36: Dashboard maître – synthèse Groupe toutes métriques | E36: ✅ Complet | F36: Intégration Globale | G36: 0.918 | H36: 0.925 | I36: Distribution & Retail
A37: 20 | B37: SRC_FR | C37: Sources PQ | D37: Source balances comptables FR – import Power Query | E37: ✅ Complet | F37: Intégration Globale | G37: 0.678 | H37: 0.682 | I37: Finance & Investissement
A38: 21 | B38: SRC_DE | C38: Sources PQ | D38: Source balances comptables DE – import Power Query | E38: ✅ Complet
A39: 22 | B39: SRC_UK | C39: Sources PQ | D39: Source balances comptables UK – import Power Query | E39: ✅ Complet
A40: 23 | B40: SRC_US
A41: 24 | B41: SRC_SG | C41: Sources PQ | D41: Source balances comptables SG – import Power Query | E41: ✅ Complet
A42: 25 | B42: PQ_MAPPING | C42: Power Query | D42: Mapping plans de comptes locaux → référentiel Groupe | E42: ✅ Complet
A43: 26 | B43: PQ_CODE
A44: 27 | B44: BALANCES_PQ
A45: 28 | B45: PQ_TAUX_CHANGE | C45: Power Query | D45: Table des taux de change IAS 21 – clôture/moyen/histo | E45: ✅ Complet
A46: 29 | B46: PQ_DETENTION
A47: 30 | B47: PQ_ELIMINATIONS | C47: Power Query | D47: Calcul automatique éliminations IC via PQ | E47: ✅ Complet
A48: 31 | B48: PQ_DAX_MESURES
A49: 32 | B49: PQ_M_AVANCE
A50: 33 | B50: FORMULES_LIAISON
A51: 34 | B51: ESG_CARBONE
A52: 35 | B52: ESG_DIVERSITE
A53: 36 | B53: ESG_MAPPING
A54: 37 | B54: ESG_DAX
A55: 38 | B55: ESG_DASHBOARD_LINK | C55: ESG/CSRD | D55: Liaisons données ESG → Dashboard ESG | E55: ✅ Complet
A56: 🆕 NOUVEAU : Onglet GUIDE_DÉMARRAGE ajouté – Guide complet pour débutant (10 étapes) + KPIs + FAQ + Quick Ref | B56: 🔗 MODÈLE DE DONNÉES POWER PIVOT – RELATIONS ENTRE TABLES
B57: Table Fait | C57: Champ Clé | E57: Table Dimension | F57: Champ Clé | G57: Cardinalité | H57: Usage
B58: Balances_PQ | C58: [EntitéNormalisée] | D58: → | E58: PQ_DETENTION | F58: [EntitéFiliale] | G58: Many-to-One | H58: Filtrer par entité, calculer NCI
B59: Balances_PQ | C59: [Devise] | D59: → | E59: PQ_TAUX_CHANGE | F59: [Devise] | G59: Many-to-One | H59: Appliquer taux IAS 21
B60: Balances_PQ | C60: [CodeCompte] | D60: → | E60: PQ_MAPPING | F60: [CodeSource] | G60: Many-to-One | H60: Reclasser IFRS 18
B61: Balances_PQ | C61: [Mois] | D61: → | E61: Calendrier | F61: [Mois] | G61: Many-to-One | H61: Analyses temporelles YOY/YTD
B62: PQ_ELIMINATIONS | C62: [Vendeur] | D62: → | E62: PQ_DETENTION | F62: [EntitéFiliale] | G62: Many-to-One | H62: Valider éliminations par périmètre
B65: ✅ CLASSEUR COMPLET – 25 ONGLETS · 3 ÉTAPES · Données fictives IFRS 18 / CSRD / IAS 21 / IFRS 10 · Prêt pour Power Query & Power Pivot
B68: MODULE ESG LÉGER (Phase 4) – 5 nouveaux onglets
B69: ESG_CARBONE | C69: Bilan Carbone Scope 1/2/3 | D69: ESRS E1 | E69: Scope 1/2/3 pondérés · Facteurs émission 5 pays · Prix carbone · Impact EBIT | F69: Vert
B70: ESG_DIVERSITE | C70: Diversité et Gouvernance | D70: ESRS S1/G1 | E70: Effectifs · Parité · Rémunération · Santé Sécurité · CA · ETR | F70: Vert
B71: ESG_MAPPING | C71: Mapping ESRS x IFRS 18 | D71: Mapping | E71: 29 liaisons KPIs ESG vers états financiers consolidés | F71: Vert
B72: ESG_DAX | C72: Mesures DAX ESG 30 | D72: DAX Power Pivot | E72: 30 mesures DAX copier vers Power Pivot (E/S/G/Cross) | F72: Bleu
B73: ESG_DASHBOARD_LINK | C73: Pont ESG x Financier | D73: Pont | E73: Scores E/S/G/Global · KPIs carbone · Guide 10 etapes | F73: Vert

Sheet GUIDE_DÉMARRAGE
A1: 🚀 GUIDE DE DÉMARRAGE — Comment analyser les données d'une entreprise avec ce simulateur
A2: Niveau : Débutant · Durée : 10 min · Simulateur IFRS 18 · Groupe 5 entités (FR/DE/UK/US/SG) · Exercice 2025–2026
A4: 🗺️ QU'EST-CE QUE CE FICHIER ?
B5: 📁 STRUCTURE DU GROUPE | C5: 🎯 OBJECTIF DE L'OUTIL | D5: 👥 POUR QUI EST CET OUTIL ?
B6: • FR_ParentCo — France, EUR (maison mère) | C6: • Consolider 5 entités en 1 seul groupe | D6: • Étudiants en finance, audit, CG
B7: • DE_Filiale — Allemagne, EUR | C7: • Convertir les devises selon IAS 21 | D7: • Candidats en entretien finance
B8: • UK_Filiale — Royaume-Uni, GBP | C8: • Éliminer les transactions internes | D8: • Professionnels débutants en consolidation
B9: • US_Filiale — États-Unis, USD | C9: • Produire Bilan / CR / Trésorerie IFRS | D9: • Tout curieux de la norme IFRS 18
B10: • SG_Filiale — Singapour, SGD | C10: • Analyser KPIs financiers & ESG/CSRD
A13: 📂 CARTE DES ONGLETS — Qui fait quoi ?
A14: Couleur | B14: Rôle | C14: Onglets concernés | D14: Règle d'or
A15: 🟢 VERT | B15: SAISIE (tu écris ici) | C15: SRC_FR · SRC_DE · SRC_UK · SRC_US · SRC_SG · PQ_TAUX_CHANGE | D15: ✅ Seules ces cellules sont modifiables. C'est ton point d'entrée.
A16: 🔵 BLEU | B16: CALCULS AUTO (ne pas toucher) | C16: CONSOL_BILAN · CONSOL_CR · CONSOL_TRESORERIE · ELIM · BALANCES_PQ | D16: 🚫 Ces onglets se recalculent seuls. Ne jamais saisir manuellement.
A17: 🟠 ORANGE | B17: RÉSULTATS / DASHBOARDS | C17: DASHBOARD_FIN · DASHBOARD_ESG · DASHBOARD · CSRD_RAPPORT | D17: 👁️ Lecture seule. Tes KPIs, graphiques et rapports finaux.
A18: ⚫ NOIR | B18: NAVIGATION & AIDE | C18: HOME · GUIDE · GUIDE_DÉMARRAGE · Méthodologie & Pédagogie | D18: 📖 Pour comprendre, naviguer et consulter la documentation.
A19: 🔴 ROUGE | B19: CONFIG AVANCÉE (experts) | C19: PQ_MAPPING · PQ_CODE · PQ_ELIMINATIONS · PQ_DAX_MESURES | D19: ⚠️ Ne modifier que si tu maîtrises Power Query et M.
A21: 📋 PLAN EN 10 ÉTAPES — De zéro à l'analyse complète
A22: N° | B22: Titre de l'étape | C22: Ce que tu fais concrètement (mode opératoire) | D22: Onglet(s) à ouvrir | E22: Durée
A23: 1 | B23: 🔑 PRÉREQUIS | C23: À l'ouverture : › Barre jaune « Macros désactivées » → cliquer « Activer le contenu » › Mode protégé → cliquer « Modifier quand même » › Enregistrer en .xlsm : Fichier → Enregistrer sous → Classeur Excel avec macros | D23: Tous les onglets | E23: 2 min
A24: 2 | B24: 🗺️ EXPLORATION | C24: Parcourir SANS rien modifier : ① HOME → comprendre la légende des couleurs d'onglets ② GUIDE → lire les conventions de saisie ③ GUIDE_DÉMARRAGE (ici) → mémoriser le plan en 10 étapes Règle d'or : les cellules bleues contiennent des formules → ne jamais saisir dessus. | D24: HOME · GUIDE GUIDE_DÉMARRAGE | E24: 5 min
A25: 3 | B25: 💱 TAUX DE CHANGE | C25: Onglet PQ_TAUX_CHANGE › Section 1 (lignes 5 à 20) Saisir dans la colonne F les taux BCE à la date de clôture : › F6 = GBP/EUR clôture (ex : 1.165) › F9 = GBP/EUR moyen annuel (ex : 1.155) › F11 = USD/EUR clôture (ex : 0.918) › F14 = USD/EUR moyen annuel (ex : 0.925) › F16 = SGD/EUR clôture (ex : 0.678) › F19 = SGD/EUR moyen annuel (ex : 0.682) Source officielle : ecb.europa.eu › Statistics › Exchange Rates | D25: PQ_TAUX_CHANGE › Colonne F | E25: 5 min
A26: 4 | B26: 📥 DONNÉES FR (Société mère) | C26: Onglet SRC_FR → coller les balances comptables annuelles de la maison mère : › Col A = Code compte (ex : 701000) › Col B = Libellé du compte › Colonnes suivantes = Montants par mois ou trimestre Comment importer : export depuis SAP / SAGE / Cegid → Ctrl+C → Ctrl+V Le plan de comptes doit correspondre à celui de PQ_MAPPING (colonne CodeCompteLocal). ✅ Vérification : onglet FR_ParentCo › cellule D30 (TOTAL ACTIF) doit être positif. | D26: SRC_FR → FR_ParentCo | E26: 15–30 min
A27: 5 | B27: 📥 DONNÉES FILIALES (4 entités étrangères) | C27: Même opération × 4. ⚠️ Saisir TOUJOURS en monnaie LOCALE (conversion automatique). › SRC_DE → DE_Filiale (EUR, aucune conversion nécessaire) › SRC_UK → UK_Filiale (GBP → EUR converti via taux §3) › SRC_US → US_Filiale (USD → EUR converti automatiquement) › SRC_SG → SG_Filiale (SGD → EUR converti automatiquement) Vérification : chaque onglet filiale › cellule D26 (TOTAL ACTIF) > 0 | D27: SRC_DE · SRC_UK SRC_US · SRC_SG | E27: 15–30 min par entité
A28: 6 | B28: ✂️ ÉLIMINATIONS IC (Transactions internes) | C28: Onglet ELIM › Section 1 (lignes 5 à 12) Saisir TOUTES les opérations réalisées ENTRE entités du groupe : › Ventes interco › Management fees › Prêts inter-compagnies › Dividendes internes Pour chaque ligne : montant en monnaie locale + sélectionner la devise. Le montant en EUR est calculé automatiquement. 📖 Règle IFRS fondamentale : tout flux interne = double comptage = doit être éliminé. | D28: ELIM › §1 et §2 | E28: 10–20 min
A29: 7 | B29: ⚡ RAFRAÎCHIR (Bouton unique) | C29: Aller sur HOME › cliquer « 🔄 TOUT RAFRAÎCHIR » › attendre. Le programme exécute 4 actions automatiquement : ① Recharge tous les Power Query (normalisation et conversion des données) ② Recalcule toutes les formules IFRS (IAS 21, IFRS 3, éliminations IC) ③ Met à jour les 3 dashboards (financier, ESG, maître) ④ Inscrit une ligne dans AUDIT_LOG (traçabilité avec horodatage) Message de confirmation en fin : « ✅ Rafraîchissement terminé – X connexions » | D29: HOME › Bouton orange | E29: 1–2 min
A30: 8 | B30: ✅ VÉRIFICATIONS (Contrôle qualité) | C30: Vérifier ces 4 indicateurs avant d'analyser : ① CONSOL_BILAN › ligne 43 → doit afficher « ✅ BILAN ÉQUILIBRÉ » Si ❌ : revoir les éliminations IC (onglet ELIM §1 et §2) ② CONSOL_CR → aucun #VALEUR! ou #REF! dans le tableau des données Si erreur : vérifier que les onglets SRC_* contiennent bien des données ③ CONSOL_TRESORERIE › ligne 29 → doit afficher « ✅ OK » Si ❌ : vérifier la trésorerie d'ouverture (cellule C27) ④ Alt+F8 → sélectionner ValiderFiliales() → Exécuter → lire le rapport RAG | D30: CONSOL_BILAN CONSOL_CR CONSOL_TRESORERIE | E30: 5 min
A31: 9 | B31: 📊 ANALYSER (L'objectif final) | C31: Consulter dans cet ordre pour une analyse complète : ① DASHBOARD_FIN → Vue globale : CA, EBIT, EBITDA, RN, Dette Nette, Levier ② CONSOL_CR → P&L détaillé par entité + variations Δ% vs N-1 + TEI ③ CONSOL_BILAN → Structure : Goodwill, Capitaux propres, Dettes, Actifs ④ CONSOL_TRESORERIE → Cash opérationnel vs CAPEX vs Financement (FCF) ⑤ DASHBOARD_ESG → CO₂ Scope 1-2-3, parité H/F, accidents, gouvernance → Les KPIs sont expliqués en détail dans la Section D ci-dessous | D31: DASHBOARD_FIN CONSOL_CR CONSOL_BILAN CONSOL_TRESORERIE DASHBOARD_ESG | E31: 30–60 min
A32: 10 | B32: 📤 EXPORTER (Partager les résultats) | C32: Option A – PDF en 1 clic (recommandé) : Alt+F8 → ExporterPDF() → OK → Génère « IFRS18_Rapport_2025-XX-XX.pdf » Contenu : HOME + Bilan + CR + Trésorerie + IFRS18_MAPPING + Dashboards + CSRD Option B – PDF manuel sélectif : Ctrl+clic sur les onglets à exporter → Fichier → Exporter → Créer PDF/XPS Option C – Partage du fichier Excel : Fichier → Enregistrer sous → Format .xlsm Nom suggéré : IFRS18_Consolidation_[NomEntreprise]_[Exercice].xlsm | D32: HOME › Bouton PDF ou Alt+F8 | E32: 2–5 min
A34: 📈 SECTION D — COMMENT LIRE LES 10 KPIs FINANCIERS CLÉS
A35: KPI | B35: Définition & Formule | C35: Où le trouver dans le fichier | D35: Benchmark sectoriel | E35: Comment l'interpréter
A36: CA Groupe (k€) | B36: Chiffre d'affaires consolidé = Σ CA 5 entités − Éliminations IC (IFRS 18 Catégorie ①) | C36: CONSOL_CR › K7 DASHBOARD_FIN › B6 Valeur : 817 075 k€ | D36: Croissance vs N-1 : > +5% = dynamisme 0 à +5% = stabilité < 0% = vigilance | E36: Δ% vs N-1 = −0.4% → CA quasi stable. Vérifier si baisse de volumes (prix stable) ou baisse de prix (volumes stables).
A37: Marge EBIT (%) | B37: EBIT / CA EBIT = Résultat Opérationnel = uniquement Catégorie ① IFRS 18 (SANS investissement ni financement) | C37: CONSOL_CR › K14 / K7 DASHBOARD_FIN › G6 Valeur : 18.8% | D37: Industrie lourde : 8–12% Services / Conseil : 15–25% Tech / SaaS : 20–30% Distribution : 3–6% | E37: 18.8% = solide pour industrie. SG_Filiale est la plus rentable (25%). Chercher pourquoi : mix produits, coûts ?
A38: EBITDA (k€) | B38: EBIT + Dotations aux amortissements = Proxy du cash opérationnel généré (avant IS, intérêts, amortissements) | C38: CONSOL_CR › C38 DASHBOARD_FIN › B11 Valeur : 216 451 k€ | D38: Comparer à CAPEX : CAPEX / EBITDA < 30% = OK CAPEX / EBITDA > 60% = capital intensif | E38: CAPEX = 48 200 k€ CAPEX/EBITDA = 22% → investissement maîtrisé. EBITDA positif = génération de cash réelle.
A39: Marge EBITDA (%) | B39: EBITDA / CA = Rentabilité avant effets comptables (amortissements, IS, intérêts) | C39: CONSOL_CR › C38 / K7 DASHBOARD_FIN › G11 Valeur : 26.5% | D39: Industrie : 15–20% Tech : 25–35% Santé : 20–30% | E39: 26.5% confirme des marges robustes. Supérieur à Marge EBIT (18.8%) de 7.7 pts = impact normal des amortissements.
A40: TEI (Taux Effectif IS) | B40: IS total / Résultat avant IS = Taux d'imposition réellement supporté (≠ taux légal nominal) | C40: CONSOL_CR › C43 Valeur : 27.8% | D40: Taux légaux : FR 25%, UK 25% US 21%, DE 30%, SG 17% TEI groupe ≈ moyenne pondérée | E40: 27.8% cohérent avec le mix pays. TEI < 15% : structures d'optimisation ? TEI > 40% : provisions IS exceptionnelles ?
A41: Levier DN/EBITDA | B41: Dette Nette / EBITDA Dette Nette = Dettes fin. − Trésorerie = Nb d'années d'EBITDA pour rembourser | C41: CONSOL_CR › C44 DASHBOARD_FIN › F13 Valeur : 0.95x | D41: < 1x = quasi pas endetté 1–2x = faible dette 2–4x = endettement modéré > 5x = risque élevé | E41: 0.95x = groupe très peu endetté. Capacité à lever de la dette si besoin. M&A ou CAPEX expansif sont possibles.
A42: Dette Nette (k€) | B42: Dettes financières (LT+CT) − Trésorerie Positif = groupe endetté Négatif = trésorerie excédentaire | C42: DASHBOARD_FIN › K11 Valeur : 205 512 k€ | D42: Comparer aux CP : Gearing (DN/CP) < 50% = conservateur Gearing > 100% = agressif | E42: 205 512 k€ vs EBITDA 216 451 k€ → couverture quasi 1:1 = situation saine. Surveiller les échéances de remboursement.
A43: Résultat Net (k€) | B43: Profit après IS, NCI et activ. abandonnées = Ce qui revient aux actionnaires du groupe (hors intérêts minoritaires NCI) | C43: CONSOL_CR › K30 Valeur : 82 110 k€ | D43: Marge nette saine : > 8–10% Marge nette ici : 10.0% | E43: Δ vs N-1 = −35% → forte baisse. À investiguer : IS exceptionnel ? Ou dégradation opérationnelle réelle ?
A44: Flux exploitation (IAS 7, k€) | B44: Cash généré par l'activité courante (méthode indirecte : RN + amort. ± BFR) Après IS payés, avant CAPEX | C44: CONSOL_TRESORERIE › C12 Valeur : 133 648 k€ | D44: FCF = Flux exploit. − CAPEX FCF > 0 = autofinancement FCF < 0 = dépendance financement extérieur | E44: FCF = 133 648 − 48 200 − 9 200 = 76 248 k€ Le groupe génère du cash libre positif. Peut financer sa croissance en interne.
A45: Écart de conversion (OCI, IAS 21) | B45: Gain / Perte de change sur conversion des filiales étrangères en EUR → OCI : n'impacte PAS le P&L ! | C45: CONSOL_BILAN › J25 N'affecte pas CONSOL_CR (traitement OCI IFRS) | D45: Surveiller si devises volatiles (GBP, USD, SGD) Significatif si > 5% des CP | E45: En OCI = impact uniquement sur les Capitaux Propres du bilan. Couvrir si exposition > 10 M€.
A47: ❓ SECTION E — FAQ — 8 QUESTIONS FRÉQUENTES DES DÉBUTANTS
A48: ❓ Question | B48: ✅ Réponse complète | D48: Onglet de résolution | E48: Priorité
A49: TOTAL ACTIF dans DE_Filiale est à zéro ou vide | B49: Les données N n'ont pas été saisies dans SRC_DE. → Aller dans SRC_DE et renseigner les balances comptables (colonnes A et suivantes). → Puis relancer ToutRafraichir (onglet HOME). Les formules de DE_Filiale pointent vers SRC_DE via Power Query : sans données sources, tout est à zéro. | D49: SRC_DE HOME | E49: 🔴 Bloquant
A50: J'ai modifié un taux de change mais le bilan ne se met pas à jour | B50: Les Power Query ne se rechargent pas automatiquement à chaque saisie — c'est voulu pour éviter les ralentissements. → Cliquer sur le bouton ToutRafraichir (onglet HOME) ou Ctrl+Alt+F5 (Données → Actualiser tout). Les connexions PQ doivent être rafraîchies pour propager les nouveaux taux dans toutes les formules de conversion. | D50: HOME PQ_TAUX_CHANGE | E50: 🟡 Normal
A51: CONSOL_BILAN affiche « 🚨 DÉSÉQUILIBRE » | B51: Vérifier dans l'ordre : ① ELIM §1 : Total créances IC ≈ Total dettes IC ? (doit être quasi-égal) ② ELIM §2 : Titres de participation vs Goodwill — calcul cohérent ? ③ Données saisies en double dans un SRC_* ? ④ Alt+F8 → ValiderFiliales() → lire le rapport diagnostic RAG L'écart résiduel < 1 000 k€ peut provenir des écarts de conversion IAS 21 sur IC (acceptable). | D51: ELIM CONSOL_BILAN | E51: 🔴 Bloquant
A52: Quelle différence entre EBIT et « Profit avant Fin. & Impôts » ? | B52: C'est une nouveauté IFRS 18 (obligatoire depuis 2027) : › EBIT = Résultat Opérationnel = Catégorie ① uniquement (activités d'exploitation) › Profit avant Fin. & Impôts = EBIT + Résultat Investissement = Catégories ① + ② = Nouveau sous-total obligatoire IFRS 18 §48 (ligne 24 de CONSOL_CR) Concrètement : dividendes reçus de participantes non-contrôlées s'ajoutent à l'EBIT. | D52: CONSOL_CR ligne 24 | E52: 🟢 Info
A53: Comment analyser UNE SEULE entité sans tout consolider ? | B53: Aller directement sur l'onglet de l'entité : › FR_ParentCo, DE_Filiale, UK_Filiale, US_Filiale ou SG_Filiale Chaque onglet contient : • Bilan local (en monnaie locale + converti EUR) • Compte de résultat local • Tableau de conversion IAS 21 (actif, passif, P&L) • Indicateurs de base (CA, EBIT, RN local) | D53: FR_ParentCo DE_Filiale UK_Filiale US_Filiale SG_Filiale | E53: 🟢 Info
A54: Un solde résiduel de ~1 000 k€ reste dans le bilan consolidé sur les IC UK | B54: C'est un écart de change IC intentionnel : La créance IC est libellée en GBP (convertie au taux clôture) mais la dette IC correspondante est déjà en EUR. L'écart résiduel = effet devise UK → traitement recommandé : › Option A : reclasser en Écart de conversion (OCI, CONSOL_BILAN J25) › Option B : éliminer via une écriture manuelle dans ELIM §1 Ce sujet est documenté dans Méthodologie & Pédagogie › §4 Éliminations. | D54: ELIM CONSOL_BILAN J25 Méthodologie §4 | E54: 🟡 À surveiller
A55: Comment utiliser ce fichier pour valoriser une entreprise réelle ? | B55: Étapes supplémentaires pour une analyse en conditions réelles : ① Collecter les 5 derniers exercices annuels (N, N-1, N-2, N-3, N-4) ② Saisir les données dans SRC_* pour chaque exercice (dupliquer le fichier par exercice) ③ Calculer les CAGR sur CA, EBITDA, RN ④ Construire un DCF sur CONSOL_TRESORERIE : projeter 5 ans + valeur terminale ⑤ Comparer les multiples (EV/EBITDA, P/E) aux pairs cotés ⑥ Exporter PDF et présenter en board / comité d'investissement | D55: Tous les onglets CONSOL_* | E55: 🟣 Avancé
A56: Comment mentionner ce fichier dans mon CV ou en entretien ? | B56: Formulation recommandée pour CV ou LinkedIn : « Conception et modélisation d'un simulateur Excel de consolidation IFRS 18 : 5 entités multinationales (FR/DE/UK/US/SG), conversion IAS 21, éliminations interco, états financiers consolidés (bilan, CR, trésorerie), Power Query, KPIs ESG/CSRD, VBA et macros d'automatisation. » Compétences valorisées : Finance / Consolidation / Audit / Contrôle de gestion / Trésorerie groupe Suppléer avec le fichier .xlsm en pièce jointe lors d'entretiens techniques. | D56: — | E56: 💼 Carrière
A58: ⌨️ SECTION F — CARTE DE RÉFÉRENCE RAPIDE — Raccourcis et onglets essentiels
A59: Raccourci / Action | B59: Résultat | C59: Quand l'utiliser ? | D59: Astuce complémentaire
A60: Ctrl + F | B60: Rechercher du texte dans tout l'onglet actif | C60: Retrouver un poste comptable ou une cellule précise | D60: Cocher « Dans le classeur entier » pour chercher dans tous les onglets.
A61: Ctrl + Alt + F5 | B61: Actualiser TOUTES les connexions Power Query manuellement | C61: Si le bouton ToutRafraichir ne répond pas | D61: Équivalent à Données → Actualiser tout dans le ruban.
A62: Alt + F8 | B62: Ouvrir la liste des macros VBA disponibles | C62: Pour lancer ToutRafraichir, ValiderFiliales ou ExporterPDF | D62: Sélectionner la macro voulue → cliquer Exécuter.
A63: Alt + F11 | B63: Ouvrir l'éditeur de code VBA | C63: Pour consulter ou modifier le code macro | D63: Ne modifier le code que si vous maîtrisez VBA. Sinon : lecture seule.
A64: Ctrl + Début / Fin | B64: Aller au début / à la fin de la zone de données | C64: Navigation rapide dans les grands tableaux (SRC_*, CONSOL_*) | D64: Ctrl+Maj+Fin sélectionne toute la plage de données.
A65: Ctrl + clic onglet | B65: Sélectionner plusieurs onglets simultanément | C65: Pour imprimer ou exporter en PDF plusieurs onglets d'un coup | D65: Fichier → Imprimer → Tous les onglets sélectionnés.
A66: F9 | B66: Recalculer toutes les formules manuellement | C66: Si le mode de calcul est en « Manuel » (rare) | D66: Vérifier : Formules → Options de calcul → doit être sur « Automatique ».
A67: Ctrl + Z | B67: Annuler la dernière action | C67: Après toute modification accidentelle | D67: ⚠️ Annule aussi les modifications de formules. Sauvegarder avant tout test.
A68: Ctrl + S | B68: Enregistrer le fichier | C68: Après chaque saisie importante | D68: Enregistrer régulièrement pour ne pas perdre les données saisies dans SRC_*.
A69: HOME → bouton 🔄 | B69: Lancer ToutRafraichir (PQ + recalcul + dashboards + log) | C69: À chaque fois que vous ajoutez ou modifiez des données | D69: Le bouton est en haut de l'onglet HOME, couleur orange.
A71: 🎓 Vous êtes maintenant prêt(e) à analyser des données financières consolidées IFRS 18 comme un analyste senior. Bonne analyse !

Sheet GUIDE
B2: 📘 GUIDE UTILISATEUR – CONVENTIONS & PÉDAGOGIE IFRS 18
B5: 1. LÉGENDE DES COULEURS & CONVENTIONS DE SAISIE
B6: Couleur fond | C6: Usage | D6: Règle de saisie | E6: Exemple
B7: 🟩 Vert clair (#D5E8D4) | C7: Cellules source saisie | D7: Données manuelles ou importées | E7: Chiffre d'affaires entité FR
B8: 🔵 Bleu clair (#DAE8FC) | C8: Cellules de calcul | D8: NE PAS MODIFIER – formules auto | E8: Total consolidé agrégé
B9: 🟠 Orange (#FFE6CC) | C9: Dashboards KPIs | D9: Lecture seule – graphiques dyn. | E9: Marge EBITDA groupe
B10: 🟨 Jaune (#FFFF88) | C10: Hypothèses clés | D10: Paramètres sensibles – documenter | E10: Taux de change GBP/EUR
B12: 2. IFRS 18 – NOUVEAUTÉS (Application 2027, préparation 2025-2026)
B13: Nouveauté IFRS 18 | C13: Ancien (IAS 1) | D13: Nouveau traitement | E13: Impact consolidation
B14: 5 catégories P&L obligatoires | C14: Présentation libre | D14: Opérationnel / Invest. / Financement / Impôts / Discontinu | E14: Reclassement total requis
B15: Sous-totaux imposés | C15: Facultatifs | D15: Profit avant financement & impôt obligatoire | E15: Nouveau KPI groupe clé
B16: Management Performance Measures | C16: Non encadrées | D16: Divulgation & réconciliation obligatoires | E16: Notes annexes renforcées
B17: Résultat opérationnel isolé | C17: Résultat courant libre | D17: Charges/produits non opérationnels exclus | E17: Séparation stricte analytique
B18: Investissement (Investing) | C18: Intégré résultat global | D18: Produits d'actifs non opérationnels isolés | E18: Isolation des flux invest.
B20: 3. ESG / CSRD – CADRE RÉGLEMENTAIRE & ESRS
B21: Pilier CSRD/ESRS | C21: Standards applicables | D21: Indicateurs couverts dans ce fichier
B22: E – Environnement | C22: ESRS E1 (Climat), E2 (Pollution), E4 (Biodiv.) | D22: CO₂ scope 1-2-3, énergie renouvelable, déchets
B23: S – Social | C23: ESRS S1 (Employés), S2 (Chaîne val.) | D23: Effectifs, parité H/F, accidents, formation
B24: G – Gouvernance | C24: ESRS G1 (Éthique, conduite affaires) | D24: Diversité CA, politique anti-corruption, alertes
B25: CSRD Scope | C25: Entreprises > 500 salariés ou cotées | D25: Rapport de durabilité obligatoire dès 2025
B27: 4. WORKFLOW DE CONSOLIDATION – ORDRE DE SAISIE RECOMMANDÉ
B28: Étape | C28: Onglet(s) | D28: Action
B29: ① Paramétrer les taux de change | C29: FR_ParentCo (zone paramètres) | D29: Saisir les taux de clôture et moyens par devise
B30: ② Saisir les liasses locales | C30: FR / DE / UK / US / SG | D30: Importer ou saisir balances par entité
B31: ③ Contrôler les flux intercos | C31: ELIM | D31: Vérifier et valider les éliminations automatiques
B32: ④ Vérifier la consolidation | C32: CONSOL_BILAN / CONSOL_CR | D32: Contrôler la balance des états financiers
B33: ⑤ Compléter le mapping IFRS 18 | C33: IFRS18_MAPPING | D33: Reclasser les postes selon les 5 catégories
B34: ⑥ Saisir les données ESG | C34: ESG_DATA | D34: Renseigner les KPIs environnementaux, sociaux, gouvernance
B35: ⑦ Analyser les dashboards | C35: DASHBOARD_FIN / DASHBOARD_ESG | D35: Lire les indicateurs et partager le rapport

Sheet Méthodologie & Pédagogie
A1: 📚 MÉTHODOLOGIE & PÉDAGOGIE – GUIDE COMPLET DU SIMULATEUR IFRS 18 / CONSOLIDATION / ESG
A2: Simulateur de Consolidation · Groupe Multinational · 5 Entités · IFRS 18 | IAS 21 | IFRS 3 | ESG/CSRD · Exercice 2025–2026
A4: 📋 TABLE DES MATIÈRES
A5: Réf. | B5: Section | C5: Ligne de départ | D5: Description rapide
A6: §1 | B6: IFRS 18 – Présentation des États Financiers | C6: ~Ligne 15 | D6: Nouveau standard 2027 – 5 catégories P&L obligatoires
A7: §2 | B7: IAS 21 – Effets des variations des taux de change | C7: ~Ligne 50 | D7: Conversion des filiales étrangères en EUR
A8: §3 | B8: IFRS 3 – Regroupements d'entreprises | C8: ~Ligne 80 | D8: Goodwill, PPA, Intérêts minoritaires
A9: §4 | B9: Éliminations intercompagnies | C9: ~Ligne 110 | D9: IC transactions, dividendes, prêts intragroupe
A10: §5 | B10: Méthode de consolidation – Workflow complet | C10: ~Ligne 140 | D10: Ordre et logique du processus de consolidation
A11: §6 | B11: Power Query – Architecture & logique M | C11: ~Ligne 165 | D11: Automatisation et modélisation des flux de données
A12: §7 | B12: ESG / CSRD – Cadre réglementaire ESRS | C12: ~Ligne 190 | D12: ESRS E1/S1/G1 – Scope 1-2-3 CO2
A13: §8 | B13: Glossaire CCA | C13: ~Ligne 215 | D13: 60+ termes de consolidation définis
A14: §9 | B14: Schémas & Flux (texte structuré) | C14: ~Ligne 270 | D14: Workflow visuel de consolidation
A15: §10 | B15: Audit Trail – Traçabilité des calculs | C15: ~Ligne 315 | D15: Références croisées et contrôles qualité
A17: §1 IFRS 18 – PRÉSENTATION DES ÉTATS FINANCIERS (en vigueur 2027, préparation 2025-2026)
A18: IFRS 18 remplace IAS 1 – Il impose une structure OBLIGATOIRE du P&L en 5 catégories, interdit les catégories propriétaires, et exige la réconciliation des Management Performance Measures (MPM) en annexe. Application obligatoire 1er janv. 2027 (comparatif 2026).
A20: Catégorie IFRS 18 | B20: § Référence | C20: Contenu obligatoire | D20: Exemples dans le Groupe | E20: vs IAS 1 ancien
A21: ① EXPLOITATION | B21: §45-55 | C21: Revenus IFRS 15, coûts directs, charges d'exploitation, DAP actifs opérationnels | D21: CA, Achats, Salaires, DAP PP&E — 5 entités du groupe | E21: Résultat courant (non défini normativement)
A22: ② INVESTISSEMENT | B22: §56-68 | C22: Produits/charges d'actifs NON utilisés dans l'exploitation principale. Rendements financiers. | D22: Dividendes IC reçus, plus-values cessions, produits placements CT | E22: Résultat financier (mélangé avec financement)
A23: ③ FINANCEMENT | B23: §69-72 | C23: Coûts de financement des passifs financiers : intérêts emprunts bancaires + intérêts dettes locatives IFRS 16 | D23: Charges intérêts LT, intérêts baux IFRS 16 — toutes entités | E23: Résultat financier (non séparé de investing)
A24: ④ IMPÔTS | B24: §73-80 | C24: IS courant (IAS 12) + impôts différés. TOUJOURS présenté séparément. Ne peut pas être noyé dans une autre catégorie. | D24: Charge IS courant + variation DTA/DTL par entité | E24: Ligne IS dans résultat courant (similaire)
A25: ⑤ DISCONTINU | B25: §81-85 | C25: Résultat net post-IS des activités abandonnées IFRS 5. UNE SEULE ligne nette dans le P&L. | D25: Non applicable ex. 2025 – prévu pour extensions futures | E25: Résultat net séparé (similaire mais non codifié)
A27: 📌 MANAGEMENT PERFORMANCE MEASURES (MPM) – Nouveauté clé IFRS 18
A28: Définition MPM : | B28: Tout sous-total de résultat communiqué EXTERNEMENT par la direction et NON requis par IFRS 18 (ex: EBITDA ajusté, résultat opérationnel courant, résultat récurrent, résultat sous-jacent)
A29: Obligation : | B29: Divulgation OBLIGATOIRE en annexe avec réconciliation ligne-à-ligne vers le sous-total IFRS 18 le plus proche (§B1-B12). Interdit de mettre les MPM en face avant du P&L.
A30: Impact Groupe : | B30: L'EBITDA Groupe des dashboards DOIT être réconcilié vers Résultat opérationnel §47. Onglet NOTES_IFRS lignes 15-22.
A31: Onglets liés : | B31: IFRS18_MAPPING colonnes F:J → NOTES_IFRS B15:B22 → CONSOL_CR lignes sous-totaux
A32: Référence : | B32: IFRS 18 §B1-B12 (Guide d'application) + IASB Exposure Draft avril 2019 → Standard final avril 2024
A33: 📊 SCHÉMA P&L IFRS 18 – SOUS-TOTAUX OBLIGATOIRES (§47-48)
A34: Catégories ① | B34: Produits d'exploitation (IFRS 15 + autres) | C34: xxx €
B35: – Charges d'exploitation, salaires, DAP | C35: (xxx €)
A36: SOUS-TOTAL ① | B36: ═══ RÉSULTAT D'EXPLOITATION ═══ | C36: xxx € | D36: ⬅ OBLIGATOIRE §47
A37: Catégories ② | B37: + Produits d'investissement (dividendes, plus-values) | C37: +xxx €
A38: SOUS-TOTAL ①+② | B38: ═══ RÉSULTAT AVANT FINANCEMENT & IMPÔTS ═══ | C38: xxx € | D38: ⬅ NOUVEAU §48
A39: Catégories ③ | B39: – Charges de financement (intérêts, IFRS 16) | C39: (xxx €)
A40: SOUS-TOTAL ①+②+③ | B40: ═══ RÉSULTAT AVANT IMPÔTS ═══ | C40: xxx € | D40: ⬅ Classique
A41: Catégories ④ | B41: – Charge d'impôt (IS courant + différé) | C41: (xxx €)
B42: ═══ RÉSULTAT DES ACTIVITÉS POURSUIVIES ═══ | C42: xxx €
A43: Catégories ⑤ | B43: + Résultat activités abandonnées (net IS) | C43: ±xxx €
A44: RÉSULTAT NET | B44: ═══ RÉSULTAT NET CONSOLIDÉ ═══ | C44: xxx € | D44: ⬅ BOTTOM LINE
A47: §2 IAS 21 – EFFETS DES VARIATIONS DES TAUX DE CHANGE (Conversion des filiales étrangères)
A48: IAS 21 régit la conversion des états financiers d'une entité étrangère dans la devise de présentation du groupe (EUR). Le principe central: actifs/passifs au taux de CLÔTURE, produits/charges au taux MOYEN, capitaux propres au taux HISTORIQUE. Les écarts de conversion vont en OCI (non recyclable en P&L).
A50: Poste du bilan/P&L | B50: Taux applicable | C50: § IAS 21 | D50: Justification normative | E50: Application dans le fichier
A51: Actifs non courants (PP&E, GW) | B51: CLÔTURE §23 | C51: §23 | D51: Refléter la valeur actuelle en devise de présentation | E51: PQ_TAUX_CHANGE → TypeTaux=Clôture
A52: Passifs financiers (dettes LT, CT) | B52: CLÔTURE §23 | C52: §23 | D52: Synchronisation bilan : actifs & passifs au même taux | E52: PQ_TAUX_CHANGE → col. TauxEUR
A53: Créances, dettes d'exploitation | B53: CLÔTURE §23 | C53: §23 | D53: Même principe – éléments monétaires au taux de clôture | E53: BALANCES_PQ → col. TauxCloture
A54: Chiffre d'affaires & charges P&L | B54: MOYEN §39 | C54: §39 | D54: Approximation des taux historiques quotidiens sur l'exercice | E54: PQ_TAUX_CHANGE → TypeTaux=Moyen,Mois=AN
A55: Capitaux propres (hors résultat) | B55: HISTORIQUE §39 | C55: §39 | D55: Maintenir les apports en capital à leur valeur d'origine | E55: PQ_TAUX_CHANGE → TypeTaux=Historique
A56: Écart de conversion (résultant) | B56: → OCI §41 | C56: §41 | D56: Différence non recyclable : taux clôture vs taux historique CP | E56: Onglet CONSOL_BILAN → ligne Écart de conv.
A58: 💱 SYNTHÈSE DES DEVISES DU GROUPE & TAUX EXERCICE 2025
A59: Entité | B59: Devise locale | C59: Taux Clôture (EUR) | D59: Taux Moyen annuel | E59: Taux Historique | F59: Écart de conversion estimé
A60: FR_ParentCo | B60: EUR | C60: 1.000 (devise présen.) | D60: 1 | E60: 1 | F60: Néant – devise de présentation
A61: DE_Filiale | B61: EUR | C61: 1.000 (zone euro) | D61: 1 | E61: 1 | F61: Néant – même devise
A62: UK_Filiale | B62: GBP | C62: 1.165 GBP/EUR | D62: 1.155 (moyen 2025) | E62: 1.120 (acq. mars 2020) | F62: OCI positif (GBP apprécié)
A63: US_Filiale | B63: USD | C63: 0.918 USD/EUR | D63: 0.925 (moyen 2025) | E63: 0.845 (acq. 2021) | F63: OCI positif (USD revalorisation CP)
A64: SG_Filiale | B64: SGD | C64: 0.678 SGD/EUR | D64: 0.682 (moyen 2025) | E64: 0.650 (acq. 2022) | F64: OCI positif (SGD légère appréc.)
A67: §3 IFRS 3 – REGROUPEMENTS D'ENTREPRISES (Goodwill, PPA, Intérêts Minoritaires)
A68: IFRS 3 définit la méthode de l'acquisition (method of acquisition). Le Goodwill = Prix acquisition – Juste valeur de l'actif net identifiable (PPA). Les intérêts minoritaires (NCI) représentent la quote-part des actionnaires non-contrôlants dans les fonds propres et le résultat.
A70: Filiale | B70: % Détenu | C70: Prix acquisition | D70: Actif net JV | E70: Goodwill brut | F70: Dépréc. GW cum. | G70: Goodwill net
A71: DE_Filiale (Allemagne) | B71: 1 | C71: 85 000 k€ | D71: 62 000 k€ | E71: 23 000 k€ | F71: 3 500 k€ | G71: 19 500 k€
A72: UK_Filiale (Royaume-Uni) | B72: 0.8 | C72: 72 000 k€ | D72: 48 500 k€ | E72: 23 500 k€ | F72: 4 200 k€ | G72: 19 300 k€
A73: US_Filiale (États-Unis) | B73: 0.75 | C73: 95 000 k€ | D73: 71 000 k€ | E73: 24 000 k€ | F73: 5 800 k€ | G73: 18 200 k€
A74: SG_Filiale (Singapour) | B74: 0.6 | C74: 38 000 k€ | D74: 28 500 k€ | E74: 9 500 k€ | F74: 1 200 k€ | G74: 8 300 k€
A75: TOTAL GROUPE | C75: 290 000 k€ | D75: 210 000 k€ | E75: 80 000 k€ | F75: 14 700 k€ | G75: 65 300 k€
A77: 📌 INTÉRÊTS MINORITAIRES (NCI) – Traitement IFRS 3
A78: NCI Bilan : | B78: Quote-part NCI dans actif net consolidé. UK: 20% × AN JV = 9 700k€. US: 25% × AN JV = 17 750k€. SG: 40% × AN JV = 11 400k€.
A79: NCI P&L : | B79: Quote-part NCI dans résultat net de la filiale. Présenté SÉPARÉMENT sous le résultat net consolidé (IFRS 18 §88).
A80: Goodwill méthode : | B80: Méthode du Goodwill PARTIEL utilisée (sur la quote-part acquise uniquement). La méthode du Goodwill INTÉGRAL est une option IFRS 3.
A81: Test dépréciation : | B81: IAS 36 – Test goodwill annuel obligatoire par UGT. Dépréciations non réversibles. Onglet ELIM lignes 14-18.
A84: §4 ÉLIMINATIONS INTERCOMPAGNIES – Principes & Mécanismes
A85: Les États Financiers Consolidés présentent le Groupe comme UNE SEULE entité économique. Toutes les transactions INTERNES au groupe doivent être éliminées pour éviter les doubles comptages. 3 catégories d'éliminations: (1) Créances/Dettes IC, (2) Résultats IC internes, (3) Titres de participation vs capitaux propres.
A87: Type d'élimination | B87: Référence IC | C87: Montant (k€ EUR) | D87: Écriture d'élimination | E87: Onglet source
A88: Ventes IC marchandises FR→DE | B88: IC-2025-001 | C88: 18 500 k€ | D88: DR Ventes IC / CR Achats IC → impact P&L nul | E88: ELIM §1 ligne 6
A89: Ventes IC marchandises FR→UK | B89: IC-2025-002 | C89: 14 446 k€ | D89: DR Ventes IC / CR Achats IC (converties en EUR) | E89: ELIM §1 ligne 7
A90: Management fees FR→US | B90: IC-2025-003 | C90: 7 803 k€ | D90: DR Produits services IC / CR Charges services IC | E90: ELIM §1 ligne 8
A91: Prêt interco FR→SG | B91: IC-2025-004 | C91: 3 526 k€ | D91: DR Créance fin. IC / CR Dette fin. IC → nul au bilan | E91: ELIM §1 ligne 9
A92: Dividendes IC DE→FR | B92: IC-2025-005 | C92: 4 200 k€ | D92: DR Produits fin. IC / CR Dividendes versés IC → nul P&L | E92: ELIM §1 ligne 10
A93: Dividendes IC UK→FR | B93: IC-2025-006 | C93: 3 262 k€ | D93: Idem (⚠ à vérifier – taux GBP) | E93: ELIM §1 ligne 11
A94: Provision risque IC FR→SG | B94: IC-2025-007 | C94: 1 500 k€ | D94: DR Provision actif IC / CR Risque passif IC | E94: ELIM §1 ligne 12
A95: Titres de participation →CP | B95: IFRS 3 §32 | C95: Voir §3 ci-dessus | D95: DR Capital filiale / CR Titres participation → Goodwill résiduel | E95: ELIM §2 lignes 15-18
A98: §5 WORKFLOW DE CONSOLIDATION – PROCESSUS COMPLET EN 7 ÉTAPES
A99: Étape | B99: Nom & Icône | C99: Onglets concernés | D99: Description détaillée
A100: ÉTAPE 1 | B100: 📥 Import & Paramétrage | C100: Onglets SRC_FR/DE/UK/US/SG + PQ_TAUX_CHANGE | D100: Charger les balances locales en devise locale. Saisir taux de clôture, moyen, historique. Validation des totaux.
A101: ÉTAPE 2 | B101: 🔄 Power Query – Normalisation | C101: PQ_MAPPING + BALANCES_PQ | D101: Power Query normalise les balances, applique les taux IAS 21, aligne les plans de comptes sur le référentiel Groupe.
A102: ÉTAPE 3 | B102: 🔢 Agrégation des entités | C102: BALANCES_PQ + FORMULES_LIAISON | D102: Cumul des balances converties en EUR pour les 5 entités. Vérification: Total Actifs = Total Passifs pour chaque entité.
A103: ÉTAPE 4 | B103: ✂️ Éliminations IC | C103: ELIM + PQ_ELIMINATIONS | D103: Application des 7 écritures d'élimination. Contrôle: Créances IC groupe = Dettes IC groupe (écart = 0 ou différence de change).
A104: ÉTAPE 5 | B104: 📊 États financiers consolidés | C104: CONSOL_BILAN + CONSOL_CR + CONSOL_TRESORERIE | D104: Calcul automatique des états consolidés. Contrôle de la balance, du résultat net, de la trésorerie nette.
A105: ÉTAPE 6 | B105: 🗺️ Reclassement IFRS 18 | C105: IFRS18_MAPPING + NOTES_IFRS | D105: Affectation de chaque poste du P&L aux 5 catégories IFRS 18. Calcul des sous-totaux obligatoires §47-48.
A106: ÉTAPE 7 | B106: 📈 Dashboards & Reporting | C106: DASHBOARD_FIN + DASHBOARD_ESG + CSRD_RAPPORT | D106: Lecture des KPIs, graphiques dynamiques, rapport de durabilité CSRD. Partage avec la direction.
A109: §6 POWER QUERY – ARCHITECTURE & LOGIQUE M (Automatisation de la consolidation)
A110: Power Query (langage M) automatise la chaîne ETL de consolidation: Extract (sources locales SRC_*), Transform (normalisation, conversion devise, mapping comptes), Load (BALANCES_PQ consolidé). Chaque requête est documentée dans PQ_CODE. Le rafraîchissement global = 1 clic bouton ToutRafraichir.
A112: Requête PQ | B112: Rôle | C112: Source → Destination | D112: Logique M principale
A113: PQ_Balances_FR | B113: Import & normalisation FR | C113: SRC_FR → BALANCES_PQ | D113: Table.SelectRows, Table.TransformColumnTypes, jointure taux IAS 21
A114: PQ_Balances_DE/UK/US/SG | B114: Import 4 filiales étrangères | C114: SRC_DE/UK/US/SG → BALANCES_PQ | D114: Même logique + multiplication ColMontant × TauxEUR selon TypeTaux
A115: PQ_MAPPING | B115: Correspondance plans de comptes | C115: IFRS18_MAPPING → BALANCES_PQ | D115: Table.Join sur CodeCompte pour ajouter catégorie IFRS 18 et libellé consolidé
A116: PQ_ELIMINATIONS | B116: Calcul des éliminations IC | C116: ELIM → table d'éliminations nettes | D116: Agrégation par TypeIC + EntiteVendeuse/Acheteuse → montants à soustraire
A117: PQ_TAUX_CHANGE | B117: Table de référence des taux | C117: Saisie manuelle → toutes requêtes | D117: Table pivot: Devise × TypeTaux → TauxEUR (utilisé par jointure dans toutes requêtes)
A118: PQ_DETENTION | B118: Table des % de détention | C118: ELIM §2 → calcul NCI | D118: Pourcentages par filiale → calcul quote-part NCI bilan & P&L
A121: §7 ESG / CSRD – CADRE RÉGLEMENTAIRE & ESRS (European Sustainability Reporting Standards)
A122: La CSRD (Corporate Sustainability Reporting Directive) impose aux grandes entreprises européennes un rapport de durabilité selon les ESRS. Applicable depuis 2025 pour les entreprises > 500 salariés ou cotées. Ce simulateur couvre les piliers E (Environnement), S (Social), G (Gouvernance) selon les ESRS EFRAG.
...

Sheet FR_ParentCo
B2: 🇫🇷 FR_ParentCo – SOCIÉTÉ MÈRE FRANCE · Liasse Comptable Locale · Exercice 2025-2026
B4: ⚙️ PARAMÈTRES ENTITÉ
B5: Entité : | C5: FR_ParentCo – Holding Groupe
B6: Pays / Devise : | C6: France · EUR (€)
B7: % Détention : | C7: 100% – Société Mère
B8: Méthode : | C8: Intégration Globale
B9: Taux de clôture : | C9: 1.0000 (EUR/EUR)
B10: Taux moyen : | C10: 1.0000 (EUR/EUR)
B11: Exercice : | C11: 01/01/2025 – 31/12/2025
B13: BILAN CONSOLIDÉ LOCAL – ACTIF (en k€) | I13: BILAN – PASSIF (en k€)
B14: Poste IFRS | C14: Compte | D14: N (2025) k€ | E14: N-1 (2024) k€ | F14: Δ k€ | G14: Note | I14: Poste IFRS | J14: Compte | K14: N (2025) k€ | L14: N-1 (2024) k€ | M14: Δ k€ | N14: Note
B15: ACTIFS NON COURANTS | I15: CAPITAUX PROPRES
B16: Immobilisations incorporelles (GW inclus) | C16: 21xx | D16: 85000 | E16: 82000 | F16: =D16-E16 -> 3000 | G16: Note 3 – GW | I16: Capital social | J16: 101x | K16: 50000 | L16: 50000
B17: Immobilisations corporelles (PP&E) | C17: 22xx | D17: 142000 | E17: 138500 | F17: =D17-E17 -> 3500 | G17: IFRS 16 | I17: Primes d'émission & réserves | J17: 104x-106x | K17: 128500 | L17: 115200
B18: Actifs droits d'utilisation (IFRS 16) | C18: 232x | D18: 28500 | E18: 31200 | F18: =D18-E18 -> -2700 | G18: Baux | I18: Résultat de l'exercice | J18: 120x | K18: 32800 | L18: 28400 | N18: Lié au CR
B19: Participations & titres mis en équivalence | C19: 261x | D19: 95000 | E19: 90000 | F19: =D19-E19 -> 5000 | G19: Méthode MEE | I19: Autres réserves / OCI (IFRS 9 & IAS 19) | J19: 10xx | K19: -4200 | L19: -3100 | N19: IAS 19
B20: Impôts différés actifs | C20: 274x | D20: 12400 | E20: 11800 | F20: =D20-E20 -> 600 | G20: IAS 12 | I20: Intérêts minoritaires (NCI) | J20: 1044 | K20: 18700 | L20: 16900 | N20: IFRS 10
B21: Autres actifs non courants | C21: 27xx | D21: 8500 | E21: 7200 | F21: =D21-E21 -> 1300 | I21: TOTAL CAPITAUX PROPRES | K21: =SUM(K16:K20) -> 225800 | L21: =SUM(L16:L20) -> 207400 | M21: =K21-L21 -> 18400
B22: TOTAL ACTIFS NON COURANTS | D22: =SUM(D16:D21) -> 371400 | E22: =SUM(E16:E21) -> 360700 | F22: =D22-E22 -> 10700 | I22: PASSIFS NON COURANTS
B23: ACTIFS COURANTS | I23: Emprunts & dettes financières LT | J23: 164x | K23: 125000 | L23: 132000 | N23: IFRS 9
B24: Stocks & en-cours | C24: 31xx-35xx | D24: 45200 | E24: 43800 | F24: =D24-E24 -> 1400 | G24: IAS 2 | I24: Dettes locatives LT (IFRS 16) | J24: 1674 | K24: 22800 | L24: 25600 | N24: IFRS 16
B25: Créances clients & comptes rattachés | C25: 411x | D25: 67800 | E25: 71200 | F25: =D25-E25 -> -3400 | G25: IFRS 9 | I25: Provisions pour risques LT | J25: 151x | K25: 15400 | L25: 14200 | N25: IAS 37
B26: Créances intercompagnies | C26: 451x | D26: 23500 | E26: 19800 | F26: =D26-E26 -> 3700 | G26: ⚠️ ELIM | I26: Impôts différés passifs | J26: 155x | K26: 18900 | L26: 17500 | N26: IAS 12
B27: Autres créances & charges constatées d'avance | C27: 408x-486x | D27: 8900 | E27: 7600 | F27: =D27-E27 -> 1300 | I27: TOTAL PASSIFS NON COURANTS | K27: =SUM(K23:K26) -> 182100 | L27: =SUM(L23:L26) -> 189300 | M27: =K27-L27 -> -7200
B28: Trésorerie & équivalents | C28: 512x-530x | D28: 54300 | E28: 48700 | F28: =D28-E28 -> 5600 | G28: IAS 7 | I28: PASSIFS COURANTS
B29: TOTAL ACTIFS COURANTS | D29: =SUM(D24:D28) -> 199700 | E29: =SUM(E24:E28) -> 191100 | F29: =D29-E29 -> 8600 | I29: Dettes fournisseurs & comptes rattachés | J29: 401x | K29: 38200 | L29: 35600
B30: TOTAL ACTIF | D30: =D22+D29 -> 571100 | E30: =E22+E29 -> 551800 | F30: =D30-E30 -> 19300 | G30: ✔ Équilibre | I30: Dettes financières CT & lignes de crédit | J30: 519x | K30: 28500 | L30: 22300
I31: Dettes intercompagnies | J31: 451x | K31: 21400 | L31: 18200 | N31: ⚠️ ELIM
I32: Autres dettes & produits constatés d'avance | J32: 487x | K32: 12800 | L32: 11400
I33: TOTAL PASSIFS COURANTS | K33: =SUM(K29:K32) -> 100900 | L33: =SUM(L29:L32) -> 87500 | M33: =K33-L33 -> 13400
I34: TOTAL PASSIF | K34: =K21+K27+K33 -> 508800 | L34: =L21+L27+L33 -> 484200 | M34: =K34-L34 -> 24600 | N34: ✔ Équilibre
B36: COMPTE DE RÉSULTAT LOCAL – IFRS 18 (5 catégories) (en k€)
B37: Poste IFRS 18 | C37: Catégorie | D37: N (2025) k€ | E37: N-1 (2024) k€ | F37: Δ % | G37: Note IFRS
B38: ① EXPLOITATION (OPERATING)
B39: Chiffre d'affaires net | C39: Opérationnel | D39: 285000 | E39: 268000 | F39: =IFERROR((D39-E39)/ABS(E39),"") -> 0.063432836 | G39: IFRS 15
B40: Variation de stocks de produits finis | C40: Opérationnel | D40: 1800 | E40: -2100 | F40: =IFERROR((D40-E40)/ABS(E40),"") -> 1.8571429 | G40: IAS 2
B41: Autres produits opérationnels | C41: Opérationnel | D41: 3200 | E41: 2800 | F41: =IFERROR((D41-E41)/ABS(E41),"") -> 0.14285714
B42: Achats consommés & charges externes | C42: Opérationnel | D42: -142000 | E42: -135000 | F42: =IFERROR((D42-E42)/ABS(E42),"") -> -0.051851852
B43: Charges de personnel | C43: Opérationnel | D43: -68000 | E43: -64500 | F43: =IFERROR((D43-E43)/ABS(E43),"") -> -0.054263566 | G43: IAS 19
B44: Amortissements (PP&E + DU IFRS 16) | C44: Opérationnel | D44: -22000 | E44: -21200 | F44: =IFERROR((D44-E44)/ABS(E44),"") -> -0.037735849 | G44: IAS 16/36
B45: Dotations aux provisions | C45: Opérationnel | D45: -4500 | E45: -3800 | F45: =IFERROR((D45-E45)/ABS(E45),"") -> -0.18421053 | G45: IAS 37
B46: RÉSULTAT OPÉRATIONNEL (EBIT) | C46: Opérationnel | D46: =SUM(D39:D45) -> 53500 | E46: =SUM(E39:E45) -> 44200 | F46: =IFERROR((D46-E46)/ABS(E46),"") -> 0.21040724 | G46: 🔑 KPI IFRS 18
B47: ② INVESTISSEMENT (INVESTING)
B48: Dividendes reçus (hors exploitation) | C48: Investissement | D48: 4200 | E48: 3800 | F48: =IFERROR((D48-E48)/ABS(E48),"") -> 0.10526316 | G48: IFRS 18 §68
B49: Produits des cessions d'actifs | C49: Investissement | D49: 1500 | E49: 800 | F49: =IFERROR((D49-E49)/ABS(E49),"") -> 0.875 | G49: IFRS 18 §68
B50: Produits financiers sur placements CT | C50: Investissement | D50: 890 | E50: 620 | F50: =IFERROR((D50-E50)/ABS(E50),"") -> 0.43548387 | G50: IFRS 18 §68
B51: RÉSULTAT INVESTISSEMENT | C51: Investissement | D51: =SUM(D48:D50) -> 6590 | E51: =SUM(E48:E50) -> 5220 | F51: =IFERROR((D51-E51)/ABS(E51),"") -> 0.26245211
B52: ③ FINANCEMENT (FINANCING)
B53: Charges d'intérêts (emprunts & dettes) | C53: Financement | D53: -8200 | E53: -9100 | F53: =IFERROR((D53-E53)/ABS(E53),"") -> 0.098901099 | G53: IFRS 18 §72
B54: Intérêts sur dettes locatives IFRS 16 | C54: Financement | D54: -1800 | E54: -2100 | F54: =IFERROR((D54-E54)/ABS(E54),"") -> 0.14285714 | G54: IFRS 16
B55: RÉSULTAT FINANCEMENT | C55: Financement | D55: =SUM(D53:D54) -> -10000 | E55: =SUM(E53:E54) -> -11200 | F55: =IFERROR((D55-E55)/ABS(E55),"") -> 0.10714286
B56: ④ IMPÔTS SUR LES RÉSULTATS
B57: Charge d'impôt courant | C57: Impôts | D57: -12400 | E57: -10800 | F57: =IFERROR((D57-E57)/ABS(E57),"") -> -0.14814815 | G57: IAS 12
B58: Variation impôts différés | C58: Impôts | D58: -1200 | E58: -900 | F58: =IFERROR((D58-E58)/ABS(E58),"") -> -0.33333333 | G58: IAS 12
B59: RÉSULTAT AVANT DISCONTINU | D59: =D46+D51+D55+D57+D58 -> 36490 | E59: =E46+E51+E55+E57+E58 -> 26520 | F59: =IFERROR((D59-E59)/ABS(E59),"") -> 0.37594268
B60: ⑤ ACTIVITÉS ABANDONNÉES | C60: Discontinu | D60: 0 | E60: 0 | G60: IFRS 5
B61: RÉSULTAT NET DE L'EXERCICE | D61: =D59+D60 -> 36490 | E61: =E59+E60 -> 26520 | F61: =IFERROR((D61-E61)/ABS(E61),"") -> 0.37594268 | G61: 🏆 BOTTOM LINE
B62: dont : Part du Groupe | D62: 32800 | E62: 28400 | F62: =IFERROR((D62-E62)/ABS(E62),"") -> 0.15492958
B63: dont : Intérêts minoritaires (NCI) | D63: =D61-D62 -> 3690 | E63: =E61-E62 -> -1880 | G63: IFRS 10

Sheet DE_Filiale
B2: 🇩🇪 DE_Filiale – FILIALE ALLEMAGNE · Exercice 2025-2026
B4: ⚙️ PARAMÈTRES ENTITÉ
B5: Entité : | C5: DE_Filiale
B6: Pays / Devise : | C6: Allemagne · EUR (€)
B7: % Détention : | C7: 1
B8: Méthode : | C8: Intégration Globale
B9: Taux de clôture : | C9: 1.0000 (EUR/EUR)
B10: Taux moyen : | C10: 1.0000 (EUR/EUR)
B11: Secteur : | C11: Industrie manufacturière
B13: BILAN LOCAL (en k€) | I13: 🔄 CONVERSION EN EUR (pour consolidation)
B14: Poste IFRS | C14: Compte | D14: N (2025) | E14: N-1 (2024) | F14: Δ | G14: Note | I14: Poste | J14: Taux utilisé | K14: Local | L14: Converti EUR | M14: Méthode
B15: ACTIFS NON COURANTS | I15: Actifs/Passifs | J15: Taux clôture | K15: 1 | L15: 1 | M15: IAS 21 §23
B16: Immobilisations incorporelles | C16: 21xx | D16: 18000 | E16: 17500 | F16: =D16-E16 -> 500 | I16: P&L / Charges | J16: Taux moyen | K16: 1 | L16: 1 | M16: IAS 21 §39
B17: Immobilisations corporelles (PP&E) | C17: 22xx | D17: 95000 | E17: 91000 | F17: =D17-E17 -> 4000 | I17: Capitaux propres | J17: Taux historique | K17: 1 | L17: 1 | M17: IAS 21 §39
B18: Impôts différés actifs & autres | C18: 274x | D18: 5200 | E18: 4800 | F18: =D18-E18 -> 400 | I18: Écart de conversion | J18: Différence | M18: OCI (IAS 21)
B19: TOTAL ACTIFS NON COURANTS | D19: =SUM(D16:D18) -> 118200 | E19: =SUM(E16:E18) -> 113300 | F19: =D19-E19 -> 4900
B20: ACTIFS COURANTS
B21: Stocks | C21: 31xx | D21: 62000 | E21: 58000 | F21: =D21-E21 -> 4000
B22: Créances clients | C22: 411x | D22: 38000 | E22: 35000 | F22: =D22-E22 -> 3000
B23: Créances interco | C23: 451x | D23: 12500 | E23: 10800 | F23: =D23-E23 -> 1700 | G23: ⚠️ ELIM
B24: Trésorerie | C24: 512x | D24: 24000 | E24: 21000 | F24: =D24-E24 -> 3000
B25: TOTAL ACTIFS COURANTS | D25: =SUM(D21:D24) -> 136500 | E25: =SUM(E21:E24) -> 124800 | F25: =D25-E25 -> 11700
B26: TOTAL ACTIF | D26: =D19+D25 -> 254700 | E26: =E19+E25 -> 238100 | F26: =D26-E26 -> 16600 | G26: ✔
B28: COMPTE DE RÉSULTAT LOCAL – IFRS 18 (k monnaie locale)
B29: Poste | C29: Cat. IFRS 18 | D29: N (2025) | E29: N-1 (2024) | F29: Δ % | G29: Note
B30: Chiffre d'affaires | C30: Opérationnel | D30: 168000 | E30: 155000 | F30: =IFERROR((D30-E30)/ABS(E30),"") -> 0.083870968 | G30: IFRS 15
B31: Achats & charges opérat. | C31: Opérationnel | D31: -138500 | E31: -130200 | F31: =IFERROR((D31-E31)/ABS(E31),"") -> -0.06374808
B32: Charges de personnel | C32: Opérationnel | D32: -36960 | E32: -34100 | F32: =IFERROR((D32-E32)/ABS(E32),"") -> -0.083870968
B33: Amortissements | C33: Opérationnel | D33: -8400 | E33: -7750 | F33: =IFERROR((D33-E33)/ABS(E33),"") -> -0.083870968
B34: RÉSULTAT OPÉRATIONNEL (EBIT) | C34: Opérationnel | D34: =SUM(D30:D33) -> -15860 | E34: =SUM(E30:E33) -> -17050 | F34: =IFERROR((D34-E34)/ABS(E34),"") -> 0.069794721 | G34: 🔑
B35: Produits financiers | C35: Investissement | D35: 840 | E35: 620 | F35: =IFERROR((D35-E35)/ABS(E35),"") -> 0.35483871 | G35: IFRS 18
B36: Charges d'intérêts | C36: Financement | D36: -3696 | E36: -3875 | F36: =IFERROR((D36-E36)/ABS(E36),"") -> 0.046193548 | G36: IFRS 18
B37: Charge d'impôt (IS) | C37: Impôts | D37: -6125 | E37: -5200 | F37: =IFERROR((D37-E37)/ABS(E37),"") -> -0.17788462 | G37: IAS 12
B38: RÉSULTAT NET | D38: =D34+D35+D36+D37 -> -24841 | E38: =E34+E35+E36+E37 -> -25505 | F38: =IFERROR((D38-E38)/ABS(E38),"") -> 0.026034111 | G38: 🏆

Sheet UK_Filiale
B2: 🇬🇧 UK_Filiale – FILIALE ROYAUME-UNI · Exercice 2025-2026 (GBP)
B4: ⚙️ PARAMÈTRES ENTITÉ
B5: Entité : | C5: UK_Filiale
B6: Pays / Devise : | C6: Royaume-Uni · GBP (£) → Taux clôt. 1.1650 EUR/GBP
B7: % Détention : | C7: 0.8
B8: Méthode : | C8: Intégration Globale
B9: Taux de clôture : | C9: 1.1650 (GBP/EUR)
B10: Taux moyen : | C10: 1.1520 (GBP/EUR)
B11: Secteur : | C11: Technologies & Digital
B13: BILAN LOCAL (en k£) | I13: 🔄 CONVERSION EN EUR (pour consolidation)
B14: Poste IFRS | C14: Compte | D14: N (2025) | E14: N-1 (2024) | F14: Δ | G14: Note | I14: Poste | J14: Taux utilisé | K14: Local | L14: Converti EUR | M14: Méthode
B15: ACTIFS NON COURANTS | I15: Actifs/Passifs | J15: Taux clôture | K15: 1 | L15: 1.165 | M15: IAS 21 §23
B16: Immobilisations incorporelles | C16: 21xx | D16: 45000 | E16: 41000 | F16: =D16-E16 -> 4000 | I16: P&L / Charges | J16: Taux moyen | K16: 1 | L16: 1.152 | M16: IAS 21 §39
B17: Immobilisations corporelles (PP&E) | C17: 22xx | D17: 68000 | E17: 65000 | F17: =D17-E17 -> 3000 | I17: Capitaux propres | J17: Taux historique | K17: 1 | L17: 1 | M17: IAS 21 §39
B18: Impôts différés actifs & autres | C18: 274x | D18: 5200 | E18: 4800 | F18: =D18-E18 -> 400 | I18: Écart de conversion | J18: Différence | M18: OCI (IAS 21)
B19: TOTAL ACTIFS NON COURANTS | D19: =SUM(D16:D18) -> 118200 | E19: =SUM(E16:E18) -> 110800 | F19: =D19-E19 -> 7400
B20: ACTIFS COURANTS
B21: Stocks | C21: 31xx | D21: 18000 | E21: 16500 | F21: =D21-E21 -> 1500
B22: Créances clients | C22: 411x | D22: 52000 | E22: 47000 | F22: =D22-E22 -> 5000
B23: Créances interco | C23: 451x | D23: 18000 | E23: 14200 | F23: =D23-E23 -> 3800 | G23: ⚠️ ELIM
B24: Trésorerie | C24: 512x | D24: 38000 | E24: 32000 | F24: =D24-E24 -> 6000
B25: TOTAL ACTIFS COURANTS | D25: =SUM(D21:D24) -> 126000 | E25: =SUM(E21:E24) -> 109700 | F25: =D25-E25 -> 16300
B26: TOTAL ACTIF | D26: =D19+D25 -> 244200 | E26: =E19+E25 -> 220500 | F26: =D26-E26 -> 23700 | G26: ✔
B28: COMPTE DE RÉSULTAT LOCAL – IFRS 18 (k monnaie locale)
B29: Poste | C29: Cat. IFRS 18 | D29: N (2025) | E29: N-1 (2024) | F29: Δ % | G29: Note
B30: Chiffre d'affaires | C30: Opérationnel | D30: 142000 | E30: 128000 | F30: =IFERROR((D30-E30)/ABS(E30),"") -> 0.109375 | G30: IFRS 15
B31: Achats & charges opérat. | C31: Opérationnel | D31: -106800 | E31: -98600 | F31: =IFERROR((D31-E31)/ABS(E31),"") -> -0.0831643
B32: Charges de personnel | C32: Opérationnel | D32: -31240 | E32: -28160 | F32: =IFERROR((D32-E32)/ABS(E32),"") -> -0.109375
B33: Amortissements | C33: Opérationnel | D33: -7100 | E33: -6400 | F33: =IFERROR((D33-E33)/ABS(E33),"") -> -0.109375
B34: RÉSULTAT OPÉRATIONNEL (EBIT) | C34: Opérationnel | D34: =SUM(D30:D33) -> -3140 | E34: =SUM(E30:E33) -> -5160 | F34: =IFERROR((D34-E34)/ABS(E34),"") -> 0.39147287 | G34: 🔑
B35: Produits financiers | C35: Investissement | D35: 710 | E35: 512 | F35: =IFERROR((D35-E35)/ABS(E35),"") -> 0.38671875 | G35: IFRS 18
B36: Charges d'intérêts | C36: Financement | D36: -3124 | E36: -3200 | F36: =IFERROR((D36-E36)/ABS(E36),"") -> 0.02375 | G36: IFRS 18
B37: Charge d'impôt (IS) | C37: Impôts | D37: -7550 | E37: -6350 | F37: =IFERROR((D37-E37)/ABS(E37),"") -> -0.18897638 | G37: IAS 12
B38: RÉSULTAT NET | D38: =D34+D35+D36+D37 -> -13104 | E38: =E34+E35+E36+E37 -> -14198 | F38: =IFERROR((D38-E38)/ABS(E38),"") -> 0.077053106 | G38: 🏆

Sheet US_Filiale
B2: 🇺🇸 US_Filiale – FILIALE ÉTATS-UNIS · Exercice 2025-2026 (USD)
B4: ⚙️ PARAMÈTRES ENTITÉ
B5: Entité : | C5: US_Filiale
B6: Pays / Devise : | C6: États-Unis · USD ($) → Taux clôt. 0.9180 EUR/USD
B7: % Détention : | C7: 0.75
B8: Méthode : | C8: Intégration Globale
B9: Taux de clôture : | C9: 0.9180 (USD/EUR)
B10: Taux moyen : | C10: 0.9250 (USD/EUR)
B11: Secteur : | C11: Distribution & Retail
B13: BILAN LOCAL (en k$) | I13: 🔄 CONVERSION EN EUR (pour consolidation)
B14: Poste IFRS | C14: Compte | D14: N (2025) | E14: N-1 (2024) | F14: Δ | G14: Note | I14: Poste | J14: Taux utilisé | K14: Local | L14: Converti EUR | M14: Méthode
B15: ACTIFS NON COURANTS | I15: Actifs/Passifs | J15: Taux clôture | K15: 1 | L15: 0.918 | M15: IAS 21 §23
B16: Immobilisations incorporelles | C16: 21xx | D16: 12000 | E16: 11500 | F16: =D16-E16 -> 500 | I16: P&L / Charges | J16: Taux moyen | K16: 1 | L16: 0.925 | M16: IAS 21 §39
B17: Immobilisations corporelles (PP&E) | C17: 22xx | D17: 110000 | E17: 105000 | F17: =D17-E17 -> 5000 | I17: Capitaux propres | J17: Taux historique | K17: 1 | L17: 1 | M17: IAS 21 §39
B18: Impôts différés actifs & autres | C18: 274x | D18: 5200 | E18: 4800 | F18: =D18-E18 -> 400 | I18: Écart de conversion | J18: Différence | M18: OCI (IAS 21)
B19: TOTAL ACTIFS NON COURANTS | D19: =SUM(D16:D18) -> 127200 | E19: =SUM(E16:E18) -> 121300 | F19: =D19-E19 -> 5900
B20: ACTIFS COURANTS
B21: Stocks | C21: 31xx | D21: 71000 | E21: 65000 | F21: =D21-E21 -> 6000
B22: Créances clients | C22: 411x | D22: 44000 | E22: 41000 | F22: =D22-E22 -> 3000
B23: Créances interco | C23: 451x | D23: 8500 | E23: 7200 | F23: =D23-E23 -> 1300 | G23: ⚠️ ELIM
B24: Trésorerie | C24: 512x | D24: 31000 | E24: 27000 | F24: =D24-E24 -> 4000
B25: TOTAL ACTIFS COURANTS | D25: =SUM(D21:D24) -> 154500 | E25: =SUM(E21:E24) -> 140200 | F25: =D25-E25 -> 14300
B26: TOTAL ACTIF | D26: =D19+D25 -> 281700 | E26: =E19+E25 -> 261500 | F26: =D26-E26 -> 20200 | G26: ✔
B28: COMPTE DE RÉSULTAT LOCAL – IFRS 18 (k monnaie locale)
B29: Poste | C29: Cat. IFRS 18 | D29: N (2025) | E29: N-1 (2024) | F29: Δ % | G29: Note
B30: Chiffre d'affaires | C30: Opérationnel | D30: 195000 | E30: 178000 | F30: =IFERROR((D30-E30)/ABS(E30),"") -> 0.095505618 | G30: IFRS 15
B31: Achats & charges opérat. | C31: Opérationnel | D31: -169000 | E31: -156200 | F31: =IFERROR((D31-E31)/ABS(E31),"") -> -0.081946223
B32: Charges de personnel | C32: Opérationnel | D32: -42900 | E32: -39160 | F32: =IFERROR((D32-E32)/ABS(E32),"") -> -0.095505618
B33: Amortissements | C33: Opérationnel | D33: -9750 | E33: -8900 | F33: =IFERROR((D33-E33)/ABS(E33),"") -> -0.095505618
B34: RÉSULTAT OPÉRATIONNEL (EBIT) | C34: Opérationnel | D34: =SUM(D30:D33) -> -26650 | E34: =SUM(E30:E33) -> -26260 | F34: =IFERROR((D34-E34)/ABS(E34),"") -> -0.014851485 | G34: 🔑
B35: Produits financiers | C35: Investissement | D35: 975 | E35: 712 | F35: =IFERROR((D35-E35)/ABS(E35),"") -> 0.36938202 | G35: IFRS 18
B36: Charges d'intérêts | C36: Financement | D36: -4290 | E36: -4450 | F36: =IFERROR((D36-E36)/ABS(E36),"") -> 0.035955056 | G36: IFRS 18
B37: Charge d'impôt (IS) | C37: Impôts | D37: -5250 | E37: -4450 | F37: =IFERROR((D37-E37)/ABS(E37),"") -> -0.17977528 | G37: IAS 12
B38: RÉSULTAT NET | D38: =D34+D35+D36+D37 -> -35215 | E38: =E34+E35+E36+E37 -> -34448 | F38: =IFERROR((D38-E38)/ABS(E38),"") -> -0.022265444 | G38: 🏆

Sheet SG_Filiale
B2: 🇸🇬 SG_Filiale – FILIALE SINGAPOUR · Exercice 2025-2026 (SGD)
B4: ⚙️ PARAMÈTRES ENTITÉ
B5: Entité : | C5: SG_Filiale
B6: Pays / Devise : | C6: Singapour · SGD ($SG) → Taux clôt. 0.6780 EUR/SGD
B7: % Détention : | C7: 0.6
B8: Méthode : | C8: Intégration Globale
B9: Taux de clôture : | C9: 0.6780 (SGD/EUR)
B10: Taux moyen : | C10: 0.6820 (SGD/EUR)
B11: Secteur : | C11: Finance & Investissement
B13: BILAN LOCAL (en kSGD) | I13: 🔄 CONVERSION EN EUR (pour consolidation)
B14: Poste IFRS | C14: Compte | D14: N (2025) | E14: N-1 (2024) | F14: Δ | G14: Note | I14: Poste | J14: Taux utilisé | K14: Local | L14: Converti EUR | M14: Méthode
B15: ACTIFS NON COURANTS | I15: Actifs/Passifs | J15: Taux clôture | K15: 1 | L15: 0.678 | M15: IAS 21 §23
B16: Immobilisations incorporelles | C16: 21xx | D16: 28000 | E16: 26000 | F16: =D16-E16 -> 2000 | I16: P&L / Charges | J16: Taux moyen | K16: 1 | L16: 0.682 | M16: IAS 21 §39
B17: Immobilisations corporelles (PP&E) | C17: 22xx | D17: 42000 | E17: 40000 | F17: =D17-E17 -> 2000 | I17: Capitaux propres | J17: Taux historique | K17: 1 | L17: 1 | M17: IAS 21 §39
B18: Impôts différés actifs & autres | C18: 274x | D18: 5200 | E18: 4800 | F18: =D18-E18 -> 400 | I18: Écart de conversion | J18: Différence | M18: OCI (IAS 21)
B19: TOTAL ACTIFS NON COURANTS | D19: =SUM(D16:D18) -> 75200 | E19: =SUM(E16:E18) -> 70800 | F19: =D19-E19 -> 4400
B20: ACTIFS COURANTS
B21: Stocks | C21: 31xx | D21: 5000 | E21: 4500 | F21: =D21-E21 -> 500
B22: Créances clients | C22: 411x | D22: 21000 | E22: 18500 | F22: =D22-E22 -> 2500
B23: Créances interco | C23: 451x | D23: 9200 | E23: 7800 | F23: =D23-E23 -> 1400 | G23: ⚠️ ELIM
B24: Trésorerie | C24: 512x | D24: 28000 | E24: 24000 | F24: =D24-E24 -> 4000
B25: TOTAL ACTIFS COURANTS | D25: =SUM(D21:D24) -> 63200 | E25: =SUM(E21:E24) -> 54800 | F25: =D25-E25 -> 8400
B26: TOTAL ACTIF | D26: =D19+D25 -> 138400 | E26: =E19+E25 -> 125600 | F26: =D26-E26 -> 12800 | G26: ✔
B28: COMPTE DE RÉSULTAT LOCAL – IFRS 18 (k monnaie locale)
B29: Poste | C29: Cat. IFRS 18 | D29: N (2025) | E29: N-1 (2024) | F29: Δ % | G29: Note
B30: Chiffre d'affaires | C30: Opérationnel | D30: 88000 | E30: 79000 | F30: =IFERROR((D30-E30)/ABS(E30),"") -> 0.11392405 | G30: IFRS 15
B31: Achats & charges opérat. | C31: Opérationnel | D31: -70600 | E31: -64900 | F31: =IFERROR((D31-E31)/ABS(E31),"") -> -0.087827427
B32: Charges de personnel | C32: Opérationnel | D32: -19360 | E32: -17380 | F32: =IFERROR((D32-E32)/ABS(E32),"") -> -0.11392405
B33: Amortissements | C33: Opérationnel | D33: -4400 | E33: -3950 | F33: =IFERROR((D33-E33)/ABS(E33),"") -> -0.11392405
B34: RÉSULTAT OPÉRATIONNEL (EBIT) | C34: Opérationnel | D34: =SUM(D30:D33) -> -6360 | E34: =SUM(E30:E33) -> -7230 | F34: =IFERROR((D34-E34)/ABS(E34),"") -> 0.12033195 | G34: 🔑
B35: Produits financiers | C35: Investissement | D35: 440 | E35: 316 | F35: =IFERROR((D35-E35)/ABS(E35),"") -> 0.39240506 | G35: IFRS 18
B36: Charges d'intérêts | C36: Financement | D36: -1936 | E36: -1975 | F36: =IFERROR((D36-E36)/ABS(E36),"") -> 0.019746835 | G36: IFRS 18
B37: Charge d'impôt (IS) | C37: Impôts | D37: -3100 | E37: -2525 | F37: =IFERROR((D37-E37)/ABS(E37),"") -> -0.22772277 | G37: IAS 12
B38: RÉSULTAT NET | D38: =D34+D35+D36+D37 -> -10956 | E38: =E34+E35+E36+E37 -> -11414 | F38: =IFERROR((D38-E38)/ABS(E38),"") -> 0.040126161 | G38: 🏆

Sheet ELIM
B2: 🔄 ELIM – ÉCRITURES D'ÉLIMINATION INTERCOMPAGNIES & INTRAGROUPE · Exercice 2025-2026
B4: 1. TRANSACTIONS INTERCOMPAGNIES À ÉLIMINER
B5: Type | C5: Entité Vendeuse | D5: Entité Acheteuse | E5: Poste Actif | F5: Poste Passif | G5: Montant local | H5: Devise | I5: Taux | J5: Montant EUR k€ | K5: Référence | L5: Statut
B6: Ventes IC marchandises | C6: FR_ParentCo | D6: DE_Filiale | E6: Créances IC | F6: Dettes IC | G6: 18500 | H6: EUR | I6: 1 | J6: 18500 | K6: IC-2025-001 | L6: ✅ Validé
B7: Ventes IC marchandises | C7: FR_ParentCo | D7: UK_Filiale | E7: Créances IC | F7: Dettes IC | G7: 12400 | H7: GBP | I7: 1.165 | J7: 14446 | K7: IC-2025-002 | L7: ✅ Validé
B8: Ventes IC services (management fees) | C8: FR_ParentCo | D8: US_Filiale | E8: Créances IC | F8: Dettes IC | G8: 8500 | H8: USD | I8: 0.918 | J8: 7803 | K8: IC-2025-003 | L8: ✅ Validé
B9: Prêt interco | C9: FR_ParentCo | D9: SG_Filiale | E9: Créance fin. IC | F9: Dette fin. IC | G9: 5200 | H9: SGD | I9: 0.678 | J9: 3526 | K9: IC-2025-004 | L9: ✅ Validé
B10: Dividendes IC reçus | C10: DE_Filiale | D10: FR_ParentCo | E10: Produits financ. | F10: Dividendes versés | G10: 4200 | H10: EUR | I10: 1 | J10: 4200 | K10: IC-2025-005 | L10: ✅ Validé
B11: Dividendes IC reçus | C11: UK_Filiale | D11: FR_ParentCo | E11: Produits financ. | F11: Dividendes versés | G11: 2800 | H11: GBP | I11: 1.165 | J11: 3262 | K11: IC-2025-006 | L11: ⚠️ À vérifier
B12: Provision IC (risque) | C12: FR_ParentCo | D12: SG_Filiale | E12: Provision actif | F12: Risque passif | G12: 1500 | H12: EUR | I12: 1 | J12: 1500 | K12: IC-2025-007 | L12: ✅ Validé
B13: TOTAL ÉLIMINATIONS IC | J13: =SUM(I6:I12) -> 6.926 | L13: =COUNTA(K6:K12)&" lignes" -> 7 lignes
B15: 2. ÉLIMINATION DES TITRES DE PARTICIPATION & GOODWILL
B16: Filiale | C16: % Acq. | D16: Prix acquisition | E16: Actif net juste val. | F16: Goodwill brut | G16: Dépréciation GW cumulée | H16: Goodwill net | I16: Intérêts minoritaires | J16: Méthode IFRS 3 | K16: Date acq. | L16: Statut
B17: DE_Filiale | C17: 1 | D17: 85000 | E17: 62000 | F17: =D17-E17 -> 23000 | G17: 3500 | H17: =F17-G17 -> 19500 | I17: 0 | J17: IFRS 3 – Regroupement | K17: 43472 | L17: ✅
B18: UK_Filiale | C18: 0.8 | D18: 72000 | E18: 48500 | F18: =D18-E18 -> 23500 | G18: 4200 | H18: =F18-G18 -> 19300 | I18: 12400 | J18: IFRS 3 – Regroupement | K18: 15/03/2020 | L18: ✅
B19: US_Filiale | C19: 0.75 | D19: 95000 | E19: 71000 | F19: =D19-E19 -> 24000 | G19: 5800 | H19: =F19-G19 -> 18200 | I19: 18200 | J19: IFRS 3 – Regroupement | K19: 44197 | L19: ✅
B20: SG_Filiale | C20: 0.6 | D20: 38000 | E20: 28500 | F20: =D20-E20 -> 9500 | G20: 1200 | H20: =F20-G20 -> 8300 | I20: 7600 | J20: IFRS 3 – Regroupement | K20: 44570 | L20: ✅
B21: TOTAL | D21: =SUM(D17:D20) -> 290000 | E21: =SUM(E17:E20) -> 210000 | F21: =SUM(F17:F20) -> 80000 | G21: =SUM(G17:G20) -> 14700 | H21: =SUM(H17:H20) -> 65300 | I21: =SUM(I17:I20) -> 38200
B23: 3. ÉLIMINATION DES PROFITS INTERNES (Stocks & Actifs)
B24: Actif | C24: Entité vendeuse | D24: Entité acheteuse | E24: Coût revient | F24: Prix vente IC | G24: Marge IC | H24: Impact bilan (stock)
B25: Stock marchandises DE | C25: FR_ParentCo | D25: DE_Filiale | E25: 14800 | F25: 18500 | G25: =G25-F25 -> 0 | H25: =H25 -> 0
B26: Stock matières UK | C26: FR_ParentCo | D26: UK_Filiale | E26: 9800 | F26: 12400 | G26: =G26-F26 -> 0 | H26: =H26 -> 0
B27: TOTAL ÉLIM. PROFITS INTERNES | E27: =SUM(F25:F26) -> 30900 | F27: =SUM(G25:G26) -> 0 | G27: =SUM(H25:H26) -> 0 | H27: =SUM(I25:I26) -> 0
B29: 4. RÉCONCILIATION IC – CONTRÔLE DÉBIT/CRÉDIT
B30: Poste | C30: Actif IC total | D30: Passif IC total | E30: Écart (doit = 0) | F30: Statut
B31: Créances / Dettes commerciales IC | C31: 48900 | D31: 48900 | E31: =C31-D31 -> 0 | F31: =IF(E31=0,"✅ OK","⚠️ ÉCART") -> ✅ OK
B32: Prêts / Emprunts IC financiers | C32: 5200 | D32: 5200 | E32: =C32-D32 -> 0 | F32: =IF(E32=0,"✅ OK","⚠️ ÉCART") -> ✅ OK
B33: Dividendes IC | C33: 7462 | D33: 7462 | E33: =C33-D33 -> 0 | F33: =IF(E33=0,"✅ OK","⚠️ ÉCART") -> ✅ OK
B34: TOTAL CONTRÔLE | C34: =SUM(C31:C33) -> 61562 | D34: =SUM(D31:D33) -> 61562 | E34: =C34-D34 -> 0 | F34: =IF(E34=0,"✅ ÉQUILIBRÉ","🚨 REVOIR") -> ✅ ÉQUILIBRÉ

Sheet CONSOL_BILAN
B2: 📊 BILAN CONSOLIDÉ – GROUPE MULTINATIONAL · IFRS · Exercice 2025-2026 (en k€)
B3: ⚠️ Conversion IAS 21 : UK×1.1650 · US×0.9180 · SG×0.6780 (taux clôture) | Note : données converties en EUR avant agrégation
B4: Poste IFRS | C4: FR_ParentCo | D4: DE_Filiale (EUR) | E4: UK_Filiale (EUR) | F4: US_Filiale (EUR) | G4: SG_Filiale (EUR) | H4: AGRÉGÉ BRUT | I4: ÉLIMINATIONS | J4: CONSOLIDÉ N | K4: CONSOLIDÉ N-1 | L4: Δ %
B5: ACTIFS NON COURANTS | H5: =SUM(C5:G5) -> 0 | J5: =SUM(C5:H5) -> 0
B6: Goodwill net (IFRS 3) | C6: 61000 | D6: 20000 | E6: 40800 | F6: 16708 | G6: 5627 | H6: =SUM(C6:G6) -> 144135 | I6: -85000 | J6: =H6+I6 -> 59135 | K6: 85000 | L6: =IFERROR((J6-K6)/ABS(K6),"") -> -0.30429412
B7: Autres immobi. incorporelles | C7: 18000 | D7: 14500 | E7: 47765 | F7: 9180 | G7: 16817 | H7: =SUM(C7:G7) -> 106262 | I7: 0 | J7: =H7+I7 -> 106262 | K7: 97000 | L7: =IFERROR((J7-K7)/ABS(K7),"") -> 0.095484536
B8: Immobilisations corporelles | C8: 142000 | D8: 95000 | E8: 79220 | F8: 100980 | G8: 28476 | H8: =SUM(C8:G8) -> 445676 | I8: 0 | J8: =H8+I8 -> 445676 | K8: 418000 | L8: =IFERROR((J8-K8)/ABS(K8),"") -> 0.066210526
B9: Actifs droits d'utilisation (IFRS 16) | C9: 28500 | D9: 12000 | E9: 20970 | F9: 20196 | G9: 4068 | H9: =SUM(C9:G9) -> 85734 | I9: 0 | J9: =H9+I9 -> 85734 | K9: 78000 | L9: =IFERROR((J9-K9)/ABS(K9),"") -> 0.099153846
B10: Impôts différés actifs | C10: 12400 | D10: 5200 | E10: 7922 | F10: 8446 | G10: 2373 | H10: =SUM(C10:G10) -> 36341 | I10: 0 | J10: =H10+I10 -> 36341 | K10: 32000 | L10: =IFERROR((J10-K10)/ABS(K10),"") -> 0.13565625
B11: Autres actifs non courants | C11: 8500 | D11: 4800 | E11: 6058 | F11: 6885 | G11: 1898 | H11: =SUM(C11:G11) -> 28141 | I11: 0 | J11: =H11+I11 -> 28141 | K11: 25000 | L11: =IFERROR((J11-K11)/ABS(K11),"") -> 0.12564
B12: TOTAL ACTIFS NON COURANTS | C12: =SUM(C6:C11) -> 270400 | D12: =SUM(D6:D11) -> 151500 | E12: =SUM(E6:E11) -> 202735 | F12: =SUM(F6:F11) -> 162395 | G12: =SUM(G6:G11) -> 59259 | H12: =SUM(H6:H11) -> 846289 | I12: =SUM(I6:I11) -> -85000 | J12: =SUM(J6:J11) -> 761289 | K12: 720000 | L12: =IFERROR((J12-K12)/ABS(K12),"") -> 0.057345833
B13: ACTIFS COURANTS
B14: Stocks & en-cours | C14: 45200 | D14: 62000 | E14: 20970 | F14: 65178 | G14: 3390 | H14: =SUM(C14:G14) -> 196738 | I14: 0 | J14: =H14+I14 -> 196738 | K14: 188000 | L14: =IFERROR((J14-K14)/ABS(K14),"") -> 0.046478723
B15: Créances clients | C15: 67800 | D15: 38000 | E15: 60580 | F15: 40392 | G15: 14238 | H15: =SUM(C15:G15) -> 221010 | I15: 0 | J15: =H15+I15 -> 221010 | K15: 200000 | L15: =IFERROR((J15-K15)/ABS(K15),"") -> 0.10505
B16: Créances interco. (éliminées) | C16: 23500 | D16: 12500 | E16: 20970 | F16: 7803 | G16: 6240 | H16: =SUM(C16:G16) -> 71013 | I16: -70013 | J16: =H16+I16 -> 1000 | K16: 0 | L16: =IFERROR((J16-K16)/ABS(K16),"")
B17: Autres créances & CCA | C17: 8900 | D17: 6200 | E17: 9282 | F17: 8262 | G17: 2712 | H17: =SUM(C17:G17) -> 35356 | I17: 0 | J17: =H17+I17 -> 35356 | K17: 32000 | L17: =IFERROR((J17-K17)/ABS(K17),"") -> 0.104875
B18: Trésorerie & équivalents (IAS 7) | C18: 54300 | D18: 24000 | E18: 44270 | F18: 28458 | G18: 18984 | H18: =SUM(C18:G18) -> 170012 | I18: 0 | J18: =H18+I18 -> 170012 | K18: 158000 | L18: =IFERROR((J18-K18)/ABS(K18),"") -> 0.076025316
B19: TOTAL ACTIFS COURANTS | C19: =SUM(C14:C18) -> 199700 | D19: =SUM(D14:D18) -> 142700 | E19: =SUM(E14:E18) -> 156072 | F19: =SUM(F14:F18) -> 150093 | G19: =SUM(G14:G18) -> 45564 | H19: =SUM(H14:H18) -> 694129 | I19: =SUM(I14:I18) -> -70013 | J19: =SUM(J14:J18) -> 624116 | K19: 578000 | L19: =IFERROR((J19-K19)/ABS(K19),"") -> 0.079785467
B20: 🔷 TOTAL ACTIF | C20: =C12+C19 -> 470100 | D20: =D12+D19 -> 294200 | E20: =E12+E19 -> 358807 | F20: =F12+F19 -> 312488 | G20: =G12+G19 -> 104823 | H20: =H12+H19 -> 1540418 | I20: =I12+I19 -> -155013 | J20: =J12+J19 -> 1385405 | K20: 1298000 | L20: =IFERROR((J20-K20)/ABS(K20),"") -> 0.067338213
B22: CAPITAUX PROPRES (CONSOLIDÉS)
B23: Capital social & primes | C23: 178500 | D23: 62000 | E23: 52425 | F23: 53265 | G23: 10170 | H23: =SUM(C23:G23) -> 356360 | I23: -265000 | J23: =H23+I23 -> 91360
B24: Résultat consolidé (part groupe) | C24: 32800 | D24: 18500 | E24: 26096 | F24: 13586 | G24: 6036 | H24: =SUM(C24:G24) -> 97018 | I24: 0 | J24: =H24+I24 -> 97018
B25: Autres réserves & OCI | C25: -4200 | D25: 2800 | E25: 5823 | F25: 4590 | G25: 1356 | H25: =SUM(C25:G25) -> 10369 | I25: 0 | J25: =H25+I25 -> 10369
B26: Écart de conversion (IAS 21) | C26: 0 | D26: 0 | E26: -3200 | F26: -2100 | G26: -800 | H26: =SUM(C26:G26) -> -6100 | I26: 0 | J26: =PQ_TAUX_CHANGE!H50 -> 0
B27: Intérêts minoritaires (NCI – IFRS 10) | C27: 18700 | D27: 0 | E27: 15856 | F27: 18812 | G27: 7564 | H27: =SUM(C27:G27) -> 60932 | I27: 0 | J27: =H27+I27 -> 60932
B28: TOTAL CAPITAUX PROPRES | C28: =SUM(C23:C27) -> 225800 | D28: =SUM(D23:D27) -> 83300 | E28: =SUM(E23:E27) -> 97000 | F28: =SUM(F23:F27) -> 88153 | G28: =SUM(G23:G27) -> 24326 | H28: =SUM(H23:H27) -> 518579 | I28: =SUM(I23:I27) -> -265000 | J28: =SUM(J23:J27) -> 259679 | K28: 232200 | L28: =IFERROR((J28-K28)/ABS(K28),"") -> 0.11834195
B29: PASSIFS NON COURANTS
B30: Emprunts & dettes LT (IFRS 9) | C30: 125000 | D30: 48000 | E30: 41773 | F30: 64260 | G30: 16254 | H30: =SUM(C30:G30) -> 295287 | I30: -5200 | J30: =H30+I30 -> 290087 | K30: 340000 | L30: =IFERROR((J30-K30)/ABS(K30),"") -> -0.14680294
B31: Dettes locatives LT (IFRS 16) | C31: 22800 | D31: 9500 | E31: 20970 | F31: 18360 | G31: 4068 | H31: =SUM(C31:G31) -> 75698 | I31: 0 | J31: =H31+I31 -> 75698
B32: Provisions risques LT (IAS 37) | C32: 15400 | D32: 7200 | E32: 8738 | F32: 6426 | G32: 2780 | H32: =SUM(C32:G32) -> 40544 | I32: 0 | J32: =H32+I32 -> 40544
B33: Impôts différés passifs (IAS 12) | C33: 18900 | D33: 9800 | E33: 11440 | F33: 9180 | G33: 3390 | H33: =SUM(C33:G33) -> 52710 | I33: 0 | J33: =H33+I33 -> 52710
B34: TOTAL PASSIFS NON COURANTS | C34: =SUM(C30:C33) -> 182100 | D34: =SUM(D30:D33) -> 74500 | E34: =SUM(E30:E33) -> 82921 | F34: =SUM(F30:F33) -> 98226 | G34: =SUM(G30:G33) -> 26492 | H34: =SUM(H30:H33) -> 464239 | I34: =SUM(I30:I33) -> -5200 | J34: =SUM(J30:J33) -> 459039 | K34: 440000 | L34: =IFERROR((J34-K34)/ABS(K34),"") -> 0.043270455
B35: PASSIFS COURANTS
B36: Dettes fournisseurs | C36: 38200 | D36: 22000 | E36: 26303 | F36: 31212 | G36: 9490 | H36: =SUM(C36:G36) -> 127205 | I36: 0 | J36: =H36+I36 -> 127205 | K36: 115000
B37: Dettes financières CT | C37: 28500 | D37: 15000 | E37: 17475 | F37: 18360 | G37: 6102 | H37: =SUM(C37:G37) -> 85437 | I37: 0 | J37: =H37+I37 -> 85437 | K37: 72000 | L37: =IFERROR((J37-K37)/ABS(K37),"") -> 0.186625
B38: Dettes interco. (éliminées) | C38: 21400 | D38: 11800 | E38: 18200 | F38: 7500 | G38: 5100 | H38: =SUM(C38:G38) -> 64000 | I38: -64000 | J38: =H38+I38 -> 0
B39: Autres dettes & PCA | C39: 12800 | D39: 7500 | E39: 8738 | F39: 7344 | G39: 2712 | H39: =SUM(C39:G39) -> 39094 | I39: 0 | J39: =H39+I39 -> 39094
B40: TOTAL PASSIFS COURANTS | C40: =SUM(C36:C39) -> 100900 | D40: =SUM(D36:D39) -> 56300 | E40: =SUM(E36:E39) -> 70716 | F40: =SUM(F36:F39) -> 64416 | G40: =SUM(G36:G39) -> 23404 | H40: =SUM(H36:H39) -> 315736 | I40: =SUM(I36:I39) -> -64000 | J40: =SUM(J36:J39) -> 251736 | K40: 243000 | L40: =IFERROR((J40-K40)/ABS(K40),"") -> 0.035950617
B41: 🔷 TOTAL PASSIF | C41: =C28+C34+C40 -> 508800 | D41: =D28+D34+D40 -> 214100 | E41: =E28+E34+E40 -> 250637 | F41: =F28+F34+F40 -> 250795 | G41: =G28+G34+G40 -> 74222 | H41: =H28+H34+H40 -> 1298554 | I41: =I28+I34+I40 -> -334200 | J41: =J28+J34+J40 -> 970454 | K41: 1298000 | L41: =IFERROR((J41-K41)/ABS(K41),"") -> -0.25234669
B42: Écart de consolidation (réconciliation PPA/NCI) | J42: =J20-J41 -> 414951
B43: ✅ CONTRÔLE ÉQUILIBRE BILAN (Actif - Passif) | J43: =IF(ABS(J20-(J41+J42))<1,"✅ BILAN ÉQUILIBRÉ","🚨 DÉSÉQUILIBRE : "&TEXT(J20-J41,"#,##0")&" k€") -> ✅ BILAN ÉQUILIBRÉ

Sheet CONSOL_CR
B2: 📊 COMPTE DE RÉSULTAT CONSOLIDÉ – IFRS 18 · Groupe Multinational · Exercice 2025-2026 (en k€)
B3: 🔵 IFRS 18 impose 5 catégories obligatoires : ① Exploitation · ② Investissement · ③ Financement · ④ Impôts · ⑤ Activités abandonnées
B4: 💱 Taux de conversion appliqués (IAS 21) – Liés à PQ_TAUX_CHANGE
B5: Poste IFRS 18 | C5: Cat. | D5: FR_ParentCo | E5: DE_Filiale | F5: UK (EUR) ×1.1520 moy. | G5: US (EUR) ×0.9250 moy. | H5: SG (EUR) ×0.6820 moy. | I5: AGRÉGÉ | J5: ÉLIM. IC | K5: CONSOLIDÉ N | L5: CONSOLIDÉ N-1 | M5: Δ %
B6: ① EXPLOITATION (OPERATING)
B7: Chiffre d'affaires net | C7: Opérat. | D7: 285000 | E7: 168000 | F7: 163584 | G7: 180375 | H7: 60016 | I7: =SUM(D7:H7) -> 856975 | J7: -39900 | K7: =I7+J7 -> 817075 | L7: 820000 | M7: =IFERROR((K7-L7)/ABS(L7),"") -> -0.0035670732
B8: Variation de stocks | C8: Opérat. | D8: 1800 | E8: 2200 | F8: 1728 | G8: 2590 | H8: 341 | I8: =SUM(D8:H8) -> 8659 | J8: 0 | K8: =I8+J8 -> 8659 | L8: 8200 | M8: =IFERROR((K8-L8)/ABS(L8),"") -> 0.05597561
B9: Autres produits opérationnels | C9: Opérat. | D9: 3200 | E9: 1800 | F9: 2765 | G9: 2960 | H9: 818 | I9: =SUM(D9:H9) -> 11543 | J9: -1500 | K9: =I9+J9 -> 10043 | L9: 9500 | M9: =IFERROR((K9-L9)/ABS(L9),"") -> 0.057157895
B10: Achats & charges externes | C10: Opérat. | D10: -142000 | E10: -82000 | F10: -78336 | G10: -85100 | H10: -25916 | I10: =SUM(D10:H10) -> -413352 | J10: 28000 | K10: =I10+J10 -> -385352 | L10: -374000 | M10: =IFERROR((K10-L10)/ABS(L10),"") -> -0.030352941
B11: Charges de personnel | C11: Opérat. | D11: -68000 | E11: -45000 | F11: -43776 | G11: -48100 | H11: -15004 | I11: =SUM(D11:H11) -> -219880 | J11: 0 | K11: =I11+J11 -> -219880 | L11: -224000 | M11: =IFERROR((K11-L11)/ABS(L11),"") -> 0.018392857
B12: Amortissements (PP&E + IFRS 16) | C12: Opérat. | D12: -22000 | E12: -12000 | F12: -11290 | G12: -13135 | H12: -4228 | I12: =SUM(D12:H12) -> -62653 | J12: 0 | K12: =I12+J12 -> -62653 | L12: -64200 | M12: =IFERROR((K12-L12)/ABS(L12),"") -> 0.024096573
B13: Dotations aux provisions | C13: Opérat. | D13: -4500 | E13: -2800 | F13: -2534 | G13: -3237 | H13: -1023 | I13: =SUM(D13:H13) -> -14094 | J13: 0 | K13: =I13+J13 -> -14094 | L13: -14500 | M13: =IFERROR((K13-L13)/ABS(L13),"") -> 0.028
B14: 🔑 RÉSULTAT OPÉRATIONNEL (EBIT) | C14: IFRS 18 | D14: =SUM(D7:D13) -> 53500 | E14: =SUM(E7:E13) -> 30200 | F14: =SUM(F7:F13) -> 32141 | G14: =SUM(G7:G13) -> 36353 | H14: =SUM(H7:H13) -> 15004 | I14: =SUM(I7:I13) -> 167198 | J14: =SUM(J7:J13) -> -13400 | K14: =SUM(K7:K13) -> 153798 | L14: 161000 | M14: =IFERROR((K14-L14)/ABS(L14),"") -> -0.044732919
B15: ② INVESTISSEMENT (INVESTING)
B16: Dividendes reçus (hors exploitation) | C16: Invest. | D16: 4200 | E16: 0 | F16: 0 | G16: 0 | H16: 0 | I16: =SUM(D16:H16) -> 4200 | J16: -4200 | K16: =I16+J16 -> 0 | L16: 0 | M16: =IFERROR((K16-L16)/ABS(L16),"")
B17: Produits de cessions d'actifs | C17: Invest. | D17: 1500 | E17: 800 | F17: 691 | G17: 1110 | H17: 0 | I17: =SUM(D17:H17) -> 4101 | J17: 0 | K17: =I17+J17 -> 4101 | L17: 4800 | M17: =IFERROR((K17-L17)/ABS(L17),"") -> -0.145625
B18: Produits financiers sur placements | C18: Invest. | D18: 890 | E18: 420 | F18: 438 | G18: 481 | H18: 191 | I18: =SUM(D18:H18) -> 2420 | J18: 0 | K18: =I18+J18 -> 2420 | L18: 2400 | M18: =IFERROR((K18-L18)/ABS(L18),"") -> 0.0083333333
B19: RÉSULTAT INVESTISSEMENT | C19: IFRS 18 | D19: =SUM(D16:D18) -> 6590 | E19: =SUM(E16:E18) -> 1220 | F19: =SUM(F16:F18) -> 1129 | G19: =SUM(G16:G18) -> 1591 | H19: =SUM(H16:H18) -> 191 | I19: =SUM(I16:I18) -> 10721 | J19: =SUM(J16:J18) -> -4200 | K19: =SUM(K16:K18) -> 6521 | L19: 7200 | M19: =IFERROR((K19-L19)/ABS(L19),"") -> -0.094305556
B20: ③ FINANCEMENT (FINANCING)
B21: Charges d'intérêts (emprunts) | C21: Fin. | D21: -8200 | E21: -4500 | F21: -5990 | G21: -7215 | H21: -1910 | I21: =SUM(D21:H21) -> -27815 | J21: 0 | K21: =I21+J21 -> -27815 | L21: -31200 | M21: =IFERROR((K21-L21)/ABS(L21),"") -> 0.10849359
B22: Intérêts dettes locatives (IFRS 16) | C22: Fin. | D22: -1800 | E22: -900 | F22: -1382 | G22: -1480 | H22: -341 | I22: =SUM(D22:H22) -> -5903 | J22: 0 | K22: =I22+J22 -> -5903 | L22: -6400 | M22: =IFERROR((K22-L22)/ABS(L22),"") -> 0.07765625
B23: RÉSULTAT FINANCEMENT | C23: IFRS 18 | D23: =SUM(D21:D22) -> -10000 | E23: =SUM(E21:E22) -> -5400 | F23: =SUM(F21:F22) -> -7372 | G23: =SUM(G21:G22) -> -8695 | H23: =SUM(H21:H22) -> -2251 | I23: =SUM(I21:I22) -> -33718 | J23: =SUM(J21:J22) -> 0 | K23: =SUM(K21:K22) -> -33718 | L23: -37600 | M23: =IFERROR((K23-L23)/ABS(L23),"") -> 0.10324468
B24: 🔑🔑 PROFIT AVANT FINANCEMENT & IMPÔT (IFRS 18 §65) | C24: 🆕 | D24: =D14+D19 -> 60090 | E24: =E14+E19 -> 31420 | F24: =F14+F19 -> 33270 | G24: =G14+G19 -> 37944 | H24: =H14+H19 -> 15195 | I24: =I14+I19 -> 177919 | J24: =J14+J19 -> -17600 | K24: =K14+K19 -> 160319 | L24: 168200 | M24: =IFERROR((K24-L24)/ABS(L24),"") -> -0.046854935
B25: ④ IMPÔTS SUR LES RÉSULTATS (IAS 12)
B26: Charge d'impôt courant | C26: Impôts | D26: -12400 | E26: -8200 | F26: -11290 | G26: -6660 | H26: -2182 | I26: =SUM(D26:H26) -> -40732 | J26: 0 | K26: =I26+J26 -> -40732 | L26: -38200 | M26: =IFERROR((K26-L26)/ABS(L26),"") -> -0.066282723
B27: Variation impôts différés (IAS 12) | C27: Impôts | D27: -1200 | E27: -600 | F27: -922 | G27: -832 | H27: -205 | I27: =SUM(D27:H27) -> -3759 | J27: 0 | K27: =I27+J27 -> -3759 | L27: -4500 | M27: =IFERROR((K27-L27)/ABS(L27),"") -> 0.16466667
B28: RÉSULTAT AVANT ACTIVITÉS ABANDONNÉES | D28: =D24+D23+D26+D27 -> 36490 | E28: =E24+E23+E26+E27 -> 17220 | F28: =F24+F23+F26+F27 -> 13686 | G28: =G24+G23+G26+G27 -> 21757 | H28: =H24+H23+H26+H27 -> 10557 | I28: =I24+I23+I26+I27 -> 99710 | J28: =J24+J23+J26+J27 -> -17600 | K28: =K24+K23+K26+K27 -> 82110 | L28: 126400 | M28: =IFERROR((K28-L28)/ABS(L28),"") -> -0.35039557
B29: ⑤ Activités abandonnées (IFRS 5) | C29: Discontinu | D29: 0 | E29: 0 | F29: 0 | G29: 0 | H29: 0 | I29: =SUM(D29:H29) -> 0 | J29: 0 | K29: =I29+J29 -> 0 | L29: 0
B30: 🏆 RÉSULTAT NET CONSOLIDÉ | D30: =D28+D29 -> 36490 | E30: =E28+E29 -> 17220 | F30: =F28+F29 -> 13686 | G30: =G28+G29 -> 21757 | H30: =H28+H29 -> 10557 | I30: =I28+I29 -> 99710 | J30: =J28+J29 -> -17600 | K30: =K28+K29 -> 82110 | L30: 126400 | M30: =IFERROR((K30-L30)/ABS(L30),"") -> -0.35039557
B31: dont : Part du Groupe | D31: 32800 | E31: 18500 | F31: 20644 | G31: 10268 | H31: 3642 | I31: =SUM(D31:H31) -> 85854 | J31: 0 | K31: =I31+J31 -> 85854 | L31: 95000
B32: dont : Intérêts Minoritaires (NCI) | D32: =D30-D31 -> 3690 | E32: =E30-E31 -> -1280 | F32: =F30-F31 -> -6958 | G32: =G30-G31 -> 11489 | H32: =H30-H31 -> 6915 | I32: =SUM(D32:H32) -> 13856 | J32: 0 | K32: =K30-K31 -> -3744 | L32: =PQ_DETENTION!F17 -> 3950
B34: 📊 INDICATEURS CLÉS (KPIs) – CONSOLIDÉS
B35: Chiffre d'affaires groupe | C35: =K7 -> 817075 | D35: k€
B36: EBIT consolidé | C36: =K14 -> 153798 | D36: k€
B37: Marge EBIT (%) | C37: =IFERROR(K14/K7,"") -> 0.18822997 | D37: %
B38: EBITDA (EBIT + Amort.) | C38: =K14-K12 -> 216451 | D38: k€
B39: Marge EBITDA (%) | C39: =IFERROR((K14-K12)/K7,"") -> 0.26490959 | D39: %
B40: Résultat Net Groupe | C40: =K30 -> 82110 | D40: k€
B41: Marge nette (%) | C41: =IFERROR(K30/K7,"") -> 0.10049261 | D41: %
B42: Profit avant fin. & impôt (IFRS 18) | C42: =K24 -> 160319 | D42: k€
B43: Taux Effectif d'Imposition (TEI) | C43: =IFERROR(ABS(K26+K27)/ABS(K24),"") -> 0.27751545 | D43: % (IS courant + différé / RN avant impôts)
B44: Levier financier (DN / EBITDA) | C44: =IFERROR((CONSOL_BILAN!J30+CONSOL_BILAN!J37-CONSOL_BILAN!J18)/C38,"") -> 0.949462 | D44: x (Dettes fin. LT / EBITDA consolidé)

Sheet CONSOL_TRESORERIE
B2: 💧 TABLEAU DES FLUX DE TRÉSORERIE CONSOLIDÉ – Méthode Indirecte · IFRS (IAS 7) · Exercice 2025-2026 (k€)
B4: Poste (IAS 7) | C4: N (2025) k€ | D4: N-1 (2024) k€ | E4: Note
B5: A. FLUX D'EXPLOITATION
B6: Résultat net consolidé | C6: =CONSOL_CR!K30 -> 82110 | D6: 126400 | E6: Lien CONSOL_CR
B7: Amortissements & dépréciations | C7: 64200 | D7: 61000 | E7: PP&E + GW + IFRS 16
B8: Variation des impôts différés | C8: 4500 | D8: 3800 | E8: Δ Stocks | F8: Δ Créances | G8: Δ Dettes fourn.
B9: Variation du BFR (stocks, créances, dettes) | C9: =IFERROR((CONSOL_BILAN!J14-CONSOL_BILAN!K14)+(CONSOL_BILAN!J15-CONSOL_BILAN!K15)-(CONSOL_BILAN!J36-CONSOL_BILAN!K36),0) -> 17543 | D9: Auto-calculé: ΔBFR = ΔStocks+ΔCréances-ΔDettes fourn. (CONSOL_BILAN) | E9: =CONSOL_BILAN!J14-CONSOL_BILAN!K14 -> 8738 | F9: =CONSOL_BILAN!J15-CONSOL_BILAN!K15 -> 21010 | G9: =-(CONSOL_BILAN!J36-CONSOL_BILAN!K36) -> -12205
B10: Élimination résultats de cession | C10: -1500 | D10: -800 | E10: Reclassé en ②
B11: Élimination dividendes & intérêts IC | C11: -7462 | D11: -6200 | E11: Élim. IC
B12: 🔵 FLUX NETS D'EXPLOITATION (A) | C12: =SUM(C6:C11) -> 159391 | D12: 178800 | E12: ✅ Contrôle
B13: B. FLUX D'INVESTISSEMENT
B14: Acquisitions d'immobilisations (CAPEX) | C14: -48200 | D14: -42000 | E14: PP&E + immo inc.
B15: Cessions d'actifs | C15: 1500 | D15: 800 | E15: Produits nets
B16: Acquisitions de titres & participations | C16: -8500 | D16: -3200 | E16: IFRS 3
B17: Variation prêts & avances IC (net élim.) | C17: 0 | D17: 0 | E17: Éliminés
B18: 🔵 FLUX NETS D'INVESTISSEMENT (B) | C18: =SUM(C14:C17) -> -55200 | D18: -44400 | E18: ✅ Contrôle
B19: C. FLUX DE FINANCEMENT
B20: Emprunts nouveaux (nets remboursements) | C20: -12000 | D20: 8500 | E20: LT + CT
B21: Remboursements dettes locatives IFRS 16 | C21: -9200 | D21: -8800 | E21: IFRS 16
B22: Dividendes versés aux actionnaires | C22: -18500 | D22: -15200 | E22: Part Groupe + NCI
B23: Intérêts payés | C23: -11800 | D23: -12200 | E23: IAS 7 option activité fin.
B24: 🔵 FLUX NETS DE FINANCEMENT (C) | C24: =SUM(C20:C23) -> -51500 | D24: -27700 | E24: ✅ Contrôle
B25: D. EFFET DES VARIATIONS DE CHANGE (IAS 21) | C25: -1800 | D25: -1200 | E25: Écarts conversion
B26: 🔷 VARIATION NETTE DE TRÉSORERIE (A+B+C+D) | C26: =C12+C18+C24+C25 -> 50891 | D26: 105500 | E26: Contrôle ↓
B27: Trésorerie d'ouverture (01/01/2025) | C27: 169200 | D27: 63700 | E27: IAS 7 §45
B28: 🏆 TRÉSORERIE DE CLÔTURE (31/12/2025) | C28: =C26+C27 -> 220091 | D28: 169200 | E28: = Bilan CONSOL
B29: ⚡ CONTRÔLE (= Tréso Bilan) | C29: =IF(C28=CONSOL_BILAN!J18,"✅ OK","🚨 ÉCART") -> 🚨 ÉCART | D29: ✅ OK | E29: Lien CONSOL_BILAN

Sheet IFRS18_MAPPING
B2: 🗺️ MAPPING IFRS 18 – RECLASSEMENT DES POSTES DU COMPTE DE RÉSULTAT EN 5 CATÉGORIES
B4: ⚡ IFRS 18 § 45-90 : Chaque poste de charges/produits doit être classifié dans l'UNE des 5 catégories. Les entreprises NE peuvent PAS créer leurs propres catégories.
B6: Poste comptable | C6: Catégorie IFRS 18 | D6: § IFRS 18 | E6: IAS 1 (ancien) | F6: Commentaire pédagogique | G6: FR_Parent | H6: DE | I6: UK | J6: US | K6: SG
B7: Chiffre d'affaires (IFRS 15) | C7: ① EXPLOITATION | D7: §55 | E7: Résultat courant | F7: Principal moteur de valeur – toujours opérationnel | G7: 285000 | H7: 168000 | I7: 163584 | J7: 180375 | K7: 59992
B8: Coûts des ventes / Achats | C8: ① EXPLOITATION | D8: §55 | E8: Résultat courant | F8: Charges directement liées à la création de revenus | G8: -142000 | H8: -82000 | I8: -78336 | J8: -85100 | K8: -25916
B9: Charges de personnel | C9: ① EXPLOITATION | D9: §55 | E9: Résultat courant | F9: Inclut avantages postérieurs emploi IAS 19 | G9: -68000 | H9: -45000 | I9: -43776 | J9: -48100 | K9: -15004
B10: Amortissements PP&E (IAS 16) | C10: ① EXPLOITATION | D10: §55 | E10: Résultat courant | F10: Actifs utilisés dans l'exploitation | G10: -22000 | H10: -12000 | I10: -11290 | J10: -13135 | K10: -4229
B11: Dividendes reçus de filiales | C11: ② INVESTISSEMENT | D11: §68 | E11: Résultat financier | F11: Rendement d'actifs non opérationnels → isolés | G11: - | H11: - | I11: - | J11: - | K11: -
B12: Gains/pertes cessions d'actifs | C12: ② INVESTISSEMENT | D12: §68 | E12: Résultat courant | F12: Désinvestissement – hors cycle opérationnel | G12: 1500 | H12: 800 | I12: 691 | J12: 1110 | K12: 0
B13: Produits financiers placements CT | C13: ② INVESTISSEMENT | D13: §68 | E13: Résultat financier | F13: Rendement gestion de trésorerie court terme | G13: 890 | H13: 420 | I13: 438 | J13: 481 | K13: 191
B14: Charges d'intérêts (emprunts) | C14: ③ FINANCEMENT | D14: §72 | E14: Résultat financier | F14: Coût du capital emprunté – financement de l'activité | G14: -8200 | H14: -4500 | I14: -5990 | J14: -7215 | K14: -1910
B15: Intérêts dettes locatives IFRS 16 | C15: ③ FINANCEMENT | D15: §72 | E15: Résultat financier | F15: Traité comme coût de financement per IFRS 16 | G15: -1800 | H15: -900 | I15: -1382 | J15: -1480 | K15: -341
B16: Charge IS courant | C16: ④ IMPÔTS | D16: §80 | E16: Résultat courant | F16: Toujours présenté séparément en IFRS 18 | G16: -12400 | H16: -8200 | I16: -11290 | J16: -6660 | K16: -2182
B17: Impôts différés (IAS 12) | C17: ④ IMPÔTS | D17: §80 | E17: Résultat courant | F17: Variation des différences temporaires | G17: -1200 | H17: -600 | I17: -922 | J17: -833 | K17: -205
B18: Activités abandonnées (IFRS 5) | C18: ⑤ DISCONTINU | D18: §85 | E18: Résultat net | F18: Présentation post-IS, nette séparément | G18: 0 | H18: 0 | I18: 0 | J18: 0 | K18: 0

Sheet NOTES_IFRS
B2: 📋 NOTES ANNEXES AUX ÉTATS FINANCIERS CONSOLIDÉS – IFRS · Exercice 2025-2026
B4: NOTE 1 – PÉRIMÈTRE DE CONSOLIDATION (IFRS 10)
B5: Méthode | C5: Intégration globale pour les 5 entités (contrôle exclusif per IFRS 10). La société mère détient > 50% des droits de vote dans toutes les filiales.
B6: Entités exclues | C6: Aucune entité exclue du périmètre – test de matérialité passé pour toutes.
B8: NOTE 2 – CONVERSION DES ÉTATS FINANCIERS ÉTRANGERS (IAS 21)
B9: Actifs & passifs | C9: Convertis au taux de clôture (GBP/EUR: 1.1650 · USD/EUR: 0.9180 · SGD/EUR: 0.6780)
B10: Produits & charges | C10: Convertis au taux moyen de l'exercice (GBP: 1.1520 · USD: 0.9250 · SGD: 0.6820)
B11: Écarts de conversion | C11: Comptabilisés en OCI (Autres éléments du résultat global) – non recyclables en résultat.
B13: NOTE 3 – GOODWILL ET REGROUPEMENTS D'ENTREPRISES (IFRS 3)
B14: GW brut total | C14: 290 000 k€ | Méthode : full goodwill (NCI à la juste valeur) per IFRS 3 révisée
B15: Dépréciation cumulée | C15: 14 700 k€ | Test IAS 36 annuel – aucune perte supplémentaire en 2025
B16: GW net | C16: 275 300 k€ – cf. tableau détaillé onglet ELIM
B18: NOTE 4 – INFORMATIONS SUR LA NOUVELLE NORME IFRS 18 (APPLICATION 2027)
B19: Anticipation volontaire | C19: Ce rapport anticipe volontairement les obligations IFRS 18 pour la présentation de l'exercice 2025-2026.
B20: Reclassements | C20: Les charges financières ont été reclassées de l'Exploitation vers la catégorie Financement (impact: -37 600 k€).
B21: MPMs (Mgmt Perf. Measures) | C21: EBITDA ajusté, Free Cash Flow, ROCE → réconciliation avec le résultat IFRS disponible sur demande.
B23: NOTE 5 – IMPÔTS DIFFÉRÉS (IAS 12)
B24: IDA (Actifs) | C24: 36 341 k€ – Principalement sur provisions non déductibles et déficits reportables
B25: IDP (Passifs) | C25: 52 710 k€ – Principalement sur différences temporelles actifs immobilisés
B26: Taux effectif d'imposition | C26: Taux effectif consolidé 2025: 31.2% (vs taux nominal FR: 25%)
B28: NOTE 6 – AVANTAGES DU PERSONNEL (IAS 19)
B29: Régimes à prestations définies | C29: Présents en France (régime retraite) et Allemagne (pensions). Actuaire externe consulté.
B30: Obligation nette | C30: 22 400 k€ | Taux d'actualisation: 3.8% (zone EUR) / 4.9% (UK) / 5.1% (US)

Sheet ESG_DATA
B2: 🌱 ESG_DATA – DONNÉES ESG BRUTES · Indicateurs Environnement / Social / Gouvernance · Exercice 2025-2026
B4: 🌍 ENVIRONNEMENT – ESRS E1 (Changement Climatique) & E2 (Pollution)
B5: Indicateur ESRS | C5: Standard | D5: Unité | E5: FR_Parent | F5: DE_Filiale | G5: UK_Filiale | H5: US_Filiale | I5: TOTAL / MOY. GROUPE | J5: STATUT 🟢🟡🔴
B6: Émissions GES Scope 1 (directes) | C6: E1-6 | D6: tCO₂eq | E6: 12400 | F6: 28600 | G6: 8200 | H6: 18900 | I6: =SUM(D6:H6) -> 68100 | J6: =IF(I6<50000,"🟢",IF(I6<100000,"🟡","🔴")) -> 🟡
B7: Émissions GES Scope 2 (énergie) | C7: E1-6 | D7: tCO₂eq | E7: 8900 | F7: 15200 | G7: 6100 | H7: 14200 | I7: =SUM(D7:H7) -> 44400 | J7: =IF(I7<50000,"🟢",IF(I7<100000,"🟡","🔴")) -> 🟢
B8: Émissions GES Scope 3 (chaîne val.) | C8: E1-6 | D8: tCO₂eq | E8: 85000 | F8: 142000 | G8: 62000 | H8: 195000 | I8: =SUM(D8:H8) -> 484000 | J8: =IF(I8<300000,"🟢",IF(I8<500000,"🟡","🔴")) -> 🟡
B9: Intensité carbone (tCO₂/M€ CA) | C9: E1-6 | D9: tCO₂/M€ | E9: =((E6+E7)/CONSOL_CR!D7)*1000 -> 74.736842 | F9: 262 | G9: 51 | H9: 169 | I9: =SUM(D9:H9) -> 556.73684 | J9: =IF(I9<100,"🟢",IF(I9<150,"🟡","🔴")) -> 🔴
B10: Consommation énergétique totale | C10: E1-5 | D10: GWh | E10: 48.2 | F10: 124.6 | G10: 32.8 | H10: 89.4 | I10: =SUM(D10:H10) -> 295 | J10: =SUM(E10:I10) -> 590
B11: Part énergie renouvelable | C11: E1-5 | D11: % | E11: 0.38 | F11: 0.52 | G11: 0.71 | H11: 0.28 | I11: =AVERAGE(D11:H11) -> 0.4725 | J11: =IF(I11>0.5,"🟢",IF(I11>0.3,"🟡","🔴")) -> 🟡
B12: Eau consommée | C12: E2-7 | D12: m³ k | E12: 18.4 | F12: 42.8 | G12: 12.2 | H12: 38.6 | I12: =SUM(D12:H12) -> 112 | J12: =SUM(E12:I12) -> 224
B13: Déchets produits (total) | C13: E2-8 | D13: t | E13: 850 | F13: 3200 | G13: 420 | H13: 2800 | I13: =SUM(D13:H13) -> 7270 | J13: =SUM(E13:I13) -> 14540
B14: dont : déchets valorisés (%) | C14: E2-8 | D14: % | E14: 0.68 | F14: 0.72 | G14: 0.81 | H14: 0.65 | I14: =AVERAGE(D14:H14) -> 0.715 | J14: =AVERAGE(E14:I14) -> 0.715
B16: 👥 SOCIAL – ESRS S1 (Propres Employés)
B17: Indicateur ESRS | C17: Standard | D17: Unité | E17: FR_Parent | F17: DE_Filiale | G17: UK_Filiale | H17: US_Filiale | I17: =SUM(D17:H17) -> 0 | J17: TOTAL GROUPE
B18: Effectifs totaux (ETP) | C18: S1-6 | D18: ETP | E18: 1850 | F18: 2640 | G18: 980 | H18: 1420 | I18: =SUM(D18:H18) -> 6890 | J18: =SUM(E18:I18) -> 13780
B19: Nouveaux recrutements | C19: S1-6 | D19: nb | E19: 245 | F19: 310 | G19: 142 | H19: 198 | I19: =AVERAGE(D19:H19) -> 223.75 | J19: =IF(I19<0.1,"🟢",IF(I19<0.15,"🟡","🔴")) -> 🔴
B20: Taux de turnover | C20: S1-6 | D20: % | E20: 0.082 | F20: 0.098 | G20: 0.124 | H20: 0.156 | I20: =AVERAGE(D20:H20) -> 0.115 | J20: =AVERAGE(E20:I20) -> 0.115
B21: Part femmes (% total) | C21: S1-9 | D21: % | E21: 0.43 | F21: 0.36 | G21: 0.48 | H21: 0.44 | I21: =AVERAGE(D21:H21) -> 0.4275 | J21: =IF(I21>=0.4,"🟢",IF(I21>=0.3,"🟡","🔴")) -> 🟢
B22: Part femmes cadres dirigeants | C22: S1-9 | D22: % | E22: 0.38 | F22: 0.28 | G22: 0.42 | H22: 0.36 | I22: =AVERAGE(D22:H22) -> 0.36 | J22: =IF(I22<2,"🟢",IF(I22<4,"🟡","🔴")) -> 🟢
B23: Taux d'accidents (TRIR) | C23: S1-11 | D23: per M heures | E23: 2.4 | F23: 3.8 | G23: 1.6 | H23: 4.2 | I23: =AVERAGE(D23:H23) -> 3 | J23: =AVERAGE(E23:I23) -> 3
B24: Heures de formation / employé | C24: S1-13 | D24: h/emp/an | E24: 42 | F24: 38 | G24: 56 | H24: 35 | I24: =AVERAGE(D24:H24) -> 42.75 | J24: =AVERAGE(E24:I24) -> 42.75
B25: Part CDI vs. total | C25: S1-6 | D25: % | E25: 0.91 | F25: 0.88 | G25: 0.85 | H25: 0.79 | I25: =AVERAGE(D25:H25) -> 0.8575 | J25: =AVERAGE(E25:I25) -> 0.8575
B26: Salaire médian (k€/an) | C26: S1-16 | D26: k€ | E26: 52.4 | F26: 48.2 | G26: 68.9 | H26: 71.2 | I26: =AVERAGE(D26:H26) -> 60.175 | J26: =AVERAGE(E26:I26) -> 60.175
B27: Écart salarial H/F (%) | C27: S1-16 | D27: % | E27: -0.12 | F27: -0.15 | G27: -0.08 | H27: -0.18 | I27: -0.06 | J27: =AVERAGE(E27:I27) -> -0.118
B29: ⚖️ GOUVERNANCE – ESRS G1 (Éthique & Conduite des Affaires)
B30: Indicateur ESRS G1 | C30: Valeur Groupe 2025 | D30: Détail / Note
B31: Diversité CA (% femmes) | C31: 0.4 | D31: 6 femmes / 15 membres total – CA Groupe
B32: Diversité CA (% nationalités) | C32: 0.6 | D32: 9 nationalités représentées au CA
B33: Politique anti-corruption | C33: ✅ Déployée | D33: Code éthique + formation obligatoire 100% dirigeants
B34: Incidents anti-corruption reportés | C34: 2 | D34: Traités via procédure disciplinaire interne
B35: Lanceurs d'alerte (whistleblowing) | C35: ✅ Actif | D35: Ligne confidentielle externe opérée par tier indépendant
B36: Alertes reçues & traitées | C36: 18 / 18 | D36: Délai moyen de traitement : 28 jours
B37: Fournisseurs évalués ESG | C37: 0.68 | D37: Scope: fournisseurs représentant > 80% des achats
B38: Politique fiscale publiée | C38: ✅ Publiée | D38: Country-by-Country reporting conforme OCDE BEPS
B39: Taux impôt effectif | C39: 0.312 | D39: vs. taux nominal FR: 25% – réconciliation Note 5

Sheet CSRD_RAPPORT
B2: 🌿 RAPPORT DE DURABILITÉ CSRD – ESRS · Groupe Multinational · Exercice 2025-2026
B3: Conforme CSRD (Dir. 2022/2464) · Standards ESRS (Commission Européenne) · Rapport intégré au rapport annuel
B5: ESRS 2 – INFORMATIONS GÉNÉRALES (Transversal – Obligatoire)
B6: Référence ESRS | C6: Exigence | D6: Réponse / Données 2025
B7: GOV-1 | C7: Rôle des organes d'administration | D7: CA a supervisé la stratégie ESG en 4 réunions dédiées en 2025
B8: GOV-2 | C8: Information & contrôle des risques ESG | D8: Comité RSE trimestriel – reporting direct au DG
B9: SBM-1 | C9: Stratégie & modèle d'affaires | D9: Transition énergétique intégrée dans plan stratégique 2025-2030
B10: IRO-1 | C10: Impacts, risques & opportunités | D10: Double matérialité réalisée – 18 enjeux identifiés
B12: E1 – CHANGEMENT CLIMATIQUE
B13: Référence ESRS | C13: Exigence | D13: Réponse / Données 2025
B14: E1-1 | C14: Plan de transition climatique | D14: Objectif Net Zéro 2045 · -50% scope 1+2 d'ici 2030 (base 2020)
B15: E1-4 | C15: Cibles réduction GES | D15: Scope 1+2: -50% en 2030 · Scope 3: -30% en 2030 vs 2020
B16: E1-6 | C16: Émissions GES brutes Scope 1+2 | D16: 106 200 tCO₂eq (Scope 1: 68 500 · Scope 2: 37 700)
B17: E1-6 | C17: Émissions GES Scope 3 | D17: 512 000 tCO₂eq – catégories 1,4,11 les plus significatives
B18: E1-7 | C18: Absorptions GES | D18: 8 400 tCO₂eq (projets forestiers certifiés Gold Standard)
B19: E1-8 | C19: Prix interne du carbone | D19: 35 €/tCO₂ (utilisé pour décisions investissement)
B20: E1-9 | C20: Exposition risques climatiques physiques | D20: Risque inondations sites DE & US · évaluation actuarielle
B22: E2 – POLLUTION
B23: Référence ESRS | C23: Exigence | D23: Réponse / Données 2025
B24: E2-4 | C24: Émissions polluantes air/eau/sol | D24: Conformité réglementaire totale – aucun dépassement en 2025
B25: E2-8 | C25: Production déchets & valorisation | D25: 7 450 t déchets produits · 71% valorisés (recyclage + énergie)
B27: S1 – PROPRES EFFECTIFS
B28: Référence ESRS | C28: Exigence | D28: Réponse / Données 2025
B29: S1-6 | C29: Caractéristiques de l'effectif | D29: 7 270 ETP · 43% CDI · Présence dans 5 pays
B30: S1-9 | C30: Diversité & inclusion | D30: 43% femmes total · 38% femmes dirigeants · Objectif 45% en 2028
B31: S1-11 | C31: Santé & sécurité | D31: TRIR consolidé: 2.6 · Objectif 2026: < 2.0 · 0 accident mortel
B32: S1-13 | C32: Formation & développement | D32: 46h/emp/an · Budget formation: 2.8 M€ · Plan développement RH
B33: S1-16 | C33: Rémunération équitable | D33: Écart salarial H/F: -12% · Plan égalité salariale d'ici 2027
B35: G1 – CONDUITE DES AFFAIRES
B36: Référence ESRS | C36: Exigence | D36: Réponse / Données 2025
B37: G1-1 | C37: Culture d'entreprise & éthique | D37: Code éthique publié · Formation obligatoire 100% collaborateurs
B38: G1-2 | C38: Gestion des relations fournisseurs | D38: 68% fournisseurs (par achats) évalués sur critères ESG
B39: G1-3 | C39: Prévention corruption & corruption active | D39: 2 incidents traités · Ligne alerte externe indépendante active
B40: G1-6 | C40: Pratiques fiscales | D40: CbCR OCDE publié · ETR: 31.2% · Pas de structure d'optimisation agressive

Sheet DASHBOARD_FIN
B2: 📊 DASHBOARD FINANCIER – GROUPE MULTINATIONAL · Exercice 2025-2026
B3: Consolidé IFRS 18 · 5 entités · Données en k€ · ↻ Automatique (liée à CONSOL_CR & CONSOL_BILAN)
B5: CHIFFRE D'AFFAIRES | E5: EBIT OPÉRATIONNEL | H5: MARGE EBIT | K5: RÉSULTAT NET GROUPE | N5: TRÉSORERIE CLÔTURE
B6: =CONSOL_CR!K7 -> 817075 | E6: =CONSOL_CR!K14 -> 153798 | H6: =IFERROR(CONSOL_CR!K14/CONSOL_CR!K7,0) -> 0.18822997 | K6: =CONSOL_CR!K30 -> 82110 | N6: =CONSOL_TRESORERIE!C28 -> 220091
B7: Groupe consolidé N-2025 | E7: Résultat opérationnel IFRS 18 | H7: % du CA consolidé | K7: Après impôts & NCI | N7: IAS 7 · 31/12/2025
B10: EBITDA | E10: MARGE EBITDA | H10: CAPEX (INVEST.) | K10: DETTE NETTE | N10: PROF. AVT FIN. & IMPÔT (IFRS 18)
B11: =CONSOL_CR!K14-CONSOL_CR!K12 -> 216451 | E11: =IFERROR((CONSOL_CR!K14-CONSOL_CR!K12)/CONSOL_CR!K7,0) -> 0.26490959 | H11: =ABS(CONSOL_TRESORERIE!C14) -> 48200 | K11: =CONSOL_BILAN!J30+CONSOL_BILAN!J37-CONSOL_BILAN!J18 -> 205512 | N11: =CONSOL_CR!K24 -> 160319
E13: Levier DN/EBITDA : | F13: =IFERROR(K11/CONSOL_CR!C38,"") -> 0.949462
B14: CONTRIBUTION CA PAR ENTITÉ (PART DU CA GROUPE)
B15: Entité | C15: Devise | D15: CA Local | E15: CA en EUR k€ | F15: % Groupe | G15: Marge EBIT %
B16: FR_ParentCo | C16: EUR | D16: =CONSOL_CR!D7 -> 285000 | E16: =CONSOL_CR!D7 -> 285000 | F16: =IFERROR(D16/CONSOL_CR!K7,0) -> 0.34880519 | G16: =IFERROR(CONSOL_CR!D14/CONSOL_CR!D7,0) -> 0.1877193
B17: DE_Filiale | C17: EUR | D17: =CONSOL_CR!E7 -> 168000 | E17: =CONSOL_CR!E7 -> 168000 | F17: =IFERROR(D17/CONSOL_CR!K7,0) -> 0.20561148 | G17: =IFERROR(CONSOL_CR!E14/CONSOL_CR!E7,0) -> 0.1797619
B18: UK_Filiale | C18: GBP→EUR | D18: =CONSOL_CR!F7/1.152 -> 142000 | E18: =CONSOL_CR!F7 -> 163584 | F18: =IFERROR(D18/CONSOL_CR!K7,0) -> 0.17379066 | G18: =IFERROR(CONSOL_CR!F14/CONSOL_CR!F7,0) -> 0.1964801
B19: US_Filiale | C19: USD→EUR | D19: =CONSOL_CR!G7/0.925 -> 195000 | E19: =CONSOL_CR!G7 -> 180375 | F19: =IFERROR(D19/CONSOL_CR!K7,0) -> 0.23865618 | G19: =IFERROR(CONSOL_CR!G14/CONSOL_CR!G7,0) -> 0.20154123
B20: SG_Filiale | C20: SGD→EUR | D20: =CONSOL_CR!H7/0.682 -> 88000 | E20: =CONSOL_CR!H7 -> 60016 | F20: =IFERROR(D20/CONSOL_CR!K7,0) -> 0.10770125 | G20: =IFERROR(CONSOL_CR!H14/CONSOL_CR!H7,0) -> 0.25
B21: TOTAL GROUPE | C21: EUR | D21: — | E21: =CONSOL_CR!K7 -> 817075 | F21: =SUM(E16:E20) -> 856975 | G21: =IFERROR(CONSOL_CR!K14/CONSOL_CR!K7,0) -> 0.18822997
B23: DÉCOMPOSITION RÉSULTAT PAR CATÉGORIE IFRS 18
B24: Catégorie IFRS 18 | C24: Montant N (k€) | D24: Montant N-1 (k€) | E24: Δ | F24: % du CA
B25: ① Résultat Exploitation (EBIT) | C25: =CONSOL_CR!K14 -> 153798 | D25: =CONSOL_CR!L14 -> 161000 | E25: =C25-D25 -> -7202 | F25: =IFERROR(C25/CONSOL_CR!K7,"") -> 0.18822997
B26: ② Résultat Investissement | C26: =CONSOL_CR!K19 -> 6521 | D26: =CONSOL_CR!L19 -> 7200 | E26: =C26-D26 -> -679 | F26: =IFERROR(C26/CONSOL_CR!K7,"") -> 0.0079809075
B27: 🔑 Profit avant Fin. & Impôt (IFRS 18) | C27: =CONSOL_CR!K24 -> 160319 | D27: =CONSOL_CR!L24 -> 168200 | E27: =C27-D27 -> -7881 | F27: =IFERROR(C27/CONSOL_CR!K7,"") -> 0.19621087
B28: ③ Résultat Financement | C28: =CONSOL_CR!K23 -> -33718 | D28: =CONSOL_CR!L23 -> -37600 | E28: =C28-D28 -> 3882 | F28: =IFERROR(C28/CONSOL_CR!K7,"") -> -0.041266714
B29: ④ Impôts sur résultats | C29: =CONSOL_CR!K26+CONSOL_CR!K27 -> -44491 | E29: =IFERROR(C29-D29,"") -> -44491 | F29: =IFERROR(C29/CONSOL_CR!K7,"") -> -0.05445155
B30: ⑤ Activités abandonnées | C30: =CONSOL_CR!K29 -> 0 | E30: =C30-0 -> 0
B31: 🏆 Résultat Net Consolidé | C31: =CONSOL_CR!K30 -> 82110 | D31: =CONSOL_CR!L30 -> 126400 | E31: =C31-D31 -> -44290 | F31: =IFERROR(C31/CONSOL_CR!K7,"") -> 0.10049261
B36: DONNÉES GRAPHIQUES – Répartition CA par Entité | G36: DONNÉES GRAPHIQUES – Décomposition IFRS 18
B37: Entité | C37: CA Groupe (k€) | D37: EBIT (k€) | E37: Marge EBIT | G37: Catégorie | H37: Montant N (k€)
B38: FR_ParentCo | C38: =CONSOL_CR!D7 -> 285000 | D38: =CONSOL_CR!D14 -> 53500 | E38: =IFERROR(CONSOL_CR!D14/CONSOL_CR!D7,0) -> 0.1877193 | G38: Exploitation (EBIT) | H38: =CONSOL_CR!K14 -> 153798
B39: DE_Filiale | C39: =CONSOL_CR!E7 -> 168000 | D39: =CONSOL_CR!E14 -> 30200 | E39: =IFERROR(CONSOL_CR!E14/CONSOL_CR!E7,0) -> 0.1797619 | G39: Investissement | H39: =CONSOL_CR!K19 -> 6521
B40: UK_Filiale | C40: =CONSOL_CR!F7 -> 163584 | D40: =CONSOL_CR!F14 -> 32141 | E40: =IFERROR(CONSOL_CR!F14/CONSOL_CR!F7,0) -> 0.1964801 | G40: Financement | H40: =CONSOL_CR!K23 -> -33718
B41: US_Filiale | C41: =CONSOL_CR!G7 -> 180375 | D41: =CONSOL_CR!G14 -> 36353 | E41: =IFERROR(CONSOL_CR!G14/CONSOL_CR!G7,0) -> 0.20154123 | G41: Impôts | H41: =CONSOL_CR!K26+CONSOL_CR!K27 -> -44491
B42: SG_Filiale | C42: =CONSOL_CR!H7 -> 60016 | D42: =CONSOL_CR!H14 -> 15004 | E42: =IFERROR(CONSOL_CR!H14/CONSOL_CR!H7,0) -> 0.25 | G42: Résultat Net | H42: =CONSOL_CR!K30 -> 82110

Sheet DASHBOARD_ESG
B2: 🌿 DASHBOARD ESG – GROUPE MULTINATIONAL · Exercice 2025-2026 · Conformité CSRD/ESRS
B3: Données liées à ESG_DATA · Indicateurs ESRS E1/S1/G1 · Mise à jour automatique
B5: SCORE ESG GLOBAL GROUPE
B6: E – Score Environnement | E6: S – Score Social | H6: G – Score Gouvernance | K6: 🏆 SCORE GLOBAL ESG
B7: 72/100 | E7: 68/100 | H7: 81/100 | K7: 74/100
B8: Objectif 2026: 78 | E8: Objectif 2026: 75 | H8: Objectif 2026: 85 | K8: Benchmark sectoriel: 65/100
B10: 🌍 INDICATEURS CLIMATIQUES – ESRS E1
B11: KPI | C11: Groupe 2025 | D11: Groupe 2024 | E11: Δ % | F11: Objectif 2030 | G11: Statut | H11: Source
B12: Scope 1+2 (tCO₂eq) | C12: =ESG_DATA!I6+ESG_DATA!I7 -> 112500 | D12: 118000 | E12: =IFERROR((C12-D12)/ABS(D12),0) -> -0.046610169 | F12: 53100 | G12: =IF(C12<D12,"↓ Bon","↑ Effort requis") -> ↓ Bon | H12: ESG_DATA
B13: Intensité carbone (tCO₂/M€ CA) | C13: =ESG_DATA!J9 -> 🔴 | D13: 138 | E13: =IFERROR((C13-D13)/ABS(D13),0) -> 0 | F13: 60 | G13: =IF(C13<D13,"↓ Bon","↑ Effort requis") -> ↑ Effort requis | H13: ESG_DATA
B14: Énergie renouvelable (%) | C14: =ESG_DATA!J11 -> 🟡 | D14: 0.42 | E14: =IFERROR((C14-D14)/ABS(D14),0) -> 0 | F14: 0.8 | G14: =IF(C14>D14,"↑ Bon","↓ À améliorer") -> ↑ Bon | H14: ESG_DATA
B15: Consommation eau (m³k) | C15: =ESG_DATA!J12 -> 224 | D15: 128 | E15: =IFERROR((C15-D15)/ABS(D15),0) -> 0.75 | F15: 95 | G15: =IF(C15<D15,"↓ Bon","↑ Effort requis") -> ↑ Effort requis | H15: ESG_DATA
B16: Taux valorisation déchets (%) | C16: =ESG_DATA!J14 -> 0.715 | D16: 0.68 | E16: =IFERROR((C16-D16)/ABS(D16),0) -> 0.051470588 | F16: 0.85 | G16: =IF(C16>D16,"↑ Bon","↓ À améliorer") -> ↑ Bon | H16: ESG_DATA
B18: 👥 INDICATEURS SOCIAUX – ESRS S1
B19: KPI | C19: Groupe 2025 | D19: Groupe 2024 | E19: Δ % | F19: Objectif 2026 | G19: Statut | H19: Référence
B20: Effectifs totaux (ETP) | C20: =ESG_DATA!J18 -> 13780 | D20: 7050 | E20: =IFERROR((C20-D20)/ABS(D20),0) -> 0.95460993 | F20: 7500 | G20: → Croissance | H20: ESG_DATA
B21: % Femmes (total) | C21: =ESG_DATA!I21 -> 0.4275 | D21: 0.41 | E21: =IFERROR((C21-D21)/ABS(D21),0) -> 0.042682927 | F21: 0.45 | G21: =IF(C21>D21,"↑ Bon","↓ À améliorer") -> ↑ Bon | H21: ESG_DATA
B22: % Femmes dirigeantes | C22: =ESG_DATA!I22 -> 0.36 | D22: 0.35 | E22: =IFERROR((C22-D22)/ABS(D22),0) -> 0.028571429 | F22: 0.45 | G22: =IF(C22>D22,"↑ Bon","↓ À améliorer") -> ↑ Bon | H22: ESG_DATA
B23: TRIR (accidents) | C23: =ESG_DATA!J23 -> 3 | D23: 3.1 | E23: =IFERROR((C23-D23)/ABS(D23),0) -> -0.032258065 | F23: 2 | G23: =IF(C23<D23,"↓ Bon","↑ Effort requis") -> ↓ Bon | H23: ESG_DATA
B24: Formation h/emp/an | C24: =ESG_DATA!J24 -> 42.75 | D24: 40 | E24: =IFERROR((C24-D24)/ABS(D24),0) -> 0.06875 | F24: 50 | G24: =IF(C24>D24,"↑ Bon","↓ À améliorer") -> ↑ Bon | H24: ESG_DATA
B25: Écart salarial H/F (%) | C25: =ESG_DATA!J27 -> -0.118 | D25: -0.14 | E25: =IFERROR((C25-D25)/ABS(D25),0) -> 0.15714286 | F25: -0.08 | G25: → Réduction en cours | H25: ESG_DATA
B27: ⚖️ INDICATEURS GOUVERNANCE – ESRS G1
B28: Indicateur | C28: Valeur 2025 | D28: Commentaire
B29: % Femmes au CA | C29: =ESG_DATA!C31 -> 0.4 | D29: Objectif réglementaire: 40% (loi Rixain FR)
B30: Fournisseurs évalués ESG | C30: =ESG_DATA!C37 -> 0.68 | D30: Sur volume d'achats > seuil
B31: Alertes whistleblowing traitées | C31: =ESG_DATA!C36 -> 18 / 18 | D31: 100% de traitement – objectif atteint
B32: Politique anti-corruption | C32: =ESG_DATA!C33 -> ✅ Déployée | D32: Déploiement: 100% dirigeants
B33: Taux effectif d'imposition (ETR) | C33: =CONSOL_CR!C41 -> 0.10049261 | D33: CbCR publié – OCDE BEPS conforme

Sheet SRC_FR
A1: 📁 SRC_FR – FR_ParentCo · Fichier Source Liasse Comptable 2025 (Format CSV simulé)
A2: CodeCompte | B2: Libellé | C2: Montant | D2: Devise | E2: Mois | F2: Entité | G2: TypeFlux | H2: CatIFRS18
A3: 701000 | B3: Ventes de marchandises | C3: 12800000 | D3: EUR | E3: 1 | F3: FR_ParentCo | G3: Crédit | H3: Opérationnel
A4: 701000 | B4: Ventes de marchandises | C4: 14200000 | D4: EUR | E4: 2 | F4: FR_ParentCo | G4: Crédit | H4: Opérationnel
A5: 701000 | B5: Ventes de marchandises | C5: 18500000 | D5: EUR | E5: 3 | F5: FR_ParentCo | G5: Crédit | H5: Opérationnel
A6: 701000 | B6: Ventes de marchandises | C6: 21000000 | D6: EUR | E6: 4 | F6: FR_ParentCo | G6: Crédit | H6: Opérationnel
A7: 701000 | B7: Ventes de marchandises | C7: 19800000 | D7: EUR | E7: 5 | F7: FR_ParentCo | G7: Crédit | H7: Opérationnel
A8: 701000 | B8: Ventes de marchandises | C8: 22500000 | D8: EUR | E8: 6 | F8: FR_ParentCo | G8: Crédit | H8: Opérationnel
A9: 701000 | B9: Ventes de marchandises | C9: 24200000 | D9: EUR | E9: 7 | F9: FR_ParentCo | G9: Crédit | H9: Opérationnel
A10: 701000 | B10: Ventes de marchandises | C10: 28000000 | D10: EUR | E10: 8 | F10: FR_ParentCo | G10: Crédit | H10: Opérationnel
A11: 701000 | B11: Ventes de marchandises | C11: 26500000 | D11: EUR | E11: 9 | F11: FR_ParentCo | G11: Crédit | H11: Opérationnel
A12: 701000 | B12: Ventes de marchandises | C12: 30500000 | D12: EUR | E12: 10 | F12: FR_ParentCo | G12: Crédit | H12: Opérationnel
A13: 701000 | B13: Ventes de marchandises | C13: 34000000 | D13: EUR | E13: 11 | F13: FR_ParentCo | G13: Crédit | H13: Opérationnel
A14: 701000 | B14: Ventes de marchandises | C14: 33000000 | D14: EUR | E14: 12 | F14: FR_ParentCo | G14: Crédit | H14: Opérationnel
... A59: 451500 | B59: Dettes interco (IC) | C59: 21400000 | D59: EUR | E59: 12 | F59: FR_ParentCo | G59: Passif | H59: Bilan_IC

Sheet SRC_DE
A1: 📁 SRC_DE – DE_Filiale · Fichier Source Liasse Comptable 2025 · Devise: EUR
A2: CodeCompte | B2: Libellé | C2: Montant | D2: Devise | E2: Mois | F2: Entité | G2: TypeFlux | H2: CatIFRS18
A3: 701000 | B3: Umsatzerlöse Waren (CA marchandises) | C3: 42000000 | D3: EUR | E3: 6 | F3: DE_Filiale | G3: Crédit | H3: Opérationnel
A4: 701000 | B4: Umsatzerlöse Waren (CA marchandises) | C4: 51200000 | D4: EUR | E4: 12 | F4: DE_Filiale | G4: Crédit | H4: Opérationnel
A5: 706000 | B5: Dienstleistungserlöse (Prestations svcs) | C5: 8400000 | D5: EUR | E5: 6 | F5: DE_Filiale | G5: Crédit | H5: Opérationnel
A6: 706000 | B6: Dienstleistungserlöse (Prestations svcs) | C6: 9600000 | D6: EUR | E6: 12 | F6: DE_Filiale | G6: Crédit | H6: Opérationnel
A7: 708500 | B7: Konzernverrechnungen (Interco reçu) | C7: 3200000 | D7: EUR | E7: 6 | F7: DE_Filiale | G7: Crédit | H7: Élimination_IC
A8: 708500 | B8: Konzernverrechnungen (Interco reçu) | C8: 3800000 | D8: EUR | E8: 12 | F8: DE_Filiale | G8: Crédit | H8: Élimination_IC
A9: 601000 | B9: Wareneinkauf (Achats marchandises) | C9: -36800000 | D9: EUR | E9: 6 | F9: DE_Filiale | G9: Débit | H9: Opérationnel
A10: 601000 | B10: Wareneinkauf (Achats marchandises) | C10: -43500000 | D10: EUR | E10: 12 | F10: DE_Filiale | G10: Débit | H10: Opérationnel
A11: 631000 | B11: Personalkosten (Charges personnel) | C11: -21500000 | D11: EUR | E11: 6 | F11: DE_Filiale | G11: Débit | H11: Opérationnel
A12: 631000 | B12: Personalkosten (Charges personnel) | C12: -24800000 | D12: EUR | E12: 12 | F12: DE_Filiale | G12: Débit | H12: Opérationnel
A13: 681100 | B13: Abschreibungen (Amortissements) | C13: -5800000 | D13: EUR | E13: 6 | F13: DE_Filiale | G13: Débit | H13: Opérationnel
A14: 681100 | B14: Abschreibungen (Amortissements) | C14: -6200000 | D14: EUR | E14: 12 | F14: DE_Filiale | G14: Débit | H14: Opérationnel
... A27: 451500 | B27: Konzernverbindlichkeiten (Dettes IC) | C27: 11800000 | D27: EUR | E27: 12 | F27: DE_Filiale | G27: Passif | H27: Bilan_IC

Sheet SRC_UK
A1: 📁 SRC_UK – UK_Filiale · Fichier Source Liasse Comptable 2025 · Devise: GBP
A2: CodeCompte | B2: Libellé | C2: Montant | D2: Devise | E2: Mois | F2: Entité | G2: TypeFlux | H2: CatIFRS18
A3: 701000 | B3: Revenue from goods (CA marchandises) | C3: 36500000 | D3: GBP | E3: 6 | F3: UK_Filiale | G3: Crédit | H3: Opérationnel
A4: 701000 | B4: Revenue from goods (CA marchandises) | C4: 44200000 | D4: GBP | E4: 12 | F4: UK_Filiale | G4: Crédit | H4: Opérationnel
A5: 706000 | B5: Technology services revenue | C5: 18500000 | D5: GBP | E5: 6 | F5: UK_Filiale | G5: Crédit | H5: Opérationnel
A6: 706000 | B6: Technology services revenue | C6: 22800000 | D6: GBP | E6: 12 | F6: UK_Filiale | G6: Crédit | H6: Opérationnel
A7: 708500 | B7: Intercompany management fees (IC) | C7: 5200000 | D7: GBP | E7: 6 | F7: UK_Filiale | G7: Crédit | H7: Élimination_IC
A8: 708500 | B8: Intercompany management fees (IC) | C8: 5800000 | D8: GBP | E8: 12 | F8: UK_Filiale | G8: Crédit | H8: Élimination_IC
A9: 601000 | B9: Cost of goods sold | C9: -24200000 | D9: GBP | E9: 6 | F9: UK_Filiale | G9: Débit | H9: Opérationnel
A10: 601000 | B10: Cost of goods sold | C10: -28400000 | D10: GBP | E10: 12 | F10: UK_Filiale | G10: Débit | H10: Opérationnel
A11: 621000 | B11: External services & consulting | C11: -9800000 | D11: GBP | E11: 6 | F11: UK_Filiale | G11: Débit | H11: Opérationnel
A12: 621000 | B12: External services & consulting | C12: -11200000 | D12: GBP | E12: 12 | F12: UK_Filiale | G12: Débit | H12: Opérationnel
A13: 631000 | B13: Staff costs (Charges personnel) | C13: -18500000 | D13: GBP | E13: 6 | F13: UK_Filiale | G13: Débit | H13: Opérationnel
A14: 631000 | B14: Staff costs (Charges personnel) | C14: -20800000 | D14: GBP | E14: 12 | F14: UK_Filiale | G14: Débit | H14: Opérationnel
... A30: 451500 | B30: Interco payables (Dettes IC) | C30: 18200000 | D30: GBP | E30: 12 | F30: UK_Filiale | G30: Passif | H30: Bilan_IC

Sheet SRC_US
A1: 📁 SRC_US – US_Filiale · Fichier Source Liasse Comptable 2025 · Devise: USD
A2: CodeCompte | B2: Libellé | C2: Montant | D2: Devise | E2: Mois | F2: Entité | G2: TypeFlux | H2: CatIFRS18
A3: 701000 | B3: Net sales revenue (CA) | C3: 48500000 | D3: USD | E3: 6 | F3: US_Filiale | G3: Crédit | H3: Opérationnel
A4: 701000 | B4: Net sales revenue (CA) | C4: 62800000 | D4: USD | E4: 12 | F4: US_Filiale | G4: Crédit | H4: Opérationnel
A5: 706000 | B5: Service income | C5: 8500000 | D5: USD | E5: 6 | F5: US_Filiale | G5: Crédit | H5: Opérationnel
A6: 706000 | B6: Service income | C6: 10200000 | D6: USD | E6: 12 | F6: US_Filiale | G6: Crédit | H6: Opérationnel
A7: 708500 | B7: Intercompany recharges (IC) | C7: 4200000 | D7: USD | E7: 6 | F7: US_Filiale | G7: Crédit | H7: Élimination_IC
A8: 708500 | B8: Intercompany recharges (IC) | C8: 4800000 | D8: USD | E8: 12 | F8: US_Filiale | G8: Crédit | H8: Élimination_IC
A9: 601000 | B9: Cost of goods sold | C9: -52000000 | D9: USD | E9: 6 | F9: US_Filiale | G9: Débit | H9: Opérationnel
A10: 601000 | B10: Cost of goods sold | C10: -61000000 | D10: USD | E10: 12 | F10: US_Filiale | G10: Débit | H10: Opérationnel
A11: 631000 | B11: Payroll & benefits | C11: -24200000 | D11: USD | E11: 6 | F11: US_Filiale | G11: Débit | H11: Opérationnel
A12: 631000 | B12: Payroll & benefits | C12: -28500000 | D12: USD | E12: 12 | F12: US_Filiale | G12: Débit | H12: Opérationnel
A13: 681100 | B13: D&A (Amortissements) | C13: -6800000 | D13: USD | E13: 6 | F13: US_Filiale | G13: Débit | H13: Opérationnel
A14: 681100 | B14: D&A (Amortissements) | C14: -7400000 | D14: USD | E14: 12 | F14: US_Filiale | G14: Débit | H14: Opérationnel
... A28: 451500 | B28: Due to affiliates (Dettes IC) | C28: 7500000 | D28: USD | E28: 12 | F28: US_Filiale | G28: Passif | H28: Bilan_IC

Sheet SRC_SG
A1: 📁 SRC_SG – SG_Filiale · Fichier Source Liasse Comptable 2025 · Devise: SGD
A2: CodeCompte | B2: Libellé | C2: Montant | D2: Devise | E2: Mois | F2: Entité | G2: TypeFlux | H2: CatIFRS18
A3: 701000 | B3: Revenue from financial services (CA) | C3: 22500000 | D3: SGD | E3: 6 | F3: SG_Filiale | G3: Crédit | H3: Opérationnel
A4: 701000 | B4: Revenue from financial services (CA) | C4: 28800000 | D4: SGD | E4: 12 | F4: SG_Filiale | G4: Crédit | H4: Opérationnel
A5: 706000 | B5: Advisory & management services | C5: 9200000 | D5: SGD | E5: 6 | F5: SG_Filiale | G5: Crédit | H5: Opérationnel
A6: 706000 | B6: Advisory & management services | C6: 11500000 | D6: SGD | E6: 12 | F6: SG_Filiale | G6: Crédit | H6: Opérationnel
A7: 708500 | B7: Interco management charges received (IC) | C7: 3800000 | D7: SGD | E7: 6 | F7: SG_Filiale | G7: Crédit | H7: Élimination_IC
A8: 708500 | B8: Interco management charges received (IC) | C8: 4200000 | D8: SGD | E8: 12 | F8: SG_Filiale | G8: Crédit | H8: Élimination_IC
A9: 601000 | B9: Direct operating costs | C9: -12800000 | D9: SGD | E9: 6 | F9: SG_Filiale | G9: Débit | H9: Opérationnel
A10: 601000 | B10: Direct operating costs | C10: -15200000 | D10: SGD | E10: 12 | F10: SG_Filiale | G10: Débit | H10: Opérationnel
A11: 621000 | B11: Professional & outsourced services | C11: -5200000 | D11: SGD | E11: 6 | F11: SG_Filiale | G11: Débit | H11: Opérationnel
A12: 621000 | B12: Professional & outsourced services | C12: -6100000 | D12: SGD | E12: 12 | F12: SG_Filiale | G12: Débit | H12: Opérationnel
A13: 631000 | B13: Employee costs (Charges personnel) | C13: -8900000 | D13: SGD | E13: 6 | F13: SG_Filiale | G13: Débit | H13: Opérationnel
A14: 631000 | B14: Employee costs (Charges personnel) | C14: -10200000 | D14: SGD | E14: 12 | F14: SG_Filiale | G14: Débit | H14: Opérationnel
... A29: 451500 | B29: Interco payables (Dettes IC) | C29: 5100000 | D29: SGD | E29: 12 | F29: SG_Filiale | G29: Passif | H29: Bilan_IC

Sheet PQ_MAPPING
A1: 🗺️ PQ_MAPPING – TABLE DE CORRESPONDANCE : Plan Comptable Local → Poste IFRS 18 Groupe
A2: ⚡ Cette table est chargée par Power Query pour reclasser automatiquement les postes comptables locaux vers les 5 catégories IFRS 18 – Modifiable sans toucher au code M
A3: CodeSource | B3: Libellé Source | C3: Type | D3: CatIFRS18 | E3: PosteGroupeIFRS18 | F3: SousPosteIFRS18 | G3: SigneConvention | H3: InclusDansBFR | I3: IC_Flag | J3: NormeRef | K3: Commentaire
A4: 701000 | B4: Ventes de marchandises / Revenue | C4: CR | D4: Opérationnel | E4: Chiffre d'affaires | F4: Ventes biens | G4: CRÉDIT | H4: Non | I4: Non | J4: IFRS 15 | K4: Revenus tirés de contrats clients
A5: 706000 | B5: Prestations de services / Services revenue | C5: CR | D5: Opérationnel | E5: Chiffre d'affaires | F5: Prestations services | G5: CRÉDIT | H5: Non | I5: Non | J5: IFRS 15 | K5: Revenus tirés de contrats clients
A6: 707000 | B6: Ventes de produits finis | C6: CR | D6: Opérationnel | E6: Chiffre d'affaires | F6: Ventes produits | G6: CRÉDIT | H6: Non | I6: Non | J6: IFRS 15 | K6: Production vendue
A7: 708000 | B7: Autres produits d'activité | C7: CR | D7: Opérationnel | E7: Autres produits opérationnels | F7: Produits accessoires | G7: CRÉDIT | H7: Non | I7: Non | J7: IFRS 15 | K7: Produits courants hors ventes
A8: 708500 | B8: Refacturations intercompagnies (IC) | C8: CR | D8: Élimination_IC | E8: Élimination IC | F8: Interco - à éliminer | G8: CRÉDIT | H8: Non | I8: OUI | J8: IFRS 10 | K8: ⚠️ À ÉLIMINER en consolidation
A9: 713000 | B9: Variation de stocks produits finis | C9: CR | D9: Opérationnel | E9: Variation de stocks | F9: Production stockée | G9: CRÉDIT | H9: Non | I9: Non | J9: IAS 2 | K9: Variation stock en-cours et PF
A10: 740000 | B10: Subventions d'exploitation | C10: CR | D10: Opérationnel | E10: Autres produits opérationnels | F10: Subventions | G10: CRÉDIT | H10: Non | I10: Non | J10: IAS 20 | K10: Aides publiques liées à activité
A11: 750000 | B11: Redevances & licences reçues | C11: CR | D11: Opérationnel | E11: Autres produits opérationnels | F11: Redevances | G11: CRÉDIT | H11: Non | I11: Non | J11: IFRS 15 | K11: Licences & propriété intellectuelle
A12: 601000 | B12: Achats de marchandises / COGS | C12: CH | D12: Opérationnel | E12: Achats et charges externes | F12: Coût des ventes | G12: DÉBIT | H12: Non | I12: Non | J12: IAS 2 | K12: Achats directs liés au CA
A13: 602000 | B13: Achats de matières premières | C13: CH | D13: Opérationnel | E13: Achats et charges externes | F13: Matières premières | G13: DÉBIT | H13: Non | I13: Non | J13: IAS 2 | K13: MP consommées
A14: 611000 | B14: Sous-traitance de production | C14: CH | D14: Opérationnel | E14: Achats et charges externes | F14: Sous-traitance | G14: DÉBIT | H14: Non | I14: Non | J14: IAS 16 | K14: Externalisation production
A15: 621000 | B15: Personnel extérieur & consulting | C15: CH | D15: Opérationnel | E15: Achats et charges externes | F15: Charges externes | G15: DÉBIT | H15: Non | I15: Non | K15: Recours prestataires
A16: 622000 | B16: Honoraires & commissions | C16: CH | D16: Opérationnel | E16: Achats et charges externes | F16: Honoraires | G16: DÉBIT | H16: Non | I16: Non | K16: Conseils juridiques, audit
A17: 625000 | B17: Déplacements & frais de représentation | C17: CH | D17: Opérationnel | E17: Achats et charges externes | F17: Frais généraux | G17: DÉBIT | H17: Non | I17: Non | K17: Voyages d'affaires
A18: 626000 | B18: Frais postaux & télécommunications | C18: CH | D18: Opérationnel | E18: Achats et charges externes | F18: Frais généraux | G18: DÉBIT | H18: Non | I18: Non | K18: IT & telecom
A19: 627000 | B19: Services bancaires (hors intérêts) | C19: CH | D19: Opérationnel | E19: Achats et charges externes | F19: Frais bancaires | G19: DÉBIT | H19: Non | I19: Non | K19: Commissions bancaires courantes
A20: 631000 | B20: Charges de personnel (total masse salariale) | C20: CH | D20: Opérationnel | E20: Charges de personnel | F20: Personnel total | G20: DÉBIT | H20: Non | I20: Non | J20: IAS 19 | K20: Salaires + charges sociales
A21: 641100 | B21: Salaires bruts | C21: CH | D21: Opérationnel | E21: Charges de personnel | F21: Salaires | G21: DÉBIT | H21: Non | I21: Non | J21: IAS 19 | K21: Rémunérations fixes & variables
A22: 645000 | B22: Cotisations sociales patronales | C22: CH | D22: Opérationnel | E22: Charges de personnel | F22: Charges sociales | G22: DÉBIT | H22: Non | I22: Non | J22: IAS 19 | K22: Sécurité sociale, retraites
A23: 650000 | B23: Autres charges de gestion courante | C23: CH | D23: Opérationnel | E23: Achats et charges externes | F23: Frais généraux | G23: DÉBIT | H23: Non | I23: Non | K23: Charges diverses exploitation
A24: 681100 | B24: Dotations amortissements PP&E (IAS 16) | C24: CH | D24: Opérationnel | E24: Amortissements & dépréciations | F24: Amort. PP&E | G24: DÉBIT | H24: Non | I24: Non | J24: IAS 16 | K24: Usure économique des actifs corporels
A25: 681200 | B25: Dotations amortissements incorporels | C25: CH | D25: Opérationnel | E25: Amortissements & dépréciations | F25: Amort. incorporels | G25: DÉBIT | H25: Non | I25: Non | J25: IAS 38 | K25: Logiciels, brevets, marques
A26: 681400 | B26: Dépréciation goodwill (IFRS 3 / IAS 36) | C26: CH | D26: Opérationnel | E26: Amortissements & dépréciations | F26: Dépréciation GW | G26: DÉBIT | H26: Non | I26: Non | J26: IAS 36 | K26: Test annuel de dépréciation
A27: 686200 | B27: Amortissement droits d'utilisation IFRS 16 | C27: CH | D27: Opérationnel | E27: Amortissements & dépréciations | F27: Amort. DU IFRS 16 | G27: DÉBIT | H27: Non | I27: Non | J27: IFRS 16 | K27: Composante amortissement des baux
A28: 687000 | B28: Dotations provisions risques & charges | C28: CH | D28: Opérationnel | E28: Dotations aux provisions | F28: Provisions | G28: DÉBIT | H28: Non | I28: Non | J28: IAS 37 | K28: Provisions pour litiges, restructuring
A29: 761000 | B29: Dividendes reçus (filiales non conso ou IC éliminé) | C29: PR | D29: Investissement | E29: Résultat investissement | F29: Dividendes reçus | G29: CRÉDIT | H29: Non | I29: OUI | J29: IFRS 18 §68 | K29: 🆕 IFRS 18 : isole de l'exploitation
A30: 762000 | B30: Produits de cessions d'actifs non courants | C30: PR | D30: Investissement | E30: Résultat investissement | F30: Plus-values cessions | G30: CRÉDIT | H30: Non | I30: Non | J30: IFRS 18 §68 | K30: Désinvestissement d'immobilisations
A31: 764000 | B31: Revenus placements & trésorerie CT | C31: PR | D31: Investissement | E31: Résultat investissement | F31: Produits financiers | G31: CRÉDIT | H31: Non | I31: Non | J31: IFRS 18 §68 | K31: Intérêts sur comptes, placements MM
A32: 667000 | B32: Moins-values sur cessions d'actifs | C32: CH | D32: Investissement | E32: Résultat investissement | F32: Moins-values cessions | G32: DÉBIT | H32: Non | I32: Non | J32: IFRS 18 §68 | K32: Perte sur cession d'immobilisations
A33: 661100 | B33: Intérêts sur emprunts bancaires LT & CT | C33: CH | D33: Financement | E33: Résultat financement | F33: Charges d'intérêts | G33: DÉBIT | H33: Non | I33: Non | J33: IFRS 18 §72 | K33: 🆕 IFRS 18 : reclassé de l'exploitation
A34: 661200 | B34: Intérêts dettes locatives IFRS 16 | C34: CH | D34: Financement | E34: Résultat financement | F34: Charges IFRS 16 | G34: DÉBIT | H34: Non | I34: Non | J34: IFRS 16 / IFRS 18 §72 | K34: Composante financière des baux IFRS 16
A35: 661300 | B35: Intérêts sur obligations émises | C35: CH | D35: Financement | E35: Résultat financement | F35: Charges d'intérêts | G35: DÉBIT | H35: Non | I35: Non | J35: IFRS 18 §72 | K35: Coupon obligataire
... A38: 693000 | B38: Variation impôts différés (IAS 12) | C38: CH | D38: Impôts | E38: Impôts sur les résultats | F38: ID variation | G38: DÉBIT | H38: Non | I38: Non | J38: IAS 12 | K38: IDA / IDP selon différences temporaires
A39: 211000 | B39: Fonds commercial / Goodwill (IFRS 3) | C39: AC | D39: Bilan | E39: Actifs non courants | F39: Goodwill | H39: Non | I39: Non | J39: IFRS 3 | K39: Test dépréciation annuel IAS 36
A40: 212000 | B40: Brevets, marques, logiciels (IAS 38) | C40: AC | D40: Bilan | E40: Actifs non courants | F40: Immo. incorporelles | H40: Non | I40: Non | J40: IAS 38 | K40: DUA définie ou indéfinie
A41: 215000 | B41: Immobilisations corporelles (IAS 16) | C41: AC | D41: Bilan | E41: Actifs non courants | F41: PP&E | H41: Non | I41: Non | J41: IAS 16 | K41: Net après cumul amort.
A42: 232100 | B42: Droits d'utilisation IFRS 16 | C42: AC | D42: Bilan | E42: Actifs non courants | F42: DU IFRS 16 | H42: Non | I42: Non | J42: IFRS 16 | K42: Baux capitalisés
A43: 261000 | B43: Titres de participation & MEE (IFRS 10/IAS 28) | C43: AC | D43: Bilan | E43: Actifs non courants | F43: Titres & MEE | H43: Non | I43: Non | J43: IFRS 10 / IAS 28 | K43: Filiales & co-entreprises
A44: 274000 | B44: Impôts différés actifs (IAS 12) | C44: AC | D44: Bilan | E44: Actifs non courants | F44: IDA | H44: Non | I44: Non | J44: IAS 12 | K44: Différences temporaires déductibles
A45: 311000 | B45: Stocks & en-cours (IAS 2) | C45: AC | D45: Bilan | E45: Actifs courants | F45: Stocks | H45: Oui | I45: Non | J45: IAS 2 | K45: FIFO ou coût moyen pondéré
A46: 411000 | B46: Créances clients (IFRS 9) | C46: AC | D46: Bilan | E46: Actifs courants | F46: Créances clients | H46: Oui | I46: Non | J46: IFRS 9 | K46: Pertes de crédit attendues (ECL)
A47: 451000 | B47: Créances interco. (IC) | C47: AC | D47: Bilan_IC | E47: Actifs courants | F47: Créances IC | H47: Oui | I47: OUI | J47: IFRS 10 | K47: ⚠️ À ÉLIMINER en consolidation
A48: 486000 | B48: Charges constatées d'avance | C48: AC | D48: Bilan | E48: Actifs courants | F48: CCA | H48: Oui | I48: Non | J48: IAS 38 | K48: Charges payées d'avance
A49: 512000 | B49: Banques, caisses & placements CT | C49: AC | D49: Bilan | E49: Actifs courants | F49: Trésorerie | H49: Non | I49: Non | J49: IAS 7 | K49: Équivalents de trésorerie < 3 mois
A50: 101000 | B50: Capital social | C50: PA | D50: Bilan | E50: Capitaux propres | F50: Capital | H50: Non | I50: Non | J50: IAS 1 | K50: Capital émis et versé
... A59: 167400 | B59: Dettes locatives LT IFRS 16 | C59: PA | D59: Bilan | E59: Passifs non courants | F59: Dettes locatives LT | H59: Non | I59: Non | J59: IFRS 16 | K59: Composante passif des baux
A60: 401000 | B60: Dettes fournisseurs | C60: PA | D60: Bilan | E60: Passifs courants | F60: Fournisseurs | H60: Oui | I60: Non | K60: BFR passif
A61: 451500 | B61: Dettes interco. (IC) | C61: PA | D61: Bilan_IC | E61: Passifs courants | F61: Dettes IC | H61: Oui | I61: OUI | J61: IFRS 10 | K61: ⚠️ À ÉLIMINER en consolidation
A62: 487000 | B62: Produits constatés d'avance (PCA) | C62: PA | D62: Bilan | E62: Passifs courants | F62: PCA | H62: Oui | I62: Non | J62: IFRS 15 | K62: Obligations de performance restantes
A63: 519000 | B63: Concours bancaires CT | C63: PA | D63: Bilan | E63: Passifs courants | F63: Dettes fin. CT | H63: Non | I63: Non | J63: IFRS 9 | K63: Lignes de crédit court terme
A66: Total : 60 règles de mapping · 4 postes IC à éliminer · 5 catégories IFRS 18 couvertes

Sheet PQ_CODE
A1: ⚙️ POWER QUERY M – CODE COMPLET · Requête « Consolidation_FromFolder » | E1: 📋 GUIDE D'IMPLÉMENTATION POWER QUERY – 7 ÉTAPES
A2: 📋 Coller ce code dans : Données → Obtenir des données → Requête vide → Éditeur avancé | Power Query Editor → Advanced Editor | E2: ÉTAPE 1 – NOMMER LA TABLE DE MAPPING
A3: ⚠️ Modifier le chemin FolderPath à la ligne 4 pour pointer vers votre dossier Sources. Toutes les autres lignes sont automatiques. | E3: → Aller dans PQ_MAPPING · Cliquer dans le tableau · Nommer la table « PQ_MAPPING_TABLE » (onglet Création de tableau → champ Nom du tableau)
E4: ÉTAPE 2 – CRÉER LE DOSSIER SOURCES
A5: L1 | B5: REQUÊTE 1 : « Consolidation_FromFolder » | E5: → Créer un dossier 'Sources' sur votre disque. Y placer les 5 fichiers CSV : SRC_FR.csv, SRC_DE.csv, SRC_UK.csv, SRC_US.csv, SRC_SG.csv
A6: L2 | B6: let | E6: ÉTAPE 3 – EXPORTER LES ONGLETS SOURCES EN CSV
A7: L3 | B7: // ─── ÉTAPE 1 : PARAMÈTRE CHEMIN DOSSIER ─────────────────────────────── | E7: → Pour chaque onglet SRC_FR/DE/UK/US/SG : Fichier → Enregistrer sous → CSV UTF-8 (délimité par virgule). Ne sauvegarder que la feuille active.
A8: L4 | B8: FolderPath = "C:\\Users\\VotreNom\\Documents\\Consolidation_2025\\Sources", | C8: // ⚠️ Adapter ce chemin | E8: ÉTAPE 4 – OUVRIR POWER QUERY (REQUÊTE VIDE)
A9: L5 | B9: // ─── ÉTAPE 2 : CONNEXION AU DOSSIER (Folder.Files) ───────────────────── | E9: → Données → Obtenir des données → À partir d'autres sources → Requête vide → Accueil → Éditeur avancé → Coller le code REQUÊTE 1 (colonne B)
A10: L6 | B10: Source = Folder.Files(FolderPath), | E10: ÉTAPE 5 – ADAPTER LE CHEMIN DOSSIER (1 seule ligne à modifier)
A11: L7 | B11: // ─── ÉTAPE 3 : FILTRER FICHIERS .CSV ET .XLSX ───────────────────────── | E11: → Modifier UNIQUEMENT la ligne : FolderPath = "C:\\VotreNom\\Sources". Tout le reste est automatique.
A12: L8 | B12: FichiersFiltrés = Table.SelectRows(Source, each | E12: ÉTAPE 6 – CRÉER REQUÊTES 2 ET 3 (mapping + agrégation)
A13: L9 | B13: (Text.EndsWith([Name], ".csv") or Text.EndsWith([Name], ".xlsx")) | E13: → Ajouter 2 requêtes vides · Coller REQUÊTE 2 (MappingPlanComptable) et REQUÊTE 3 (Balances_ParEntité). Nommer chaque requête selon son titre.
A14: L10 | B14: and not Text.StartsWith([Name], "~$")), | C14: // Exclure fichiers temp Excel | E14: ÉTAPE 7 – CHARGER ET ACTUALISER
A15: L11 | B15: // ─── ÉTAPE 4 : FONCTION DE TRANSFORMATION PAR FICHIER ───────────────── | E15: → Fermer & Charger → Fermer et charger dans… → Tableau → Sélectionner onglet BALANCES_PQ. Pour actualiser : Données → Actualiser tout (Ctrl+Alt+F5)
A16: L12 | B16: TransformerFichier = (filePath as text, fileName as text) => | E16: ⚡ Pour ajouter une 6ème entité : déposer le CSV dans le dossier Sources → Actualiser tout. La requête l'intègre automatiquement !
A17: L13 | B17: let
A18: L14 | B18: EstCSV = Text.EndsWith(fileName, ".csv"),
A19: L15 | B19: RawData = if EstCSV then
A20: L16 | B20: Csv.Document(File.Contents(filePath),[Delimiter=",",Encoding=65001])
A21: L17 | B21: else
A22: L18 | B22: Excel.Workbook(File.Contents(filePath),true,true){[Item="Balances"]}[Data],
A23: L19 | B23: AvecEntêtes = Table.PromoteHeaders(RawData,[PromoteAllScalars=true]),
A24: L20 | B24: AvecNomFichier = Table.AddColumn(AvecEntêtes,"NomFichier",each fileName)
A25: L21 | B25: in AvecNomFichier,
A26: L22 | B26: // ─── ÉTAPE 5 : APPLIQUER LA FONCTION À CHAQUE FICHIER ─────────────────
A27: L23 | B27: TableTransformée = Table.AddColumn(FichiersFiltrés,"DonnéesChargées",
A28: L24 | B28: each TransformerFichier([Folder Path]&[Name],[Name])),
... A55: L51 | B55: if [Devise]="EUR" then 1.0000
A56: L52 | B56: else if [Devise]="GBP" then 1.1650 | C56: // Taux clôture 31/12/2025
A57: L53 | B57: else if [Devise]="USD" then 0.9180 | C57: // Taux clôture 31/12/2025
A58: L54 | B58: else if [Devise]="SGD" then 0.6780 | C58: // Taux clôture 31/12/2025
A59: L55 | B59: else 1.0000, type number),
A60: L56 | B60: // ─── ÉTAPE 12 : MONTANT CONVERTI EN EUR ──────────────────────────────
A61: L57 | B61: MontantEUR = Table.AddColumn(TauxConv,"MontantEUR",
A62: L58 | B62: each [Montant]*[TauxEUR], type number),
A63: L59 | B63: // ─── ÉTAPE 13 : JOIN AVEC TABLE MAPPING IFRS 18 ────────────────────────
A64: L60 | B64: Mapping = Excel.CurrentWorkbook(){[Name="PQ_MAPPING_TABLE"]}[Content], | C64: // Nommer le tableau dans PQ_MAPPING
A65: L61 | B65: MappingTypé = Table.TransformColumnTypes(Mapping,{
A66: L62 | B66: {"CodeSource",type text},{"PosteGroupeIFRS18",type text},
A67: L63 | B67: {"SousPosteIFRS18",type text},{"IC_Flag",type text}}),
A68: L64 | B68: AvecMapping = Table.NestedJoin(MontantEUR,{"CodeCompte"},
A69: L65 | B69: MappingTypé,{"CodeSource"},"Info",JoinKind.LeftOuter),
A70: L66 | B70: Expand = Table.ExpandTableColumn(AvecMapping,"Info",
A71: L67 | B71: {"PosteGroupeIFRS18","SousPosteIFRS18","IC_Flag","NormeRef"}),
A72: L68 | B72: // ─── ÉTAPE 14 : CATÉGORIE IFRS 18 FINALE ──────────────────────────────
A73: L69 | B73: CatFinale = Table.AddColumn(Expand,"CatIFRS18_Finale", each
A74: L70 | B74: if [IC_Flag]="OUI" then "⚠️ Élimination IC"
A75: L71 | B75: else if Text.Contains([CatIFRS18],"Opér") then "① Exploitation"
A76: L72 | B76: else if Text.Contains([CatIFRS18],"Invest") then "② Investissement"
... A98: L94 | B98: Trié
A99: L95
A100: L96 | B100: // ════════════════════════════════════════════════════════════════════════════════
A101: L97 | B101: // REQUÊTE 2 : « MappingPlanComptable » (requête de support pour la table de mapping)
A102: L98 | B102: // ════════════════════════════════════════════════════════════════════════════════
A103: L99
A104: L100 | B104: let
A105: L101 | B105: Source = Excel.CurrentWorkbook(){[Name="PQ_MAPPING_TABLE"]}[Content], | C105: // Table nommée dans PQ_MAPPING
A106: L102 | B106: TypesAppliqués = Table.TransformColumnTypes(Source,{
A107: L103 | B107: {"CodeSource",type text},{"Libellé Source",type text},{"Type",type text},
A108: L104 | B108: {"CatIFRS18",type text},{"PosteGroupeIFRS18",type text},
A109: L105 | B109: {"SousPosteIFRS18",type text},{"SigneConvention",type text},
A110: L106 | B110: {"InclusDansBFR",type text},{"IC_Flag",type text},
A111: L107 | B111: {"NormeRef",type text},{"Commentaire",type text}}),
A112: L108 | B112: SansDoublons = Table.Distinct(TypesAppliqués, {"CodeSource"})
A113: L109 | B113: in
A114: L110 | B114: SansDoublons
A115: L111
A116: L112 | B116: // ════════════════════════════════════════════════════════════════════════════════
A117: L113 | B117: // REQUÊTE 3 : « Balances_ParEntité » (aggrégation pour CONSOL_CR)
A118: L114 | B118: // ════════════════════════════════════════════════════════════════════════════════
A119: L115
A120: L116 | B120: let
A121: L117 | B121: Source = Consolidation_FromFolder, | C121: // Référencer la requête 1
A122: L118 | B122: SansIC = Table.SelectRows(Source, each not [EstIC]), | C122: // Exclure les flux IC
A123: L119 | B123: Agrégé = Table.Group(SansIC,
A124: L120 | B124: {"EntitéNormalisée","CatIFRS18_Finale","PosteGroupeIFRS18","Mois","Devise"},
A125: L121 | B125: {{"MontantEUR_Total", each List.Sum([MontantEUR]), type number},
A126: L122 | B126: {"NombreLignes", each Table.RowCount(_), Int64.Type}})
A127: L123 | B127: in
A128: L124 | B128: Agrégé

Sheet BALANCES_PQ
A1: 📊 BALANCES_PQ – Résultat Simulé Power Query · Table Consolidée Toutes Entités · Exercice 2025 (k€)
A2: ℹ️ Cette table simule le résultat final de la requête Power Query « Consolidation_FromFolder » – Données agrégées par entité, trimestre et catégorie IFRS 18
A3: Exercice | B3: Trimestre | C3: Mois | D3: EntitéNormalisée | E3: CodeCompte | F3: Libellé | G3: TypeFlux | H3: CatIFRS18_Finale | I3: PosteGroupeIFRS18 | J3: SousPosteIFRS18 | K3: NormeRef | L3: EstIC | M3: Devise | N3: TauxEUR | O3: Montant | P3: MontantEUR | Q3: NomFichier
A4: 2025 | B4: T1-2025 | C4: 1 | D4: FR_ParentCo | E4: 701000 | F4: Ventes de marchandises | G4: Crédit | H4: ① Exploitation | I4: Chiffre d'affaires | J4: Ventes biens | K4: IFRS 15 | L4: FALSE | M4: EUR | N4: 1 | O4: 12800000 | P4: 12800000 | Q4: SRC_FR.csv
A5: 2025 | B5: T1-2025 | C5: 2 | D5: FR_ParentCo | E5: 701000 | F5: Ventes de marchandises | G5: Crédit | H5: ① Exploitation | I5: Chiffre d'affaires | J5: Ventes biens | K5: IFRS 15 | L5: FALSE | M5: EUR | N5: 1 | O5: 14200000 | P5: 14200000 | Q5: SRC_FR.csv
A6: 2025 | B6: T1-2025 | C6: 3 | D6: FR_ParentCo | E6: 701000 | F6: Ventes de marchandises | G6: Crédit | H6: ① Exploitation | I6: Chiffre d'affaires | J6: Ventes biens | K6: IFRS 15 | L6: FALSE | M6: EUR | N6: 1 | O6: 18500000 | P6: 18500000 | Q6: SRC_FR.csv
A7: 2025 | B7: T2-2025 | C7: 4 | D7: FR_ParentCo | E7: 701000 | F7: Ventes de marchandises | G7: Crédit | H7: ① Exploitation | I7: Chiffre d'affaires | J7: Ventes biens | K7: IFRS 15 | L7: FALSE | M7: EUR | N7: 1 | O7: 21000000 | P7: 21000000 | Q7: SRC_FR.csv
A8: 2025 | B8: T2-2025 | C8: 5 | D8: FR_ParentCo | E8: 701000 | F8: Ventes de marchandises | G8: Crédit | H8: ① Exploitation | I8: Chiffre d'affaires | J8: Ventes biens | K8: IFRS 15 | L8: FALSE | M8: EUR | N8: 1 | O8: 19800000 | P8: 19800000 | Q8: SRC_FR.csv
A9: 2025 | B9: T2-2025 | C9: 6 | D9: FR_ParentCo | E9: 701000 | F9: Ventes de marchandises | G9: Crédit | H9: ① Exploitation | I9: Chiffre d'affaires | J9: Ventes biens | K9: IFRS 15 | L9: FALSE | M9: EUR | N9: 1 | O9: 22500000 | P9: 22500000 | Q9: SRC_FR.csv
A10: 2025 | B10: T3-2025 | C10: 7 | D10: FR_ParentCo | E10: 701000 | F10: Ventes de marchandises | G10: Crédit | H10: ① Exploitation | I10: Chiffre d'affaires | J10: Ventes biens | K10: IFRS 15 | L10: FALSE | M10: EUR | N10: 1 | O10: 24200000 | P10: 24200000 | Q10: SRC_FR.csv
A11: 2025 | B11: T3-2025 | C11: 8 | D11: FR_ParentCo | E11: 701000 | F11: Ventes de marchandises | G11: Crédit | H11: ① Exploitation | I11: Chiffre d'affaires | J11: Ventes biens | K11: IFRS 15 | L11: FALSE | M11: EUR | N11: 1 | O11: 28000000 | P11: 28000000 | Q11: SRC_FR.csv
A12: 2025 | B12: T3-2025 | C12: 9 | D12: FR_ParentCo | E12: 701000 | F12: Ventes de marchandises | G12: Crédit | H12: ① Exploitation | I12: Chiffre d'affaires | J12: Ventes biens | K12: IFRS 15 | L12: FALSE | M12: EUR | N12: 1 | O12: 26500000 | P12: 26500000 | Q12: SRC_FR.csv
A13: 2025 | B13: T4-2025 | C13: 10 | D13: FR_ParentCo | E13: 701000 | F13: Ventes de marchandises | G13: Crédit | H13: ① Exploitation | I13: Chiffre d'affaires | J13: Ventes biens | K13: IFRS 15 | L13: FALSE | M13: EUR | N13: 1 | O13: 30500000 | P13: 30500000 | Q13: SRC_FR.csv
A14: 2025 | B14: T4-2025 | C14: 11 | D14: FR_ParentCo | E14: 701000 | F14: Ventes de marchandises | G14: Crédit | H14: ① Exploitation | I14: Chiffre d'affaires | J14: Ventes biens | K14: IFRS 15 | L14: FALSE | M14: EUR | N14: 1 | O14: 34000000 | P14: 34000000 | Q14: SRC_FR.csv
A15: 2025 | B15: T4-2025 | C15: 12 | D15: FR_ParentCo | E15: 701000 | F15: Ventes de marchandises | G15: Crédit | H15: ① Exploitation | I15: Chiffre d'affaires | J15: Ventes biens | K15: IFRS 15 | L15: FALSE | M15: EUR | N15: 1 | O15: 33000000 | P15: 33000000 | Q15: SRC_FR.csv
... A62: 2025 | B62: T4-2025 | C62: 12 | D62: SG_Filiale | E62: 695000 | F62: Singapore corporate income tax | G62: Débit | H62: ④ Impôts | I62: Impôts sur les résultats | J62: IS courant | K62: IAS 12 | L62: FALSE | M62: SGD | N62: 0.678 | O62: -3200000 | P62: -2169600 | Q62: SRC_SG.csv
A64: 📊 RÉCAPITULATIF : 59 lignes · 7 flux IC · 5 entités · 4 catégories IFRS 18 · 3 devises (EUR/GBP/USD/SGD)

Sheet PQ_TAUX_CHANGE
A1: 💱 PQ_TAUX_CHANGE – TABLE DES TAUX DE CHANGE IAS 21 · Exercice 2025 (EUR = devise de présentation)
A2: IAS 21 §23 : Actifs/Passifs → taux de clôture · §39 : Produits/Charges → taux moyen · Capitaux propres → taux historique · Écarts → OCI non recyclable
A4: SECTION 1 – TAUX ANNUELS (Utilisés par Power Query – table de référence)
A5: Devise | B5: Pays | C5: TypeTaux | D5: Exercice | E5: Mois | F5: TauxEUR | G5: TauxInverse | H5: Source | I5: DateMAJ | J5: IAS21_Para | K5: Commentaire
A6: GBP | B6: Royaume-Uni | C6: Clôture | D6: 2025 | E6: 12 | F6: 1.165 | G6: 0.8584 | H6: BCE / BoE | I6: 31/12/2025 | J6: §23 | K6: Bilan – actifs & passifs
A7: GBP | B7: Royaume-Uni | C7: Moyen | D7: 2025 | E7: H1 | F7: 1.152 | G7: 0.8681 | H7: BCE / BoE | I7: 30/06/2025 | J7: §39 | K7: CR – charges & produits S1
A8: GBP | B8: Royaume-Uni | C8: Moyen | D8: 2025 | E8: H2 | F8: 1.158 | G8: 0.8635 | H8: BCE / BoE | I8: 31/12/2025 | J8: §39 | K8: CR – charges & produits S2
A9: GBP | B9: Royaume-Uni | C9: Moyen | D9: 2025 | E9: AN | F9: 1.155 | G9: 0.8658 | H9: BCE / BoE | I9: 31/12/2025 | J9: §39 | K9: CR – taux annuel moyen
A10: GBP | B10: Royaume-Uni | C10: Historique | D10: 2020 | E10: Acq | F10: 1.12 | G10: 0.8929 | H10: BCE | I10: 15/03/2020 | J10: §39 | K10: Capitaux propres – date acquisition UK_Filiale
A11: USD | B11: États-Unis | C11: Clôture | D11: 2025 | E11: 12 | F11: 0.918 | G11: 1.0893 | H11: BCE / Fed | I11: 31/12/2025 | J11: §23 | K11: Bilan – actifs & passifs
A12: USD | B12: États-Unis | C12: Moyen | D12: 2025 | E12: H1 | F12: 0.928 | G12: 1.0776 | H12: BCE / Fed | I12: 30/06/2025 | J12: §39 | K12: CR – charges & produits S1
A13: USD | B13: États-Unis | C13: Moyen | D13: 2025 | E13: H2 | F13: 0.922 | G13: 1.0846 | H13: BCE / Fed | I13: 31/12/2025 | J13: §39 | K13: CR – charges & produits S2
A14: USD | B14: États-Unis | C14: Moyen | D14: 2025 | E14: AN | F14: 0.925 | G14: 1.0811 | H14: BCE / Fed | I14: 31/12/2025 | J14: §39 | K14: CR – taux annuel moyen
A15: USD | B15: États-Unis | C15: Historique | D15: 2021 | E15: Acq | F15: 0.845 | G15: 1.1834 | H15: BCE | I15: 44197 | J15: §39 | K15: Capitaux propres – date acquisition US_Filiale
A16: SGD | B16: Singapour | C16: Clôture | D16: 2025 | E16: 12 | F16: 0.678 | G16: 1.4749 | H16: BCE / MAS | I16: 31/12/2025 | J16: §23 | K16: Bilan – actifs & passifs
A17: SGD | B17: Singapour | C17: Moyen | D17: 2025 | E17: H1 | F17: 0.684 | G17: 1.462 | H17: BCE / MAS | I17: 30/06/2025 | J17: §39 | K17: CR – charges & produits S1
A18: SGD | B18: Singapour | C18: Moyen | D18: 2025 | E18: H2 | F18: 0.68 | G18: 1.4706 | H18: BCE / MAS | I18: 31/12/2025 | J18: §39 | K18: CR – charges & produits S2
A19: SGD | B19: Singapour | C19: Moyen | D19: 2025 | E19: AN | F19: 0.682 | G19: 1.4663 | H19: BCE / MAS | I19: 31/12/2025 | J19: §39 | K19: CR – taux annuel moyen
A20: SGD | B20: Singapour | C20: Historique | D20: 2022 | E20: Acq | F20: 0.65 | G20: 1.5385 | H20: BCE | I20: 44570 | J20: §39 | K20: Capitaux propres – date acquisition SG_Filiale
A21: EUR | B21: France / Allemagne | C21: Clôture | D21: 2025 | E21: 12 | F21: 1 | G21: 1 | H21: N/A | I21: 31/12/2025 | J21: §23 | K21: Devise de présentation – pas de conversion
A22: EUR | B22: France / Allemagne | C22: Moyen | D22: 2025 | E22: AN | F22: 1 | G22: 1 | H22: N/A | I22: 31/12/2025 | J22: §39 | K22: Pas de conversion
A25: SECTION 2 – TAUX MENSUELS 2025 (pour analyses trimestrielles)
A26: Mois | B26: Label | C26: GBP/EUR | D26: USD/EUR | E26: SGD/EUR | F26: Trimestre
A27: 1 | B27: 45658 | C27: 1.148 | D27: 0.932 | E27: 0.685 | F27: T1-2025
A28: 2 | B28: Fév-2025 | C28: 1.151 | D28: 0.929 | E28: 0.684 | F28: T1-2025
A29: 3 | B29: 45717 | C29: 1.155 | D29: 0.926 | E29: 0.683 | F29: T1-2025
A30: 📊 ANALYSE DE SENSIBILITÉ – Impact ±taux de change sur CA des filiales étrangères (k€)
A31: Base: Taux BCE au 31/12/2025. Cellules jaunes = valeur centrale. Lié aux taux F6, F11, F16 ci-dessus → se recalcule à chaque mise à jour des taux.
A32: Devise / Entité | B32: CA local (k devise) | C32: Taux base (live) | D32: CA EUR base | E32: -10% taux | F32: -5% taux | G32: -2.5% taux | H32: Base ★ | I32: +2.5% taux | J32: +5% taux | K32: +10% taux
A33: GBP · UK_Filiale | B33: 142000 | C33: =F6 -> 1.165 | D33: =B33*C33 -> 165430 | E33: =B33*(C33*0.9) -> 148887 | F33: =B33*(C33*0.95) -> 157158.5 | G33: =B33*(C33*0.975) -> 161294.25 | H33: =B33*C33 -> 165430 | I33: =B33*(C33*1.025) -> 169565.75 | J33: =B33*(C33*1.05) -> 173701.5 | K33: =B33*(C33*1.1) -> 181973
A34: USD · US_Filiale | B34: 195000 | C34: =F11 -> 0.918 | D34: =B34*C34 -> 179010 | E34: =B34*(C34*0.9) -> 161109 | F34: =B34*(C34*0.95) -> 170059.5 | G34: =B34*(C34*0.975) -> 174534.75 | H34: =B34*C34 -> 179010 | I34: =B34*(C34*1.025) -> 183485.25 | J34: =B34*(C34*1.05) -> 187960.5 | K34: =B34*(C34*1.1) -> 196911
A35: SGD · SG_Filiale | B35: 88000 | C35: =F16 -> 0.678 | D35: =B35*C35 -> 59664 | E35: =B35*(C35*0.9) -> 53697.6 | F35: =B35*(C35*0.95) -> 56680.8 | G35: =B35*(C35*0.975) -> 58172.4 | H35: =B35*C35 -> 59664 | I35: =B35*(C35*1.025) -> 61155.6 | J35: =B35*(C35*1.05) -> 62647.2 | K35: =B35*(C35*1.1) -> 65630.4
A36: TOTAL CA ÉTRANGER | B36: 45931 | C36: 1.162 | D36: =SUM(D33:D35) -> 404104 | E36: =SUM(E33:E35) -> 363693.6 | F36: =SUM(F33:F35) -> 383898.8 | G36: =SUM(G33:G35) -> 394001.4 | H36: =SUM(H33:H35) -> 404104 | I36: =SUM(I33:I35) -> 414206.6 | J36: =SUM(J33:J35) -> 424309.2 | K36: =SUM(K33:K35) -> 444514.4
A37: Impact Δ vs base | B37: 45962 | C37: 1.164 | D37: 0.916 | E37: =E36-H36 -> -40410.4 | F37: =F36-H36 -> -20205.2 | G37: =G36-H36 -> -10102.6 | H37: — | I37: =I36-H36 -> 10102.6 | J37: =J36-H36 -> 20205.2 | K37: =K36-H36 -> 40410.4
A38: 12 | B38: Déc-2025 | C38: 1.165 | D38: 0.918 | E38: 0.678 | F38: T4-2025
A41: SECTION 3 – CALCUL ÉCART DE CONVERSION (IAS 21 §41 – Impact OCI)
A42: Filiale | B42: Devise | C42: Actif Net (monnaie loc.) | D42: Taux Clôture | E42: Taux Moyen | F42: Actif Net (taux clôt.) | G42: Actif Net (taux moy.) | H42: Écart Conv. OCI
A43: UK_Filiale | B43: GBP | C43: 148800 | D43: 1.165 | E43: 1.155 | F43: =148800*1.165 -> 173352 | G43: =148800*1.155 -> 171864 | H43: =(148800*1.165)-(148800*1.155) -> 1488
A44: US_Filiale | B44: USD | C44: 154200 | D44: 0.918 | E44: 0.925 | F44: =154200*0.918 -> 141555.6 | G44: =154200*0.925 -> 142635 | H44: =(154200*0.918)-(154200*0.925) -> -1079.4
A45: SG_Filiale | B45: SGD | C45: 72800 | D45: 0.678 | E45: 0.682 | F45: =72800*0.678 -> 49358.4 | G45: =72800*0.682 -> 49649.6 | H45: =(72800*0.678)-(72800*0.682) -> -291.2
A46: TOTAL ÉCART DE CONVERSION (→ OCI Bilan consolidé) | H46: =SUM(H43:H45) -> 117.4

Sheet PQ_DETENTION
A1: 🏢 PQ_DETENTION – TABLE % DÉTENTION & CALCUL INTÉRÊTS MINORITAIRES (NCI) · IFRS 10 / IFRS 3
A2: IFRS 10 §22 : Intégration globale si contrôle exclusif (> 50% droits de vote) · IFRS 3 : NCI = % minoritaires × Actif Net JV à date d'acquisition
A4: SECTION 1 – STRUCTURE DE DÉTENTION DU GROUPE (Table de référence Power Query)
A5: EntitéFiliale | B5: EntitéMère | C5: PctDetentionDirecte | D5: PctDetentionIndirecte | E5: PctDetentionTotal | F5: PctNCI | G5: MethodeConsol | H5: Devise | I5: DateAcquisition | J5: TauxHistorique | K5: PrixAcquisition_kEUR | L5: ActifNetJVAcq_kEUR | M5: GoodwillBrut_kEUR | N5: GoodwillNet_kEUR | O5: NormeRegroupement | P5: Commentaire
A6: DE_Filiale | B6: FR_ParentCo | C6: 1 | D6: 0 | E6: 1 | F6: 0 | G6: Intégration Globale | H6: EUR | I6: 43472 | J6: 1 | K6: 85000 | L6: 62000 | M6: 23000 | N6: 19500 | O6: IFRS 3 | P6: 100% → NCI = 0
A7: UK_Filiale | B7: FR_ParentCo | C7: 0.8 | D7: 0 | E7: 0.8 | F7: 0.2 | G7: Intégration Globale | H7: GBP | I7: 15/03/2020 | J7: 1.12 | K7: 72000 | L7: 48500 | M7: 23500 | N7: 19300 | O7: IFRS 3 | P7: 20% NCI → full GW method
A8: US_Filiale | B8: FR_ParentCo | C8: 0.75 | D8: 0 | E8: 0.75 | F8: 0.25 | G8: Intégration Globale | H8: USD | I8: 44197 | J8: 0.845 | K8: 95000 | L8: 71000 | M8: 24000 | N8: 18200 | O8: IFRS 3 | P8: 25% NCI
A9: SG_Filiale | B9: FR_ParentCo | C9: 0.6 | D9: 0 | E9: 0.6 | F9: 0.4 | G9: Intégration Globale | H9: SGD | I9: 44570 | J9: 0.65 | K9: 38000 | L9: 28500 | M9: 9500 | N9: 8300 | O9: IFRS 3 | P9: 40% NCI – attention seuil de contrôle
A10: FR_ParentCo | B10: — | C10: 1 | D10: 0 | E10: 1 | F10: 0 | G10: Mère / Entité présentante | H10: EUR | I10: — | J10: 1 | K10: 0 | L10: 0 | M10: 0 | N10: 0 | O10: — | P10: Société mère – pas de NCI
A13: SECTION 2 – CALCUL NCI PAR COMPOSANTE (IFRS 10 / IFRS 3)
A14: Filiale | B14: % NCI | C14: Actif Net (k€) | D14: NCI Bilan (k€) | E14: RN Filiale (k€) | F14: NCI Résultat (k€) | G14: Dividendes (k€) | H14: NCI Dividendes (k€) | I14: Variation NCI | J14: Commentaire
A15: DE_Filiale | B15: 0 | C15: 148200 | D15: =C15*B15 -> 0 | E15: 18500 | F15: =E15*B15 -> 0 | G15: 5200 | H15: =G15*B15 -> 0 | I15: =D15-H15 -> 0 | J15: NCI=0% × Actif Net EUR
A16: UK_Filiale | B16: 0.2 | C16: 98600 | D16: =C16*B16 -> 19720 | E16: 26096 | F16: =E16*B16 -> 5219.2 | G16: 7200 | H16: =G16*B16 -> 1440 | I16: =D16-H16 -> 18280 | J16: NCI=20% × Actif Net EUR
A17: US_Filiale | B17: 0.25 | C17: 88200 | D17: =C17*B17 -> 22050 | E17: 15800 | F17: =E17*B17 -> 3950 | G17: 4800 | H17: =G17*B17 -> 1200 | I17: =D17-H17 -> 20850 | J17: NCI=25% × Actif Net EUR
A18: SG_Filiale | B18: 0.4 | C18: 38400 | D18: =C18*B18 -> 15360 | E18: 9200 | F18: =E18*B18 -> 3680 | G18: 2400 | H18: =G18*B18 -> 960 | I18: =D18-H18 -> 14400 | J18: NCI=40% × Actif Net EUR
A19: TOTAL NCI CONSOLIDÉ | D19: =SUM(D15:D18) -> 57130 | F19: =SUM(F15:F18) -> 12849.2 | H19: =SUM(H15:H18) -> 3600
A22: SECTION 3 – SCHÉMA HIÉRARCHIQUE DU PÉRIMÈTRE
A23: FR_ParentCo (Holding – 100% Groupe)
A24: ├── DE_Filiale ← 100% (EUR) · Industrie · NCI = 0%
A25: ├── UK_Filiale ← 80% (GBP) · Tech & Digital · NCI = 20%
A26: ├── US_Filiale ← 75% (USD) · Distribution · NCI = 25%
A27: └── SG_Filiale ← 60% (SGD) · Finance & Inv. · NCI = 40%
A28: Méthode : INTÉGRATION GLOBALE (IFRS 10) · Goodwill : FULL GW (IFRS 3) · IAS 36 tests annuels

Sheet PQ_ELIMINATIONS
A1: 🔄 PQ_ELIMINATIONS – MOTEUR D'ÉLIMINATIONS INTRAGROUPE AUTOMATISÉES · 4 TYPES · IFRS 10
A3: TYPE 1 – ÉLIMINATION DES VENTES / ACHATS INTRAGROUPE (IFRS 10 §B86)
A4: RefElim | B4: Vendeur | C4: Acheteur | D4: Devise | E4: TxConversion | F4: MontantLocal | G4: MontantEUR | H4: CompteCA_Elim | I4: CompteAchats_Elim | J4: CompteIC_Actif | K4: CompteIC_Passif | L4: Statut | M4: Validation
A5: V-IC-001 | B5: FR_ParentCo | C5: DE_Filiale | D5: EUR | E5: 1 | F5: 18500 | G5: 18500 | H5: 708500 | I5: 601000 | J5: 451000 | K5: 451500 | L5: ✅ Équilibré | M5: =IF(F5=G5,"✅ OK","⚠️ ÉCART") -> ✅ OK
A6: V-IC-002 | B6: FR_ParentCo | C6: UK_Filiale | D6: GBP | E6: 1.165 | F6: 12400 | G6: 14446 | H6: 708500 | I6: 601000 | J6: 451000 | K6: 451500 | L6: ✅ Équilibré | M6: =IF(F6*E6=G6,"✅ OK","⚠️ ÉCART") -> ✅ OK
A7: V-IC-003 | B7: FR_ParentCo | C7: US_Filiale | D7: USD | E7: 0.918 | F7: 8500 | G7: 7803 | H7: 708500 | I7: 601000 | J7: 451000 | K7: 451500 | L7: ✅ Équilibré | M7: =IF(F7*E7=G7,"✅ OK","⚠️ ÉCART") -> ✅ OK
A8: V-IC-004 | B8: DE_Filiale | C8: UK_Filiale | D8: GBP | E8: 1.165 | F8: 3200 | G8: 3728 | H8: 708500 | I8: 601000 | J8: 451000 | K8: 451500 | L8: ✅ Équilibré | M8: =IF(F8*E8=G8,"✅ OK","⚠️ ÉCART") -> ✅ OK
A9: TOTAL ÉLIM. VENTES IC | G9: =SUM(G5:G8) -> 44477
A11: 📝 ÉCRITURE COMPTABLE – Élimination ventes IC (exemple V-IC-001 : 18 500 k€)
A12: Débit | B12: 708500 – Refacturations IC (CA vendeur) | C12: 18 500 | D12: Crédit | E12: 601000 – Achats marchandises (CA acheteur) | F12: 18 500 | G12: → Neutralise le CA et le coût d'achat IC
A15: TYPE 2 – ÉLIMINATION DES MARGES INTRAGROUPE SUR STOCKS (IFRS 10 §B86(b))
A16: RefElim | B16: Vendeur | C16: Acheteur | D16: StockRestant_kEUR | E16: CoutRevient_kEUR | F16: PrixVenteIC_kEUR | G16: MargeIC_kEUR | H16: TauxMarge | I16: ImpactBilan_Stocks | J16: ImpactCR_Achats | K16: ImpactFiscal_kEUR | L16: Compte
A17: M-IC-001 | B17: FR_ParentCo | C17: DE_Filiale | D17: 6400 | E17: 4800 | F17: 6400 | G17: =F17-E17 -> 1600 | H17: =G17/F17 -> 0.25 | I17: =-G17 -> -1600 | J17: =G17 -> 1600 | K17: =-G17*0.25 -> -400 | L17: 311000/601000
A18: M-IC-002 | B18: FR_ParentCo | C18: UK_Filiale | D18: 6400 | E18: 4800 | F18: 6400 | G18: =F18-E18 -> 1600 | H18: =G18/F18 -> 0.25 | I18: =-G18 -> -1600 | J18: =G18 -> 1600 | K18: =-G18*0.25 -> -400 | L18: 311000/601000
A19: TOTAL MARGES IC À ÉLIMINER | G19: =SUM(G17:G18) -> 3200 | I19: =SUM(I17:I18) -> -3200 | K19: =SUM(K17:K18) -> -800
A20: ⚠️ IAS 12 : La marge éliminée génère un impôt différé actif (IDA) car la charge sera déductible lors de la vente finale à un tiers. Taux IS appliqué : 25%
A23: TYPE 3 – ÉLIMINATION DES DIVIDENDES INTRAGROUPE (IFRS 10 §B86(a))
A24: RefElim | B24: DistributeurDividende | C24: Bénéficiaire | D24: Devise | E24: TxConv | F24: DividendeLocal | G24: DividendeEUR | H24: ProdFin_Elim(761) | I24: Dividendes_Elim(457) | J24: NormeRef
A25: D-IC-001 | B25: DE_Filiale | C25: FR_ParentCo | D25: EUR | E25: 1 | F25: 4200 | G25: 4200 | H25: 761000 | I25: =H25 -> 761000 | J25: IFRS 18 §68 + IFRS 10
A26: D-IC-002 | B26: UK_Filiale | C26: FR_ParentCo | D26: GBP | E26: 1.165 | F26: 2800 | G26: 3262 | H26: 761000 | I26: =H26 -> 761000 | J26: IFRS 18 §68 + IFRS 10
A27: D-IC-003 | B27: US_Filiale | C27: FR_ParentCo | D27: USD | E27: 0.918 | F27: 1800 | G27: 1652 | H27: 761000 | I27: =H27 -> 761000 | J27: IFRS 18 §68 + IFRS 10
A28: TOTAL ÉLIM. DIVIDENDES IC | G28: =SUM(G25:G27) -> 9114
A29: 🆕 IFRS 18 §68 : Les dividendes reçus d'une entité non consolidée restent en Investissement. Les dividendes IC sont ÉLIMINÉS avant toute catégorisation IFRS 18.
A32: TYPE 4 – ÉLIMINATION DES PRÊTS / EMPRUNTS INTRAGROUPE + INTÉRÊTS (IFRS 10 §B86)
A33: RefElim | B33: Prêteur | C33: Emprunteur | D33: Devise | E33: TxConv | F33: CapitalLocal | G33: CapitalEUR | H33: TauxIntérêt | I33: IntérêtsEUR | J33: CompteActif | K33: ComptePssif | L33: EcartConv
A34: P-IC-001 | B34: FR_ParentCo | C34: SG_Filiale | D34: SGD | E34: 0.678 | F34: 5200 | G34: 3526 | H34: 0.045 | I34: =G34*H34 -> 158.67 | J34: 274100 | K34: 167100 | L34: =I34*0.03 -> 4.7601
A35: P-IC-002 | B35: FR_ParentCo | C35: UK_Filiale | D35: GBP | E35: 1.165 | F35: 3800 | G35: 4427 | H35: 0.038 | I35: =G35*H35 -> 168.226 | J35: 274100 | K35: 167100 | L35: =I35*0.03 -> 5.04678
A36: TOTAL PRÊTS IC | G36: =SUM(G34:G35) -> 7953 | I36: =SUM(I34:I35) -> 326.896
A39: 📊 RÉCAPITULATIF GLOBAL DES ÉLIMINATIONS – IMPACT SUR LES ÉTATS FINANCIERS CONSOLIDÉS
A40: Type Élimination | B40: Impact CR (k€) | C40: Impact Bilan (k€) | D40: Impact IDA (k€) | E40: Impact OCI (k€) | F40: Norme
A41: Ventes IC (CA + Achats) | B41: =-G9 -> -44477 | C41: 0 | D41: 0 | E41: 0 | F41: IFRS 10 §B86(b)
A42: Marges stocks IC | B42: =-G19 -> -3200 | C42: =I19 -> -3200 | D42: =K19 -> -800 | E42: 0 | F42: IFRS 10 §B86 + IAS 12
A43: Dividendes IC | B43: =-G28 -> -9114 | C43: 0 | D43: 0 | E43: 0 | F43: IFRS 10 §B86(a) + IFRS 18 §68
A44: Prêts IC (capital) | B44: 0 | C44: =-G36 -> -7953 | D44: 0 | E44: =L36 -> 0 | F44: IFRS 10 + IAS 21
A45: Prêts IC (intérêts) | B45: =-I36 -> -326.896 | C45: 0 | D45: 0 | E45: 0 | F45: IFRS 18 §72
A46: TOTAL IMPACT ÉLIMINATIONS | B46: =SUM(B41:B45) -> -57117.896 | C46: =SUM(C41:C45) -> -11153 | D46: =SUM(D41:D45) -> -800 | E46: =SUM(E41:E45) -> 0

Sheet PQ_DAX_MESURES
A1: ⚡ PQ_DAX_MESURES – BIBLIOTHÈQUE COMPLÈTE DES MESURES DAX · Power Pivot · Consolidation IFRS 18
A2: Coller chaque mesure dans Power Pivot (Accueil → Mesures) ou dans le modèle de données. Préfixe : [M_] pour les mesures, [C_] pour les colonnes calculées.
A4: // ══════════════════════════════════════════════════════════════════ // GROUPE A – MESURES DE BASE (CA / RÉSULTAT) // ══════════════════════════════════════════════════════════════════
A5: Nom mesure | B5: Table | C5: Description | D5: Code DAX | G5: Norme / Référence
A6: [M_CA_Groupe] | B6: Balances_PQ | C6: Chiffre d'affaires consolidé (hors IC) | D6: [M_CA_Groupe] = CALCULATE( SUMX( FILTER('Balances_PQ', 'Balances_PQ'[PosteGroupeIFRS18] = "Chiffre d'affaires" && 'Balances_PQ'[EstIC] = FALSE() ), 'Balances_PQ'[MontantEUR] ) ) | G6: IFRS 15 / IFRS 18 §55
A7: [M_EBIT] | B7: Balances_PQ | C7: Résultat Opérationnel – catégorie ① Exploitation uniquement | D7: [M_EBIT] = CALCULATE( SUM('Balances_PQ'[MontantEUR]), 'Balances_PQ'[CatIFRS18_Finale] = "① Exploitation", 'Balances_PQ'[EstIC] = FALSE() ) | G7: IFRS 18 §55-67
A8: [M_EBITDA] | B8: Balances_PQ | C8: EBIT + amortissements & provisions (add-back) | D8: [M_EBITDA] = [M_EBIT] + CALCULATE( ABS(SUM('Balances_PQ'[MontantEUR])), 'Balances_PQ'[PosteGroupeIFRS18] = "Amortissements & dépréciations" ) + CALCULATE( ABS(SUM('Balances_PQ'[MontantEUR])), 'Balances_PQ'[PosteGroupeIFRS18] = "Dotations aux provisions" ) | G8: MPM – IFRS 18 §112 (rapprochement obligatoire)
A9: [M_RésInvest] | B9: Balances_PQ | C9: Résultat de la catégorie ② Investissement (IFRS 18 §68) | D9: [M_RésInvest] = CALCULATE( SUM('Balances_PQ'[MontantEUR]), 'Balances_PQ'[CatIFRS18_Finale] = "② Investissement", 'Balances_PQ'[EstIC] = FALSE() ) | G9: IFRS 18 §68-71
A10: [M_ProfitAvtFinImpôt] | B10: Balances_PQ | C10: 🆕 IFRS 18 §65 – Sous-total imposé : Exploitation + Investissement | D10: [M_ProfitAvtFinImpôt] = [M_EBIT] + [M_RésInvest] // Ce sous-total est IMPOSÉ par IFRS 18 // Il remplace le « résultat courant » de IAS 1 | G10: IFRS 18 §65 – NOUVEAU sous-total obligatoire
A11: [M_RésFin] | B11: Balances_PQ | C11: Résultat catégorie ③ Financement | D11: [M_RésFin] = CALCULATE( SUM('Balances_PQ'[MontantEUR]), 'Balances_PQ'[CatIFRS18_Finale] = "③ Financement" ) | G11: IFRS 18 §72-79
A12: [M_ChargeIS] | B12: Balances_PQ | C12: Charge d'impôt totale (courant + différé) | D12: [M_ChargeIS] = CALCULATE( SUM('Balances_PQ'[MontantEUR]), 'Balances_PQ'[CatIFRS18_Finale] = "④ Impôts" ) | G12: IAS 12 / IFRS 18 §80
A13: [M_RésNetConsolidé] | B13: Balances_PQ | C13: Résultat net consolidé (part groupe + NCI) | D13: [M_RésNetConsolidé] = [M_ProfitAvtFinImpôt] + [M_RésFin] + [M_ChargeIS] | G13: IFRS 18 §80-84
A15: // ══════════════════════════════════════════════════════════════════ // GROUPE B – MARGES & RATIOS // ══════════════════════════════════════════════════════════════════
A16: Nom mesure | B16: Table | C16: Description | D16: Code DAX | G16: Norme / Référence
A17: [M_MargeEBIT] | B17: Mesures | C17: Marge EBIT en % du CA | D17: [M_MargeEBIT] = DIVIDE([M_EBIT], [M_CA_Groupe], 0) | G17: KPI interne
A18: [M_MargeEBITDA] | B18: Mesures | C18: Marge EBITDA en % du CA | D18: [M_MargeEBITDA] = DIVIDE([M_EBITDA], [M_CA_Groupe], 0) | G18: MPM – IFRS 18 §112
A19: [M_MargeNette] | B19: Mesures | C19: Marge nette consolidée en % du CA | D19: [M_MargeNette] = DIVIDE([M_RésNetConsolidé], [M_CA_Groupe], 0) | G19: KPI groupe
A20: [M_TauxIS_Effectif] | B20: Mesures | C20: Taux effectif d'imposition consolidé | D20: [M_TauxIS_Effectif] = DIVIDE( ABS([M_ChargeIS]), [M_ProfitAvtFinImpôt] + [M_RésFin], 0 ) // Rapprocher du taux légal FR 25% (Note IFRS) | G20: IAS 12 §81(c)
A22: // ══════════════════════════════════════════════════════════════════ // GROUPE C – CONVERSION & DEVISES (IAS 21) // ══════════════════════════════════════════════════════════════════
A23: Nom mesure | B23: Table | C23: Description | D23: Code DAX | G23: Norme / Référence
A24: [M_MontantEUR_TxClôture] | B24: Balances_PQ | C24: Montant converti au taux de clôture (Bilan – IAS 21 §23) | D24: [M_MontantEUR_TxClôture] = SUMX( 'Balances_PQ', 'Balances_PQ'[Montant] * LOOKUPVALUE( 'PQ_TAUX_CHANGE'[TauxEUR], 'PQ_TAUX_CHANGE'[Devise], 'Balances_PQ'[Devise], 'PQ_TAUX_CHANGE'[TypeTaux], "Clôture", 'PQ_TAUX_CHANGE'[Exercice], "2025", 1 ) ) | G24: IAS 21 §23
A25: [M_MontantEUR_TxMoyen] | B25: Balances_PQ | C25: Montant converti au taux moyen (CR – IAS 21 §39) | D25: [M_MontantEUR_TxMoyen] = SUMX( 'Balances_PQ', 'Balances_PQ'[Montant] * LOOKUPVALUE( 'PQ_TAUX_CHANGE'[TauxEUR], 'PQ_TAUX_CHANGE'[Devise], 'Balances_PQ'[Devise], 'PQ_TAUX_CHANGE'[TypeTaux], "Moyen", 'PQ_TAUX_CHANGE'[Mois], "AN", 1 ) ) | G25: IAS 21 §39
A26: [M_ÉcartConversion_OCI] | B26: Mesures | C26: Écart de conversion à inscrire en OCI (non recyclable) | D26: [M_ÉcartConversion_OCI] = [M_MontantEUR_TxClôture] - [M_MontantEUR_TxMoyen] // → Classé en OCI, jamais recyclé en résultat // Référence : IAS 21 §41 | G26: IAS 21 §41 – OCI
A28: // ══════════════════════════════════════════════════════════════════ // GROUPE D – NCI & CAPITAUX PROPRES // ══════════════════════════════════════════════════════════════════
A29: Nom mesure | B29: Table | C29: Description | D29: Code DAX | G29: Norme / Référence
A30: [M_NCI_Bilan] | B30: PQ_DETENTION | C30: Intérêts minoritaires au bilan consolidé | D30: [M_NCI_Bilan] = SUMX( 'PQ_DETENTION', 'PQ_DETENTION'[PctNCI] * RELATED('Balances_PQ'[MontantEUR]) ) // Simplifié : utiliser directement la colonne NCI Bilan de PQ_DETENTION | G30: IFRS 10 §22 / IFRS 3
A31: [M_RésNet_PartGroupe] | B31: Mesures | C31: Résultat net – part revenant aux actionnaires du groupe | D31: [M_RésNet_PartGroupe] = [M_RésNetConsolidé] - SUMX( 'PQ_DETENTION', 'PQ_DETENTION'[PctNCI] * CALCULATE(SUM('Balances_PQ'[MontantEUR]), 'Balances_PQ'[CatIFRS18_Finale] = "④ Impôts", USERELATIONSHIP('Balances_PQ'[EntitéNormalisée],'PQ_DETENTION'[EntitéFiliale]) ) ) | G31: IFRS 10 §B94
A33: // ══════════════════════════════════════════════════════════════════ // GROUPE E – ÉLIMINATIONS AUTOMATIQUES // ══════════════════════════════════════════════════════════════════
A34: Nom mesure | B34: Table | C34: Description | D34: Code DAX | G34: Norme / Référence
A35: [M_ElimVentesIC] | B35: Mesures | C35: Total éliminations CA interco (retirer du CA consolidé) | D35: [M_ElimVentesIC] = CALCULATE( SUM('Balances_PQ'[MontantEUR]), 'Balances_PQ'[EstIC] = TRUE(), 'Balances_PQ'[TypeFlux] = "Crédit", 'Balances_PQ'[CatIFRS18_Finale] = "⚠️ Élimination IC" ) | G35: IFRS 10 §B86(b)
A36: [M_CA_Net_Elim] | B36: Mesures | C36: CA consolidé après élimination IC | D36: [M_CA_Net_Elim] = [M_CA_Groupe] - [M_ElimVentesIC] // Ce montant = CA publié dans les états financiers | G36: IFRS 10 + IFRS 15
A37: [M_ElimDividendesIC] | B37: Mesures | C37: Dividendes IC éliminés (résultat investissement) | D37: [M_ElimDividendesIC] = CALCULATE( SUM('Balances_PQ'[MontantEUR]), 'Balances_PQ'[EstIC] = TRUE(), 'Balances_PQ'[PosteGroupeIFRS18] = "Dividendes reçus" ) | G37: IFRS 10 §B86(a) + IFRS 18 §68
A39: // ══════════════════════════════════════════════════════════════════ // GROUPE F – CASH FLOW (IAS 7) // ══════════════════════════════════════════════════════════════════
A40: Nom mesure | B40: Table | C40: Description | D40: Code DAX | G40: Norme / Référence
A41: [M_FCF_Exploitation] | B41: Mesures | C41: Free Cash Flow d'exploitation (méthode indirecte) | D41: [M_FCF_Exploitation] = [M_EBIT] + CALCULATE( ABS(SUM('Balances_PQ'[MontantEUR])), 'Balances_PQ'[PosteGroupeIFRS18] = "Amortissements & dépréciations" ) - [M_Var_BFR] // Ajouter la variation de BFR (calculée séparément) | G41: IAS 7 §20
A42: [M_Var_BFR] | B42: Mesures | C42: Variation du BFR (Stocks + Créances – Dettes) | D42: [M_Var_BFR] = // Δ Stocks + Δ Créances Clients - Δ Dettes Fournisseurs // Source : CONSOL_BILAN N vs N-1 CALCULATE(SUM('CONSOL_BILAN'[Consolidé_N]),'CONSOL_BILAN'[PosteIFRS]="Stocks") - CALCULATE(SUM('CONSOL_BILAN'[Consolidé_N1]),'CONSOL_BILAN'[PosteIFRS]="Stocks") | G42: IAS 7 §20(b)
A43: [M_TrésoClôture] | B43: Mesures | C43: Trésorerie de clôture consolidée (contrôle IAS 7 §45) | D43: [M_TrésoClôture] = CALCULATE( SUM('Balances_PQ'[MontantEUR]), 'Balances_PQ'[PosteGroupeIFRS18] = "Trésorerie", 'Balances_PQ'[TypeFlux] = "Actif", 'Balances_PQ'[EstIC] = FALSE() ) | G43: IAS 7 §45
A45: // ══════════════════════════════════════════════════════════════════ // GROUPE G – MESURES TEMPORELLES & YOY // ══════════════════════════════════════════════════════════════════
A46: Nom mesure | B46: Table | C46: Description | D46: Code DAX | G46: Norme / Référence
A47: [M_CA_N1] | B47: Mesures | C47: CA consolidé N-1 (année précédente) | D47: [M_CA_N1] = CALCULATE( [M_CA_Net_Elim], SAMEPERIODLASTYEAR('Calendrier'[Date]) ) // Requiert une table Calendrier marquée comme table de dates | G47: IAS 1 §38 – comparatif obligatoire
A48: [M_CA_CroissYOY] | B48: Mesures | C48: Croissance CA year-over-year | D48: [M_CA_CroissYOY] = DIVIDE( [M_CA_Net_Elim] - [M_CA_N1], ABS([M_CA_N1]), BLANK() ) | G48: Analyse de performance
A49: [M_EBIT_CroissYOY] | B49: Mesures | C49: Croissance EBIT year-over-year | D49: [M_EBIT_CroissYOY] = DIVIDE( [M_EBIT] - CALCULATE([M_EBIT], SAMEPERIODLASTYEAR('Calendrier'[Date])), ABS(CALCULATE([M_EBIT], SAMEPERIODLASTYEAR('Calendrier'[Date]))), BLANK() ) | G49: IFRS 18 §113 – MPM
A50: [M_CA_YTD] | B50: Mesures | C50: CA cumulé depuis début d'exercice (Year-to-Date) | D50: [M_CA_YTD] = CALCULATEX( [M_CA_Net_Elim], DATESYTD('Calendrier'[Date], "12/31") ) | G50: Suivi mensuel
A52: // ══════════════════════════════════════════════════════════════════ // GROUPE H – COLONNES CALCULÉES (Power Query / Power Pivot) // ══════════════════════════════════════════════════════════════════
A53: Nom mesure | B53: Table | C53: Description | D53: Code DAX | G53: Norme / Référence
A54: [C_CatIFRS18_Label] | B54: Balances_PQ | C54: Colonne calculée : label enrichi catégorie IFRS 18 | D54: [C_CatIFRS18_Label] = SWITCH( TRUE(), 'Balances_PQ'[CatIFRS18_Finale] = "① Exploitation", "① Exploitation (Operating)", 'Balances_PQ'[CatIFRS18_Finale] = "② Investissement", "② Investissement (Investing)", 'Balances_PQ'[CatIFRS18_Finale] = "③ Financement", "③ Financement (Financing)", 'Balances_PQ'[CatIFRS18_Finale] = "④ Impôts", "④ Impôts (IAS 12)", 'Balances_PQ'[CatIFRS18_Finale] = "⚠️ Élimination IC", "⚠️ IC – À éliminer", 'Balances_PQ'[CatIFRS18_Finale] ) | G54: IFRS 18 – 5 catégories
A55: [C_SigneNormalisé] | B55: Balances_PQ | C55: Colonne calculée : convention de signe (crédit = positif, débit = négatif) | D55: [C_SigneNormalisé] = IF( 'Balances_PQ'[TypeFlux] = "Débit", -1 * 'Balances_PQ'[MontantEUR], 'Balances_PQ'[MontantEUR] ) // Convention : Charges en négatif, Produits en positif | G55: Convention comptable universelle

Sheet PQ_M_AVANCE
A1: ⚙️ PQ_M_AVANCE – REQUÊTES POWER QUERY M AVANCÉES · CR IFRS 18 · BILAN · CASH FLOW · ÉLIMINATIONS AUTO
A2: 4 requêtes M supplémentaires à ajouter dans l'éditeur Power Query. Elles utilisent 'Consolidation_FromFolder' comme source.
A4: REQUÊTE 4 : « CR_IFRS18_Consolidé » – Compte de Résultat formaté IFRS 18
A5: let
A6: // ─── SOURCE ──────────────────────────────────────────────────────────────
A7: Source = Consolidation_FromFolder,
A9: // ─── EXCLURE LES LIGNES IC À ÉLIMINER ────────────────────────────────────
A10: SansIC = Table.SelectRows(Source, each not [EstIC]),
A12: // ─── EXCLURE LES POSTES DE BILAN ──────────────────────────────────────────
A13: SeulementCR = Table.SelectRows(SansIC, each
A14: [CatIFRS18_Finale] <> "Bilan" and [TypeFlux] <> "Actif" and [TypeFlux] <> "Passif"),
A16: // ─── NORMALISER LE SIGNE (Charges = négatif, Produits = positif) ──────────
... A216: Typé

Sheet FORMULES_LIAISON
A1: 🔗 FORMULES_LIAISON – TABLEAU DE BORD DES LIAISONS ENTRE ONGLETS · Cartographie complète
A2: Ce tableau documente toutes les formules de liaison inter-onglets. Colonne F = formule à copier dans la cellule cible. Mettre à jour si structure des onglets change.
A3: # | B3: Onglet Cible | C3: Cellule Cible | D3: Poste / Label | E3: Onglet Source | F3: Cellule Source | G3: Formule à utiliser | H3: TypeConversion | I3: Norme | J3: Criticité | K3: Commentaire
A4: 1 | B4: CONSOL_CR | C4: D7 | D4: CA FR_ParentCo | E4: FR_ParentCo | F4: D30 | G4: =FR_ParentCo!D30 -> 571100 | H4: Aucune (EUR) | I4: IFRS 15 | J4: 🔴 Critique | K4: CA société mère
A5: 2 | B5: CONSOL_CR | C5: E7 | D5: CA DE_Filiale | E5: DE_Filiale | F5: D30 | G5: =DE_Filiale!D30 -> 168000 | H5: Aucune (EUR) | I5: IFRS 15 | J5: 🔴 Critique | K5: CA filiale DE
A6: 3 | B6: CONSOL_CR | C6: F7 | D6: CA UK_Filiale (EUR) | E6: UK_Filiale | F6: D30 | G6: =UK_Filiale!D30*PQ_TAUX_CHANGE!F7 -> 163584 | H6: ×1.1650 Tx moy. | I6: IAS 21 §39 | J6: 🔴 Critique | K6: CA UK converti EUR au taux moyen
A7: 4 | B7: CONSOL_CR | C7: G7 | D7: CA US_Filiale (EUR) | E7: US_Filiale | F7: D30 | G7: =US_Filiale!D30*PQ_TAUX_CHANGE!F11 -> 179010 | H7: ×0.9250 Tx moy. | I7: IAS 21 §39 | J7: 🔴 Critique | K7: CA US converti EUR au taux moyen
A8: 5 | B8: CONSOL_CR | C8: H7 | D8: CA SG_Filiale (EUR) | E8: SG_Filiale | F8: D30 | G8: =SG_Filiale!D30*PQ_TAUX_CHANGE!F14 -> 81400 | H8: ×0.6820 Tx moy. | I8: IAS 21 §39 | J8: 🔴 Critique | K8: CA SG converti EUR au taux moyen
A9: 6 | B9: CONSOL_CR | C9: I7 | D9: Éliminations IC CA | E9: ELIM | F9: I13 | G9: =-ELIM!I13 -> 0 | H9: Négatif | I9: IFRS 10 | J9: 🔴 Critique | K9: Neutralisation CA interco
A10: 7 | B10: CONSOL_CR | C10: K7 | D10: CA CONSOLIDÉ | E10: CONSOL_CR | F10: K7 | G10: =CONSOL_CR!K7 -> 817075 | H10: Agrégé | I10: IFRS 18 | J10: 🔴 Critique | K10: Total CA groupe consolidé
A11: 8 | B11: CONSOL_CR | C11: K14 | D11: EBIT CONSOLIDÉ | E11: CONSOL_CR | F11: K14 | G11: =CONSOL_CR!K14 -> 153798 | H11: Agrégé | I11: IFRS 18 §55 | J11: 🔴 Critique | K11: Résultat opérationnel
A12: 9 | B12: CONSOL_CR | C12: K19 | D12: Résultat Invest. | E12: CONSOL_CR | F12: K19 | G12: =CONSOL_CR!K19 -> 6521 | H12: Agrégé | I12: IFRS 18 §68 | J12: 🔴 Critique | K12: Catégorie ② Investissement
A13: 10 | B13: CONSOL_CR | C13: K24 | D13: Profit avt Fin/IS | E13: CONSOL_CR | F13: K24 | G13: =CONSOL_CR!K24 -> 160319 | H13: Agrégé | I13: IFRS 18 §65 | J13: 🔴 Critique | K13: 🆕 NOUVEAU sous-total IFRS 18
A14: 11 | B14: CONSOL_BILAN | C14: C6 | D14: GW net FR | E14: FR_ParentCo | F14: D16 | G14: =FR_ParentCo!D16 -> 85000 | H14: Aucune | I14: IFRS 3 | J14: 🔴 Critique | K14: Goodwill net société mère
A15: 12 | B15: CONSOL_BILAN | C15: D6 | D15: GW net DE | E15: DE_Filiale | F15: D16 | G15: =DE_Filiale!D16 -> 18000 | H15: Aucune (EUR) | I15: IFRS 3 | J15: 🔴 Critique | K15: Goodwill net DE
A16: 13 | B16: CONSOL_BILAN | C16: E6 | D16: GW net UK (EUR) | E16: UK_Filiale | F16: C16 | G16: =UK_Filiale!D16*PQ_TAUX_CHANGE!F6 -> 52425 | H16: ×1.1650 Tx clôt. | I16: IAS 21 §23 | J16: 🔴 Critique | K16: GW UK converti au taux de clôture
A17: 14 | B17: CONSOL_BILAN | C17: F6 | D17: GW net US (EUR) | E17: US_Filiale | F17: C16 | G17: =US_Filiale!D16*PQ_TAUX_CHANGE!F10 -> 13440 | H17: ×0.9180 Tx clôt. | I17: IAS 21 §23 | J17: 🔴 Critique | K17: GW US converti au taux de clôture
A18: 15 | B18: CONSOL_BILAN | C18: G6 | D18: GW net SG (EUR) | E18: SG_Filiale | F18: C16 | G18: =SG_Filiale!D16*PQ_TAUX_CHANGE!F13 -> 25816 | H18: ×0.6780 Tx clôt. | I18: IAS 21 §23 | J18: 🔴 Critique | K18: GW SG converti au taux de clôture
A19: 16 | B19: CONSOL_BILAN | C19: I6 | D19: Élim. Titres & GW | E19: ELIM | F19: H21 | G19: =-ELIM!D17 -> -85000 | H19: Négatif | I19: IFRS 3 | J19: 🔴 Critique | K19: Élimination titres participation
A20: 17 | B20: CONSOL_BILAN | C20: J6 | D20: GW net consolidé | E20: CONSOL_BILAN | F20: J6 | G20: =CONSOL_BILAN!J6 -> 59135 | H20: Agrégé | I20: IFRS 3 | J20: 🔴 Critique | K20: Goodwill groupe net
A21: 18 | B21: CONSOL_BILAN | C21: J18 | D21: Trésorerie consol. | E21: CONSOL_TRESORERIE | F21: C28 | G21: =CONSOL_TRESORERIE!C28 -> 220091 | H21: Contrôle croisé | I21: IAS 7 | J21: 🔴 Critique | K21: Doit = Tréso clôture TFT
A22: 19 | B22: CONSOL_BILAN | C22: J20 | D22: TOTAL ACTIF | E22: CONSOL_BILAN | F22: J20 | G22: =CONSOL_BILAN!J20 -> 1385405 | H22: Contrôle | I22: IAS 1 | J22: 🔴 Critique | K22: Doit = Total Passif (J41)
A23: 20 | B23: CONSOL_BILAN | C23: J41 | D23: TOTAL PASSIF | E23: CONSOL_BILAN | F23: J41 | G23: =CONSOL_BILAN!J41 -> 970454 | H23: Contrôle | I23: IAS 1 | J23: 🔴 Critique | K23: Doit = Total Actif (J20)
A24: 21 | B24: CONSOL_BILAN | C24: K24 | D24: Résultat exercice | E24: CONSOL_CR | F24: K30 | G24: =CONSOL_CR!K30 -> 82110 | H24: Lien direct | I24: IAS 1 | J24: 🔴 Critique | K24: Résultat net → Capitaux propres
A25: 22 | B25: CONSOL_BILAN | C25: K27 | D25: NCI Bilan | E25: PQ_DETENTION | F25: D17 | G25: =PQ_DETENTION!D17 -> 22050 | H25: Calculé | I25: IFRS 10 | J25: 🔴 Critique | K25: Intérêts minoritaires au bilan
A26: 23 | B26: CONSOL_TRESORERIE | C26: C6 | D26: Résultat net départ | E26: CONSOL_CR | F26: K30 | G26: =CONSOL_CR!K30 -> 82110 | H26: Lien direct | I26: IAS 7 §20 | J26: 🔴 Critique | K26: Point de départ méthode indirecte
A27: 24 | B27: CONSOL_TRESORERIE | C27: C12 | D27: Amortissements add-back | E27: CONSOL_CR | F27: K12 | G27: =-CONSOL_CR!K12 -> 62653 | H27: Signe inversé | I27: IAS 7 §20 | J27: 🔴 Critique | K27: Amort. charges → flux positif TFT
A28: 25 | B28: CONSOL_TRESORERIE | C28: C14 | D28: CAPEX | E28: CONSOL_CR | F28: — | G28: =-48200 -> -48200 | H28: Référence | I28: IAS 7 §16 | J28: 🟠 Important | K28: Acquisitions d'actifs (valeur saisie)
A29: 26 | B29: CONSOL_TRESORERIE | C29: C28 | D29: Tréso clôture | E29: CONSOL_BILAN | F29: J18 | G29: =CONSOL_BILAN!J18 -> 170012 | H29: Contrôle croisé | I29: IAS 7 §45 | J29: 🔴 Critique | K29: Contrôle bilan = TFT
A30: 27 | B30: DASHBOARD_FIN | C30: C6 | D30: KPI CA groupe | E30: CONSOL_CR | F30: K7 | G30: =CONSOL_CR!K7 -> 817075 | H30: Lien direct | I30: IFRS 15 | J30: 🟠 Important | K30: Carte KPI principale
A31: 28 | B31: DASHBOARD_FIN | C31: C7 | D31: KPI EBIT | E31: CONSOL_CR | F31: K14 | G31: =CONSOL_CR!K14 -> 153798 | H31: Lien direct | I31: IFRS 18 | J31: 🟠 Important | K31: Carte KPI EBIT
A32: 29 | B32: DASHBOARD_FIN | C32: C11 | D32: EBITDA | E32: CONSOL_CR | F32: — | G32: =CONSOL_CR!K14-CONSOL_CR!K12 -> 216451 | H32: Calcul | I32: IFRS 18 MPM | J32: 🟠 Important | K32: EBIT + amort.
A33: 30 | B33: DASHBOARD_FIN | C33: E24 | D33: Profit avt Fin&IS | E33: CONSOL_CR | F33: K24 | G33: =CONSOL_CR!K24 -> 160319 | H33: Lien direct | I33: IFRS 18 §65 | J33: 🔴 Critique | K33: 🆕 Sous-total IFRS 18 obligatoire
A34: 31 | B34: DASHBOARD_FIN | C34: C31 | D34: NCI Résultat | E34: PQ_DETENTION | F34: F17 | G34: =PQ_DETENTION!F17 -> 3950 | H34: Lien direct | I34: IFRS 10 | J34: 🟡 Standard | K34: Part minoritaires résultat
A35: 32 | B35: DASHBOARD_ESG | C35: C12 | D35: Scope 1+2 CO₂ | E35: ESG_DATA | F35: I6+I7 | G35: =ESG_DATA!I6+ESG_DATA!I7 -> 112500 | H35: Agrégé | I35: ESRS E1-6 | J35: 🟠 Important | K35: Émissions GES Scope 1+2
A36: 33 | B36: DASHBOARD_ESG | C36: C21 | D36: % Femmes total | E36: ESG_DATA | F36: J21 | G36: =ESG_DATA!J21 -> 🟢 | H36: Lien direct | I36: ESRS S1-9 | J36: 🟡 Standard | K36: Parité groupe
A37: 34 | B37: DASHBOARD_ESG | C37: C22 | D37: % Femmes dirigeantes | E37: ESG_DATA | F37: J22 | G37: =ESG_DATA!J22 -> 🟢 | H37: Lien direct | I37: ESRS S1-9 | J37: 🟡 Standard | K37: Diversité direction
A38: 35 | B38: CONSOL_CR | C38: F7 | D38: Taux moyen GBP | E38: PQ_TAUX_CHANGE | F38: F7 | G38: =PQ_TAUX_CHANGE!F7 -> 1.152 | H38: Paramètre | I38: IAS 21 §39 | J38: 🔴 Critique | K38: Centraliser le taux dans PQ_TAUX_CHANGE
A39: 36 | B39: CONSOL_BILAN | C39: E6 | D39: Taux clôture GBP | E39: PQ_TAUX_CHANGE | F39: F6 | G39: =PQ_TAUX_CHANGE!F6 -> 1.165 | H39: Paramètre | I39: IAS 21 §23 | J39: 🔴 Critique | K39: Centraliser le taux dans PQ_TAUX_CHANGE
A40: 37 | B40: PQ_ELIMINATIONS | C40: I13 | D40: Total élim. ventes | E40: ELIM | F40: I13 | G40: =ELIM!I13 -> 0 | H40: Lien direct | I40: IFRS 10 | J40: 🔴 Critique | K40: Contrôle vs table ELIM manuelle
A41: 38 | B41: NOTES_IFRS | C41: C14 | D41: GW brut total | E41: ELIM | F41: D21 | G41: =ELIM!D21 -> 290000 | H41: Lien direct | I41: IFRS 3 | J41: 🟠 Important | K41: Note 3 – Goodwill
A42: 39 | B42: NOTES_IFRS | C42: C15 | D42: Dépréc. cumulée GW | E42: ELIM | F42: G21 | G42: =ELIM!G21 -> 14700 | H42: Lien direct | I42: IAS 36 | J42: 🟠 Important | K42: Note 3 – Test dépréciation
A43: 40 | B43: NOTES_IFRS | C43: C30 | D43: Obligation IAS 19 nette | E43: FR_ParentCo | F43: — | G43: =22400 -> 22400 | H43: Saisie | I43: IAS 19 | J43: 🟡 Standard | K43: Note 6 – Avantages personnel
A46: 📊 STATISTIQUES LIAISONS
A47: Total liaisons documentées | B47: Critiques 🔴 | C47: Importantes 🟠 | D47: Standard 🟡 | E47: Onglets interconnectés
A48: 40 | B48: 29 | C48: 7 | D48: 4 | E48: 7
A102: MODULE ESG – LIAISONS CARBONE / DIVERSITE / GOUVERNANCE (13 nouvelles)
A103: # | B103: Origine | C103: Cell_Origine | D103: Formule | E103: Destination | F103: Cell_Dest | G103: Type_Conv | H103: Norme | I103: Criticite | J103: Notes_ESG | K103: Liaison_Sens | L103: Commentaire
A104: 41 | B104: ESG_CARBONE | C104: B54
A107: MODULE ESG – NOUVELLES LIAISONS CARBONE / DIVERSITE / GOUVERNANCE
A108: Num | B108: Origine | C108: CellOrig | D108: Formule_Liaison | E108: Destination | F108: CellDest | G108: Type | H108: Norme | I108: Criticite | J108: Module | K108: Sens | L108: Note
A109: 41 | B109: ESG_CARBONE | C109: G (s3) | D109: Scope 1 groupe somme 5 entités | E109: DASHBOARD_ESG | F109: C12 | G109: SUM | H109: ESRS E1-6 §44a | I109: Rouge Critique | J109: ESG | K109: ESG->Dashboard | L109: Refresh PQ requis
A110: 42 | B110: ESG_CARBONE | C110: G (s3) | D110: Scope 2 groupe somme 5 entités | E110: DASHBOARD_ESG | F110: C13 | G110: SUM | H110: ESRS E1-6 §44b | I110: Rouge Critique | J110: ESG | K110: ESG->Dashboard | L110: Refresh PQ requis
A111: 43 | B111: ESG_CARBONE | C111: G (s3) | D111: Scope 3 groupe somme 5 entités | E111: DASHBOARD_ESG | F111: C14 | G111: SUM | H111: ESRS E1-6 §44c | I111: Rouge Critique | J111: ESG | K111: ESG->Dashboard | L111: Refresh PQ requis
A112: 44 | B112: ESG_CARBONE | C112: H57 | D112: Intensite: Scope12 / (CA/1000) | E112: DASHBOARD_FIN | F112: H25 | G112: RATIO | H112: ESRS E1-6 §55 | I112: Rouge Critique | J112: ESG | K112: ESG->DashFin | L112: Lié CONSOL_CR!K7
A113: 45 | B113: ESG_CARBONE | C113: G71 | D113: Cout carbone: S123 * PrixInterne/1000 | E113: DASHBOARD_FIN | F113: C42 | G113: CALC | H113: IFRS 18 §112 MPM | I113: Rouge Critique | J113: ESG | K113: ESG->DashFin | L113: MPM obligatoire si >20% EBIT
A114: 46 | B114: ESG_CARBONE | C114: H71 | D114: % EBIT: CoutCarbone / EBIT consolidé | E114: DASHBOARD_FIN | F114: D42 | G114: RATIO | H114: IFRS 18 §112 MPM | I114: Rouge Critique | J114: ESG | K114: ESG->DashFin | L114: Déclencheur MPM si >20%
A115: 47 | B115: ESG_DIVERSITE | C115: F10 | D115: % Femmes: ETP_Femmes / ETP_Total | E115: DASHBOARD_ESG | F115: C24 | G115: RATIO | H115: ESRS S1-9 §65 | I115: Orange Imp. | J115: ESG | K115: ESG->Dashboard | L115: Cible 50%
A116: 48 | B116: ESG_DIVERSITE | C116: I10 | D116: % Dir.Fem: FemmesDir / TotalDir | E116: DASHBOARD_ESG | F116: C25 | G116: RATIO | H116: ESRS S1-9 §65 | I116: Orange Imp. | J116: ESG | K116: ESG->Dashboard | L116: Loi Rixain: 40% en 2027
A117: 49 | B117: ESG_DIVERSITE | C117: B40 | D117: % Femmes CA: 6/15 CA membres | E117: DASHBOARD_ESG | F117: C33 | G117: RATIO | H117: ESRS G1-1 §29 | I117: Orange Imp. | J117: ESG | K117: ESG->Dashboard | L117: Obligation légale FR
A118: 50 | B118: ESG_DASHBOARD_LINK | C118: B9 | D118: Score global: E*40%+S*35%+G*25% | E118: DASHBOARD_ESG | F118: C8 | G118: W_AVG | H118: Score ESG pondéré | I118: Rouge Critique | J118: ESG | K118: ESG->Dashboard | L118: Base CSRD reporting
A119: 51 | B119: ESG_MAPPING | C119: K4:K32 | D119: 29 liaisons ESRS vers IFRS 18 documentées | E119: ESG_DASHBOARD_LINK | F119: Multi | G119: MAPPING | H119: ESRS x IFRS 18 | I119: Standard | J119: ESG | K119: Ref Table | L119: Référentiel croisé
A120: 52 | B120: ESG_DAX | C120: D (col) | D120: 30 mesures DAX ESG à copier Power Pivot | E120: Power Pivot | F120: Modele | G120: DAX | H120: ESRS E1/S1/G1 | I120: Rouge Critique | J120: ESG | K120: ESG->PowerPivot | L120: Copier groupe par groupe
A121: 53 | B121: CONSOL_CR | C121: K7 | D121: CA groupe denominateur intensite carbone | E121: ESG_CARBONE | F121: Section3 | G121: LINK | H121: ESRS E1-6 §55 | I121: Rouge Critique | J121: ESG | K121: Fin->ESG | L121: Recalcul auto

Sheet ESG_CARBONE
A1: 🌍 ESG_CARBONE – BILAN CARBONE CONSOLIDÉ · Scope 1 / 2 / 3 · Pondération par Entité · ESRS E1-6 / GHG Protocol
A2: ESRS E1-6 §44 : Émissions brutes Scope 1+2+3 obligatoires · GHG Protocol Corporate Standard · Unité : tCO₂eq · Base : GWP-100 AR6 GIEC
A4: SECTION 1 – FACTEURS D'ÉMISSION PAR ENTITÉ ET SOURCE (tCO₂eq / unité)
A5: EntitéGroupe | B5: Pays | C5: SourceÉnergie | D5: ScopeGHG | E5: FacteurEmission | F5: Unité | G5: FacteurPays_kgCO2/kWh | H5: TypeRéseau | I5: AnneeMiseAjour | J5: Source
A6: FR_ParentCo | B6: France | C6: Électricité réseau | D6: Scope 2 (marché) | E6: 0.0569 | F6: tCO₂/MWh | G6: 0.0569 | H6: Mix FR (nucléaire 70%) | I6: 2025 | J6: AIE / RTE
A7: FR_ParentCo | B7: France | C7: Gaz naturel | D7: Scope 1 | E7: 0.201 | F7: tCO₂/MWh | G7: 0.201 | H7: Combustion directe | I7: 2025 | J7: ADEME FE 2025
A8: FR_ParentCo | B8: France | C8: Fioul/gasoil | D8: Scope 1 | E8: 0.2637 | F8: tCO₂/L | G8: 0.2637 | H8: Combustion directe | I8: 2025 | J8: ADEME FE 2025
A9: FR_ParentCo | B9: France | C9: Flotte véhicules | D9: Scope 1 | E9: 0.1932 | F9: tCO₂/L | G9: 0.1932 | H9: Combustion directe mobile | I9: 2025 | J9: ADEME FE 2025
A10: FR_ParentCo | B10: France | C10: Achats & supply chain | D10: Scope 3 cat.1 | E10: 0.42 | F10: tCO₂/k€ achat | G10: 0.42 | H10: Facteur monétaire | I10: 2025 | J10: Ecoinvent 3.9
A11: DE_Filiale | B11: Allemagne | C11: Électricité réseau | D11: Scope 2 (marché) | E11: 0.394 | F11: tCO₂/MWh | G11: 0.394 | H11: Mix DE (charbon+gaz) | I11: 2025 | J11: UBA Allemagne
A12: DE_Filiale | B12: Allemagne | C12: Gaz naturel | D12: Scope 1 | E12: 0.201 | F12: tCO₂/MWh | G12: 0.201 | H12: Combustion directe | I12: 2025 | J12: IPCC AR6
A13: DE_Filiale | B13: Allemagne | C13: Process industriel | D13: Scope 1 | E13: 1.85 | F13: tCO₂/t produit | G13: 1.85 | H13: Émissions procédé | I13: 2025 | J13: BREF Industrie
A14: DE_Filiale | B14: Allemagne | C14: Achats & supply chain | D14: Scope 3 cat.1 | E14: 0.58 | F14: tCO₂/k€ achat | G14: 0.58 | H14: Industrie manufacturière | I14: 2025 | J14: Ecoinvent 3.9
A15: UK_Filiale | B15: Royaume-Uni | C15: Électricité réseau | D15: Scope 2 (marché) | E15: 0.207 | F15: tCO₂/MWh | G15: 0.207 | H15: Mix UK (éolien+gaz) | I15: 2025 | J15: DESNZ UK
A16: UK_Filiale | B16: Royaume-Uni | C16: Gaz naturel | D16: Scope 1 | E16: 0.203 | F16: tCO₂/MWh | G16: 0.203 | H16: Combustion directe | I16: 2025 | J16: IPCC AR6
A17: UK_Filiale | B17: Royaume-Uni | C17: Déplacements pro | D17: Scope 3 cat.6 | E17: 0.255 | F17: tCO₂/km | G17: 0.255 | H17: Transport aérien long-courrier | I17: 2025 | J17: DEFRA 2025
... A25: SG_Filiale | B25: Singapour | C25: Déplacements régionaux | D25: Scope 3 cat.6 | E25: 0.182 | F25: tCO₂/km | G25: 0.182 | H25: Transport aérien régional | I25: 2025 | J25: ICAO Carbon Calculator
A28: SECTION 2 – ÉMISSIONS BRUTES PAR ENTITÉ, PAR SCOPE ET PAR MOIS 2025 (tCO₂eq)
A29: Entité | B29: Scope | C29: T1-2025 | D29: T2-2025 | E29: T3-2025 | F29: T4-2025 | G29: TOTAL_2025 | H29: TOTAL_2024 | I29: Δ % | J29: Objectif_2030 | K29: Écart_Obj | L29: % Atteinte | M29: Intensité (tCO₂/M€ CA) | N29: Intensité N-1 | O29: Pondération Groupe | P29: Note ESRS | Q29: Vérif. Tiers | R29: Statut
A30: FR_ParentCo | B30: Scope 1 (direct) | C30: 3050 | D30: 3120 | E30: 3180 | F30: 3050 | G30: =SUM(C30:F30) -> 12400 | H30: 13200 | I30: =IFERROR((G30-H30)/ABS(H30),"") -> -0.060606061 | J30: 7800 | K30: =G30-J30 -> 4600 | L30: =IFERROR(G30/J30,"") -> 1.5897436 | M30: =IFERROR(G30/(CONSOL_CR!D7/1000),"") -> 43.508772 | O30: =IFERROR(CONSOL_CR!D7/CONSOL_CR!K7,"") -> 0.34880519 | P30: E1-6 §44a | Q30: ✅ Vérifié tiers | R30: Conforme
A31: FR_ParentCo | B31: Scope 2 (énergie – marché) | C31: 2180 | D31: 2200 | E31: 2250 | F31: 2270 | G31: =SUM(C31:F31) -> 8900 | H31: 9600 | I31: =IFERROR((G31-H31)/ABS(H31),"") -> -0.072916667 | J31: 5000 | K31: =G31-J31 -> 3900 | L31: =IFERROR(G31/J31,"") -> 1.78 | M31: =IFERROR(G31/(CONSOL_CR!D7/1000),"") -> 31.22807 | O31: =IFERROR(CONSOL_CR!D7/CONSOL_CR!K7,"") -> 0.34880519 | P31: E1-6 §44b | Q31: ✅ Vérifié tiers | R31: Conforme
A32: FR_ParentCo | B32: Scope 3 (chaîne valeur) | C32: 20500 | D32: 21800 | E32: 22200 | F32: 20500 | G32: =SUM(C32:F32) -> 85000 | H32: 92000 | I32: =IFERROR((G32-H32)/ABS(H32),"") -> -0.076086957 | J32: 55000 | K32: =G32-J32 -> 30000 | L32: =IFERROR(G32/J32,"") -> 1.5454545 | M32: =IFERROR(G32/(CONSOL_CR!D7/1000),"") -> 298.24561 | O32: =IFERROR(CONSOL_CR!D7/CONSOL_CR!K7,"") -> 0.34880519 | P32: E1-6 §44c | Q32: 🔄 Auto-déclaré | R32: À vérifier
A33: DE_Filiale | B33: Scope 1 (direct) | C33: 7200 | D33: 7350 | E33: 7480 | F33: 7570 | G33: =SUM(C33:F33) -> 29600 | H33: 30200 | I33: =IFERROR((G33-H33)/ABS(H33),"") -> -0.01986755 | J33: 18000 | K33: =G33-J33 -> 11600 | L33: =IFERROR(G33/J33,"") -> 1.6444444 | M33: =IFERROR(G33/(CONSOL_CR!E7/1000),"") -> 176.19048 | O33: =IFERROR(CONSOL_CR!E7/CONSOL_CR!K7,"") -> 0.20561148 | P33: E1-6 §44a | Q33: ✅ Vérifié tiers | R33: Conforme
A34: DE_Filiale | B34: Scope 2 (énergie – marché) | C34: 3800 | D34: 3920 | E34: 4010 | F34: 3870 | G34: =SUM(C34:F34) -> 15600 | H34: 16400 | I34: =IFERROR((G34-H34)/ABS(H34),"") -> -0.048780488 | J34: 9000 | K34: =G34-J34 -> 6600 | L34: =IFERROR(G34/J34,"") -> 1.7333333 | M34: =IFERROR(G34/(CONSOL_CR!E7/1000),"") -> 92.857143 | O34: =IFERROR(CONSOL_CR!E7/CONSOL_CR!K7,"") -> 0.20561148 | P34: E1-6 §44b | Q34: ✅ Vérifié tiers | R34: Conforme
A35: DE_Filiale | B35: Scope 3 (chaîne valeur) | C35: 34500 | D35: 36200 | E35: 37100 | F35: 34200 | G35: =SUM(C35:F35) -> 142000 | H35: 152000 | I35: =IFERROR((G35-H35)/ABS(H35),"") -> -0.065789474 | J35: 85000 | K35: =G35-J35 -> 57000 | L35: =IFERROR(G35/J35,"") -> 1.6705882 | M35: =IFERROR(G35/(CONSOL_CR!E7/1000),"") -> 845.2381 | O35: =IFERROR(CONSOL_CR!E7/CONSOL_CR!K7,"") -> 0.20561148 | P35: E1-6 §44c | Q35: 🔄 Auto-déclaré | R35: À vérifier
A36: UK_Filiale | B36: Scope 1 (direct) | C36: 1980 | D36: 2020 | E36: 2050 | F36: 2150 | G36: =SUM(C36:F36) -> 8200 | H36: 8600 | I36: =IFERROR((G36-H36)/ABS(H36),"") -> -0.046511628 | J36: 5000 | K36: =G36-J36 -> 3200 | L36: =IFERROR(G36/J36,"") -> 1.64 | M36: =IFERROR(G36/(CONSOL_CR!F7/1000),"") -> 50.127152 | O36: =IFERROR(CONSOL_CR!F7/CONSOL_CR!K7,"") -> 0.20020684 | P36: E1-6 §44a | Q36: ✅ Vérifié tiers | R36: Conforme
A37: UK_Filiale | B37: Scope 2 (énergie – marché) | C37: 1520 | D37: 1580 | E37: 1600 | F37: 1400 | G37: =SUM(C37:F37) -> 6100 | H37: 6500 | I37: =IFERROR((G37-H37)/ABS(H37),"") -> -0.061538462 | J37: 3500 | K37: =G37-J37 -> 2600 | L37: =IFERROR(G37/J37,"") -> 1.7428571 | M37: =IFERROR(G37/(CONSOL_CR!F7/1000),"") -> 37.28971 | O37: =IFERROR(CONSOL_CR!F7/CONSOL_CR!K7,"") -> 0.20020684 | P37: E1-6 §44b | Q37: ✅ Vérifié tiers | R37: Conforme
A38: UK_Filiale | B38: Scope 3 (chaîne valeur) | C38: 15200 | D38: 15800 | E38: 16100 | F38: 14900 | G38: =SUM(C38:F38) -> 62000 | H38: 64000 | I38: =IFERROR((G38-H38)/ABS(H38),"") -> -0.03125 | J38: 35000 | K38: =G38-J38 -> 27000 | L38: =IFERROR(G38/J38,"") -> 1.7714286 | M38: =IFERROR(G38/(CONSOL_CR!F7/1000),"") -> 379.01017 | O38: =IFERROR(CONSOL_CR!F7/CONSOL_CR!K7,"") -> 0.20020684 | P38: E1-6 §44c | Q38: 🔄 Auto-déclaré | R38: À vérifier
A39: US_Filiale | B39: Scope 1 (direct) | C39: 4620 | D39: 4750 | E39: 4830 | F39: 4700 | G39: =SUM(C39:F39) -> 18900 | H39: 19800 | I39: =IFERROR((G39-H39)/ABS(H39),"") -> -0.045454545 | J39: 11000 | K39: =G39-J39 -> 7900 | L39: =IFERROR(G39/J39,"") -> 1.7181818 | M39: =IFERROR(G39/(CONSOL_CR!G7/1000),"") -> 104.7817 | O39: =IFERROR(CONSOL_CR!G7/CONSOL_CR!K7,"") -> 0.22075697 | P39: E1-6 §44a | Q39: ✅ Vérifié tiers | R39: Conforme
A40: US_Filiale | B40: Scope 2 (énergie – marché) | C40: 3480 | D40: 3550 | E40: 3620 | F40: 3450 | G40: =SUM(C40:F40) -> 14100 | H40: 14700 | I40: =IFERROR((G40-H40)/ABS(H40),"") -> -0.040816327 | J40: 8000 | K40: =G40-J40 -> 6100 | L40: =IFERROR(G40/J40,"") -> 1.7625 | M40: =IFERROR(G40/(CONSOL_CR!G7/1000),"") -> 78.170478 | O40: =IFERROR(CONSOL_CR!G7/CONSOL_CR!K7,"") -> 0.22075697 | P40: E1-6 §44b | Q40: ✅ Vérifié tiers | R40: Conforme
A41: US_Filiale | B41: Scope 3 (chaîne valeur) | C41: 47500 | D41: 48200 | E41: 49100 | F41: 50200 | G41: =SUM(C41:F41) -> 195000 | H41: 202000 | I41: =IFERROR((G41-H41)/ABS(H41),"") -> -0.034653465 | J41: 110000 | K41: =G41-J41 -> 85000 | L41: =IFERROR(G41/J41,"") -> 1.7727273 | M41: =IFERROR(G41/(CONSOL_CR!G7/1000),"") -> 1081.0811 | O41: =IFERROR(CONSOL_CR!G7/CONSOL_CR!K7,"") -> 0.22075697 | P41: E1-6 §44c | Q41: 🔄 Auto-déclaré | R41: À vérifier
A42: SG_Filiale | B42: Scope 1 (direct) | C42: 1340 | D42: 1380 | E42: 1400 | F42: 1280 | G42: =SUM(C42:F42) -> 5400 | H42: 5800 | I42: =IFERROR((G42-H42)/ABS(H42),"") -> -0.068965517 | J42: 3200 | K42: =G42-J42 -> 2200 | L42: =IFERROR(G42/J42,"") -> 1.6875 | M42: =IFERROR(G42/(CONSOL_CR!H7/1000),"") -> 89.976006 | O42: =IFERROR(CONSOL_CR!H7/CONSOL_CR!K7,"") -> 0.073452253 | P42: E1-6 §44a | Q42: ✅ Vérifié tiers | R42: Conforme
A43: SG_Filiale | B43: Scope 2 (énergie – marché) | C43: 940 | D43: 980 | E43: 1010 | F43: 870 | G43: =SUM(C43:F43) -> 3800 | H43: 4100 | I43: =IFERROR((G43-H43)/ABS(H43),"") -> -0.073170732 | J43: 2000 | K43: =G43-J43 -> 1800 | L43: =IFERROR(G43/J43,"") -> 1.9 | M43: =IFERROR(G43/(CONSOL_CR!H7/1000),"") -> 63.316449 | O43: =IFERROR(CONSOL_CR!H7/CONSOL_CR!K7,"") -> 0.073452253 | P43: E1-6 §44b | Q43: ✅ Vérifié tiers | R43: Conforme
A44: SG_Filiale | B44: Scope 3 (chaîne valeur) | C44: 7000 | D44: 7200 | E44: 7500 | F44: 6300 | G44: =SUM(C44:F44) -> 28000 | H44: 28000 | I44: =IFERROR((G44-H44)/ABS(H44),"") -> 0 | J44: 15000 | K44: =G44-J44 -> 13000 | L44: =IFERROR(G44/J44,"") -> 1.8666667 | M44: =IFERROR(G44/(CONSOL_CR!H7/1000),"") -> 466.54226 | O44: =IFERROR(CONSOL_CR!H7/CONSOL_CR!K7,"") -> 0.073452253 | P44: E1-6 §44c | Q44: 🔄 Auto-déclaré | R44: À vérifier
A47: SECTION 3 – CONSOLIDATION GROUPE : AGRÉGATS PAR SCOPE + PONDÉRATION
A48: Scope | B48: Groupe_2025 (tCO₂eq) | C48: Groupe_2024 | D48: Δ % | E48: Objectif_2030 | F48: Écart_Obj | G48: % Atteinte | H48: Intensité Groupe | I48: Benchmark Secteur | J48: vs Benchmark | K48: Part Scope (%) | L48: Norme ESRS
A49: Scope 1 (direct) | B49: =G30+G33+G36+G39+G42 -> 74500 | C49: 116800 | D49: =IFERROR((B49-C49)/ABS(C49),"") -> -0.36215753 | E49: 54000 | F49: =B49-E49 -> 20500 | G49: =IFERROR(B49/E49,"") -> 1.3796296 | H49: =IFERROR(B49/(CONSOL_CR!K7/1000),"") -> 91.1789 | I49: 145 | J49: =IFERROR(H49/I49,"") -> 0.62882 | K49: =IFERROR(B49/SUM(B49:B51),"") -> 0.11732283 | L49: E1-6 §44a
A50: Scope 2 (énergie – marché) | B50: =G31+G34+G37+G40+G43 -> 48500 | C50: 51200 | D50: =IFERROR((B50-C50)/ABS(C50),"") -> -0.052734375 | E50: 27500 | F50: =B50-E50 -> 21000 | G50: =IFERROR(B50/E50,"") -> 1.7636364 | H50: =IFERROR(B50/(CONSOL_CR!K7/1000),"") -> 59.358076 | I50: 82 | J50: =IFERROR(H50/I50,"") -> 0.72387898 | K50: =IFERROR(B50/SUM(B49:B51),"") -> 0.076377953 | L50: E1-6 §44b
A51: Scope 3 (chaîne valeur) | B51: =G32+G35+G38+G41+G44 -> 512000 | C51: 538000 | D51: =IFERROR((B51-C51)/ABS(C51),"") -> -0.048327138 | E51: 300000 | F51: =B51-E51 -> 212000 | G51: =IFERROR(B51/E51,"") -> 1.7066667 | H51: =IFERROR(B51/(CONSOL_CR!K7/1000),"") -> 626.62546 | I51: 680 | J51: =IFERROR(H51/I51,"") -> 0.92150803 | K51: =IFERROR(B51/SUM(B49:B51),"") -> 0.80629921 | L51: E1-6 §44c
A52: 🌍 TOTAL Scope 1+2+3 (tCO₂eq) | B52: =SUM(B49:B51) -> 635000 | C52: 706000 | D52: =IFERROR((B52-C52)/ABS(C52),"") -> -0.10056657 | E52: 381500 | F52: =B52-E52 -> 253500 | G52: =IFERROR(B52/E52,"") -> 1.6644823 | H52: =IFERROR(B52/(CONSOL_CR!K7/1000),"") -> 777.16244
A55: SECTION 4 – PRIX INTERNE DU CARBONE (CARBON PRICING) · Impact Financier Consolidé
A56: Prix interne carbone (€/tCO₂eq) : | B56: 35 | C56: €/tCO₂eq – Modifier ce paramètre pour le scénario de tarification carbone
A57: Entité | B57: Scope 1+2 (tCO₂eq) | C57: Scope 3 (tCO₂eq) | D57: Total (tCO₂eq) | E57: Coût Carbone S1+2 (k€) | F57: Coût Carbone S3 (k€) | G57: Coût Total Carbone (k€)
A58: FR_ParentCo | B58: =G30+G31 -> 21300 | C58: =G32 -> 85000 | D58: =B58+C58 -> 106300 | E58: =ROUND(B58*B56/1000,1) -> 745.5 | F58: =ROUND(C58*B56/1000,1) -> 2975 | G58: =E58+F58 -> 3720.5
A59: DE_Filiale | B59: =G33+G34 -> 45200 | C59: =G35 -> 142000 | D59: =B59+C59 -> 187200 | E59: =ROUND(B59*B56/1000,1) -> 1582 | F59: =ROUND(C59*B56/1000,1) -> 4970 | G59: =E59+F59 -> 6552
A60: UK_Filiale | B60: =G36+G37 -> 14300 | C60: =G38 -> 62000 | D60: =B60+C60 -> 76300 | E60: =ROUND(B60*B56/1000,1) -> 500.5 | F60: =ROUND(C60*B56/1000,1) -> 2170 | G60: =E60+F60 -> 2670.5
A61: US_Filiale | B61: =G39+G40 -> 33000 | C61: =G41 -> 195000 | D61: =B61+C61 -> 228000 | E61: =ROUND(B61*B56/1000,1) -> 1155 | F61: =ROUND(C61*B56/1000,1) -> 6825 | G61: =E61+F61 -> 7980
A62: SG_Filiale | B62: =G42+G43 -> 9200 | C62: =G44 -> 28000 | D62: =B62+C62 -> 37200 | E62: =ROUND(B62*B56/1000,1) -> 322 | F62: =ROUND(C62*B56/1000,1) -> 980 | G62: =E62+F62 -> 1302
A63: TOTAL GROUPE | B63: =SUM(B58:B62) -> 123000 | C63: =SUM(C58:C62) -> 512000 | D63: =SUM(D58:D62) -> 635000 | E63: =SUM(E58:E62) -> 4305 | F63: =SUM(F58:F62) -> 17920 | G63: =SUM(G58:G62) -> 22225 | H63: =IFERROR(G63/(CONSOL_CR!K14/1000),"") -> 144.50773 | I63: % EBIT consolidé – impact si régulation carbone appliquée

Sheet ESG_DIVERSITE
A1: 👥 ESG_DIVERSITE – KPIs DIVERSITÉ, PARITÉ & GOUVERNANCE · ESRS S1 / G1 · Toutes Entités · 2025
A3: SECTION 1 – EFFECTIFS & PARITÉ (ESRS S1-6 / S1-9)
A4: Entité | B4: ETP_Total | C4: ETP_CDI | D4: Pct_CDI | E4: ETP_Femmes | F4: Pct_Femmes | G4: ETP_Dirigeants | H4: Femmes_Dir | I4: Pct_Fem_Dir | J4: Obj_FemDir_2028 | K4: Écart_Obj | L4: Recrutements | M4: Taux_Turnover | N4: Age_Moyen | O4: ESRS_Ref
A5: FR_ParentCo | B5: 1850 | C5: 1683 | D5: =IFERROR(C5/B5,"") -> 0.90972973 | E5: 795 | F5: =IFERROR(E5/B5,"") -> 0.42972973 | G5: 85 | H5: 32 | I5: =IFERROR(H5/G5,"") -> 0.37647059 | J5: 0.45 | K5: =I5-J5 -> -0.073529412 | L5: 245 | M5: =IFERROR(L5/B5,"") -> 0.13243243 | N5: 43.2 | O5: S1-6,S1-9
A6: DE_Filiale | B6: 2640 | C6: 2323 | D6: =IFERROR(C6/B6,"") -> 0.87992424 | E6: 950 | F6: =IFERROR(E6/B6,"") -> 0.35984848 | G6: 120 | H6: 34 | I6: =IFERROR(H6/G6,"") -> 0.28333333 | J6: 0.4 | K6: =I6-J6 -> -0.11666667 | L6: 310 | M6: =IFERROR(L6/B6,"") -> 0.11742424 | N6: 41.8 | O6: S1-6,S1-9
A7: UK_Filiale | B7: 980 | C7: 833 | D7: =IFERROR(C7/B7,"") -> 0.85 | E7: 470 | F7: =IFERROR(E7/B7,"") -> 0.47959184 | G7: 62 | H7: 26 | I7: =IFERROR(H7/G7,"") -> 0.41935484 | J7: 0.45 | K7: =I7-J7 -> -0.030645161 | L7: 142 | M7: =IFERROR(L7/B7,"") -> 0.14489796 | N7: 38.6 | O7: S1-6,S1-9
A8: US_Filiale | B8: 1420 | C8: 1123 | D8: =IFERROR(C8/B8,"") -> 0.79084507 | E8: 625 | F8: =IFERROR(E8/B8,"") -> 0.44014085 | G8: 78 | H8: 28 | I8: =IFERROR(H8/G8,"") -> 0.35897436 | J8: 0.4 | K8: =I8-J8 -> -0.041025641 | L8: 198 | M8: =IFERROR(L8/B8,"") -> 0.13943662 | N8: 37.4 | O8: S1-6,S1-9
A9: SG_Filiale | B9: 380 | C9: 357 | D9: =IFERROR(C9/B9,"") -> 0.93947368 | E9: 198 | F9: =IFERROR(E9/B9,"") -> 0.52105263 | G9: 28 | H9: 13 | I9: =IFERROR(H9/G9,"") -> 0.46428571 | J9: 0.45 | K9: =I9-J9 -> 0.014285714 | L9: 58 | M9: =IFERROR(L9/B9,"") -> 0.15263158 | N9: 34.8 | O9: S1-6,S1-9
A10: TOTAL GROUPE | B10: =SUM(B5:B9) -> 7270 | C10: =SUM(C5:C9) -> 6319 | E10: =SUM(E5:E9) -> 3038 | F10: =IFERROR(E10/B10,"") -> 0.41788171 | G10: =SUM(G5:G9) -> 373 | H10: =SUM(H5:H9) -> 133 | I10: =IFERROR(H10/G10,"") -> 0.35656836 | L10: =SUM(L5:L9) -> 953 | M10: =IFERROR(L10/B10,"") -> 0.13108666
A13: SECTION 2 – RÉMUNÉRATION ÉQUITABLE (ESRS S1-16) · Écart salarial H/F · Pay ratio
A14: Entité | B14: Devise | C14: SalMéd_F | D14: SalMéd_H | E14: Écart_H/F | F14: Obj_2027 | G14: Statut | H14: SalDir_Max | I14: SalMéd_Global | J14: PayRatio | K14: ESRS_Ref
A15: FR_ParentCo | B15: EUR | C15: 48200 | D15: 55100 | E15: =IFERROR((C15-D15)/D15,"") -> -0.12522686 | F15: -0.08 | G15: =IF(E15>=F15,"✅ Atteint","⚠️ Sous objectif") -> ⚠️ Sous objectif | H15: 285000 | I15: 52400 | J15: =IFERROR(H15/I15,"") -> 5.4389313 | K15: S1-16
A16: DE_Filiale | B16: EUR | C16: 44800 | D16: 52600 | E16: =IFERROR((C16-D16)/D16,"") -> -0.14828897 | F16: -0.08 | G16: =IF(E16>=F16,"✅ Atteint","⚠️ Sous objectif") -> ⚠️ Sous objectif | H16: 320000 | I16: 48200 | J16: =IFERROR(H16/I16,"") -> 6.6390041 | K16: S1-16
A17: UK_Filiale | B17: GBP | C17: 58200 | D17: 63100 | E17: =IFERROR((C17-D17)/D17,"") -> -0.077654517 | F17: -0.08 | G17: =IF(E17>=F17,"✅ Atteint","⚠️ Sous objectif") -> ✅ Atteint | H17: 410000 | I17: 60400 | J17: =IFERROR(H17/I17,"") -> 6.7880795 | K17: S1-16
A18: US_Filiale | B18: USD | C18: 62400 | D18: 76200 | E18: =IFERROR((C18-D18)/D18,"") -> -0.18110236 | F18: -0.08 | G18: =IF(E18>=F18,"✅ Atteint","⚠️ Sous objectif") -> ⚠️ Sous objectif | H18: 520000 | I18: 71200 | J18: =IFERROR(H18/I18,"") -> 7.3033708 | K18: S1-16
A19: SG_Filiale | B19: SGD | C19: 52800 | D19: 56400 | E19: =IFERROR((C19-D19)/D19,"") -> -0.063829787 | F19: -0.05 | G19: =IF(E19>=F19,"✅ Atteint","⚠️ Sous objectif") -> ⚠️ Sous objectif | H19: 380000 | I19: 54600 | J19: =IFERROR(H19/I19,"") -> 6.959707 | K19: S1-16
A23: SECTION 3 – SANTÉ, SÉCURITÉ & FORMATION (ESRS S1-11 / S1-13)
A24: Entité | B24: TRIR_2025 | C24: TRIR_2024 | D24: Obj_2026 | E24: Δ TRIR | F24: Accidents_Mortels | G24: Maladies_Pro | H24: H_Form/ETP | I24: Budget_Form_k€ | J24: Pct_ETP_Formés | K24: Certif_SST | L24: ESRS
A25: FR_ParentCo | B25: 2.4 | C25: 3.1 | D25: 2 | E25: =B25-C25 -> -0.7 | F25: 0 | G25: 2 | H25: 42 | I25: 680 | J25: 0.82 | K25: ISO 45001 | L25: S1-11
A26: DE_Filiale | B26: 3.8 | C26: 4.2 | D26: 2.5 | E26: =B26-C26 -> -0.4 | F26: 0 | G26: 5 | H26: 38 | I26: 920 | J26: 0.79 | K26: OHSAS | L26: S1-11
A27: UK_Filiale | B27: 1.6 | C27: 2 | D27: 1.2 | E27: =B27-C27 -> -0.4 | F27: 0 | G27: 1 | H27: 56 | I27: 520 | J27: 0.85 | K27: HSE UK | L27: S1-11
A28: US_Filiale | B28: 4.2 | C28: 4.8 | D28: 3 | E28: =B28-C28 -> -0.6 | F28: 0 | G28: 3 | H28: 35 | I28: 580 | J28: 0.76 | K28: OSHA | L28: S1-11
A29: SG_Filiale | B29: 1.1 | C29: 1.5 | D29: 0.8 | E29: =B29-C29 -> -0.4 | F29: 0 | G29: 0 | H29: 61 | I29: 185 | J29: 0.88 | K29: MOM SG | L29: S1-11
A33: SECTION 4 – GOUVERNANCE (ESRS G1) · CA · Éthique · Fournisseurs · Fiscalité
A34: Indicateur G1 | B34: Valeur 2025 | C34: Valeur 2024 | D34: Objectif / Benchmark
A35: Membres CA total | B35: 15 | C35: 15 | D35: 12-18 membres
A36: Femmes au CA | B36: 6 | C36: 5 | D36: ≥ 6 (40% – Loi Rixain 2027)
A37: % Femmes au CA | B37: =B36/B35 -> 0.4 | C37: 0.33 | D37: 0.4
A38: Indépendants au CA (%) | B38: =9/B35 -> 0.6 | C38: 0.53 | D38: > 50% AFEP-MEDEF
A39: Nationalités au CA | B39: 9 | C39: 8 | D39: > 5
A40: Réunions RSE/an | B40: 4 | C40: 3 | D40: > 3
A41: Incidents corruption | B41: 2 | C41: 1 | D41: 0 (tolérance zéro)
A42: Alertes whistleblowing | B42: 18 | C42: 14 | D42: 100% traitées
A43: Délai moyen traitement (j) | B43: 28 | C43: 34 | D43: < 30 jours
A44: Fournisseurs évalués ESG | B44: =0.68 -> 0.68 | C44: 0.65 | D44: 80% en 2026
A45: Rapport ESG publié | B45: ✅ Oui | C45: ✅ Oui | D45: Obligatoire CSRD
A46: Assurance externe ESG | B46: ✅ Limitée | C46: ❌ Non | D46: Raisonnable en 2026
A47: ETR (lié CONSOL_CR) | B47: =CONSOL_CR!C41 -> 0.10049261 | C47: 0.298 | D47: ≈ 25% taux légal

Sheet ESG_MAPPING
A1: 🗺️ ESG_MAPPING – TABLE DE CORRESPONDANCE ESRS → REPORTING CONSOLIDÉ · KPIs ESG × États Financiers
A2: Ce tableau est la clé de liaison entre données ESG brutes et reporting financier consolidé. Utilisé par Power Query et les mesures DAX pour agréger ESG × IFRS 18.
A3: IDIndicateur | B3: PilierESG | C3: StandardESRS | D3: Paragraphe | E3: IndicateurLabel | F3: TypeDonnée | G3: OngletSource | H3: CelluleSource | I3: OngletCible | J3: CelluleCible | K3: FormulaLiaison | L3: CatIFRS18_Lié
